Workbook
Name _Hlk152162896: '指定共同生活援助（共通）'!$B$67
Name _Hlk152264793: '指定共同生活援助（共通）'!$B$70
Name _Hlk152162896: '指定共同生活援助（日中サービス支援型）'!#REF!
Name _Hlk152264793: '指定共同生活援助（日中サービス支援型）'!#REF!
Name _Hlk152162896: '指定共同生活援助（外部サービス利用型）'!#REF!
Name _Hlk152264793: '指定共同生活援助（外部サービス利用型）'!#REF!
Name _Hlk152162896: '指定共同生活援助（訓練等給付費の算定）'!#REF!
Name _Hlk152264793: '指定共同生活援助（訓練等給付費の算定）'!#REF!

Sheet 要確認一覧
A1: シート名 | B1: 確認項目（大区分） | C1: 確認事項（抜粋） | D1: 判定
A2: 指定共同生活援助（共通） | B2: （指定障害福祉サービス事業者の一般原則） | C2: （１）指定共同生活援助事業者は、利用者の意向、適性、障害の特性その他の事情を踏まえた計画（個別支援計画）を作成し、これに基づき利用者に対して指定共同生活援助を提 | D2: ='指定共同生活援助（共通）'!G5
A3: 指定共同生活援助（共通） | C3: （２）指定共同生活援助事業者は、利用者の意思及び人格を尊重して、常に当該利用者の立場に立った指定共同生活援助の提供に努めているか。 | D3: ='指定共同生活援助（共通）'!G6
A4: 指定共同生活援助（共通） | C4: （３）指定共同生活援助事業者は、利用者の人権の擁護、虐待の防止等のため、必要な体制の整備を行うとともに、その従業者に対し、研修を実施する等の措置を講じているか。 | D4: ='指定共同生活援助（共通）'!G7
A5: 指定共同生活援助（共通） | C5: （４）指定共同生活援助の事業は、利用者が地域において共同して自立した日常生活又は社会生活を営むことができるよう、当該利用者の身体及び精神の状況並びにその置かれて | D5: ='指定共同生活援助（共通）'!G8
A6: 指定共同生活援助（共通） | B6: １ 指定共同生活援助事業所の従業者の員数 | C6: 指定共同生活援助事業所に置くべき従業者及びその員数は、次のとおりになっているか。 | D6: ='指定共同生活援助（共通）'!G11
A7: 指定共同生活援助（共通） | B7: （１）世話人 | C7: 指定共同生活援助事業所ごとに、常勤換算方法で、利用者の数を6で除した数以上となっているか。 | D7: ='指定共同生活援助（共通）'!G12
A8: 指定共同生活援助（共通） | B8: （２）生活支援員 | C8: 指定共同生活援助事業所ごとに、常勤換算方法で、次の①から④までに掲げる数の合計数以上となっているか。 ① 障害支援区分に係る市町村審査会による審査及び判定の基準 | D8: ='指定共同生活援助（共通）'!G13
A9: 指定共同生活援助（共通） | B9: （３）サービス管理責任者 | C9: 指定共同生活援助事業所ごとに、①又は②に掲げる利用者の数の区分に応じ、それぞれ①又は②に掲げる数となっているか。 ① 利用者の数が30以下 1以上 ② 利用者の | D9: ='指定共同生活援助（共通）'!G14
A10: 指定共同生活援助（共通） | B10: （４）利用者数の算定 | C10: (1)から(3)の利用者の数は、前年度の平均値となっているか。ただし、新規に指定を受ける場合は、適切な推定数により算定されているか。 | D10: ='指定共同生活援助（共通）'!G15
A11: 指定共同生活援助（共通） | B11: （５）職務の専従 | C11: (1)から(3)に規定する指定共同生活援助の従業者は､専ら当該指定共同生活援助事業所の職務に従事する者となっているか。 （ただし、利用者の支援に支障がない場合は | D11: ='指定共同生活援助（共通）'!G16
A12: 指定共同生活援助（共通） | B12: （６）管理者 | C12: ① 指定共同生活援助事業所ごとに専らその職務に従事する常勤の管理者を置いているか。 （ただし、指定共同生活援助事業所の管理上支障がない場合は、当該指定共同生活援 | D12: ='指定共同生活援助（共通）'!G17
A13: 指定共同生活援助（共通） | C13: ② 指定共同生活援助事業所の管理者は、適切な指定共同生活援助を提供するために必要な知識及び経験を有する者となっているか。 | D13: ='指定共同生活援助（共通）'!G18
A14: 指定共同生活援助（共通） | B14: 設備 | C14: ① 指定共同生活援助に係る共同生活住居は、住宅地又は住宅地と同程度に利用者の家族や地域住民との交流の機会が確保される地域にあり、かつ、入所により日中及び夜間を通 | D14: ='指定共同生活援助（共通）'!G21
A15: 指定共同生活援助（共通） | C15: ② 指定共同生活援助事業所は、1以上の共同生活住居（サテライト型住居を除く。以下この②、④から⑥までにおいて同じ。）を有するものとし、当該共同生活住居及びサテラ | D15: ='指定共同生活援助（共通）'!G22
A16: 指定共同生活援助（共通） | C16: ③ 共同生活住居の配置、構造及び設備は、利用者の特性に応じて工夫したものとなっているか。 | D16: ='指定共同生活援助（共通）'!G23
A17: 指定共同生活援助（共通） | C17: ④ 共同生活住居は、その入居定員は2人以上10人以下となっているか。 ただし、既存の建物を共同生活住居とする場合にあっては、当該共同生活住居の入居定員は2人以 | D17: ='指定共同生活援助（共通）'!G24
A18: 指定共同生活援助（共通） | C18: ⑤ 既存の建物を共同生活住居とした共同生活住居を改築する場合であって、都道府県知事が特に必要があると認めるときは、④の規定にかかわらず、当該共同生活住居の入居定 | D18: ='指定共同生活援助（共通）'!G25
A19: 指定共同生活援助（共通） | C19: ⑥ 共同生活住居は、１以上のユニットを有するほか、日常生活を営む上で必要な設備を設けているか。 | D19: ='指定共同生活援助（共通）'!G26
A20: 指定共同生活援助（共通） | C20: ⑦ ユニットの入居定員は、2人以上10人以下となっているか。 | D20: ='指定共同生活援助（共通）'!G27
A21: 指定共同生活援助（共通） | C21: ⑧ ユニットには、居室及び居室に近接して設けられる相互に交流を図ることができる設備を設けているか。その基準は次のとおりとなっているか。 ア １の居室の定員は、１ | D21: ='指定共同生活援助（共通）'!G28
A22: 指定共同生活援助（共通） | C22: ⑨ サテライト型住居の基準は、次のとおりとなっているか。 ア 入居定員を１人とすること。 イ 日常生活を営む上で必要な設備を設けること。 ウ 居室の面積は、収 | D22: ='指定共同生活援助（共通）'!G29
A23: 指定共同生活援助（共通） | C23: （経過措置） （１）平成18年厚生労働省令第171号（指定障害福祉サービス基準）の施行日（施行日）において現に入所施設又は病院の敷地内に存する建物を共同生活住居 | D23: ='指定共同生活援助（共通）'!G30
A24: 指定共同生活援助（共通） | C24: （２）指定共同生活援助事業者は、施行日において現に存する指定共同生活援助事業所において、指定共同生活援助の事業を行う場合には、当該事業所の共同生活住居（基本的な | D24: ='指定共同生活援助（共通）'!G31
A25: 指定共同生活援助（共通） | C25: （３）施行日において現に存する身体障害者福祉ホーム、精神障害者生活訓練施設、指定知的障害者通勤寮若しくは知的障害者福祉ホーム又は旧精神障害者福祉ホ－ム（基本的な | D25: ='指定共同生活援助（共通）'!G32
A26: 指定共同生活援助（共通） | B26: １ 内容及び手続の説明及び同意 | C26: （１）指定共同生活援助事業者は、支給決定障害者等が指定共同生活援助の利用の申込みを行ったときは、当該利用申込者に係る障害の特性に応じた適切な配慮をしつつ、当該利 | D26: ='指定共同生活援助（共通）'!G35
A27: 指定共同生活援助（共通） | C27: （２）指定共同生活援助事業者は、社会福祉法第77条の規定に基づき書面の交付を行う場合は、利用者の障害の特性に応じた適切な配慮をしているか。 | D27: ='指定共同生活援助（共通）'!G36
A28: 指定共同生活援助（共通） | B28: ２ 提供拒否の禁止 | C28: 指定共同生活援助事業者は、正当な理由がなく、指定共同生活援助の提供を拒んでいないか。 | D28: ='指定共同生活援助（共通）'!G37
A29: 指定共同生活援助（共通） | B29: ３ 連絡調整に対する協力 | C29: 指定共同生活援助事業者は、指定共同生活援助の利用について市町村又は一般相談支援事業若しくは特定相談支援事業を行う者が行う連絡調整に、できる限り協力しているか。 | D29: ='指定共同生活援助（共通）'!G38
A30: 指定共同生活援助（共通） | B30: ４ 受給資格の確認 | C30: 指定共同生活援助事業者は、指定共同生活援助の提供を求められた場合は、その者の提示する受給者証によって、支給決定の有無、支給決定の有効期間、支給量等を確かめている | D30: ='指定共同生活援助（共通）'!G39
A31: 指定共同生活援助（共通） | B31: ５ 訓練等給付費の支給の申請に係る援助 | C31: （１）指定共同生活援助事業者は、共同生活援助に係る支給決定を受けていない者から利用の申込みがあった場合は、その者の意向を踏まえて速やかに訓練等給付費の支給の申請 | D31: ='指定共同生活援助（共通）'!G40
A32: 指定共同生活援助（共通） | C32: （２）指定共同生活援助事業者は、共同生活援助に係る支給決定に通常要すべき標準的な期間を考慮し、支給決定の有効期間の終了に伴う訓練等給付費の支給申請について、必要 | D32: ='指定共同生活援助（共通）'!G41
A33: 指定共同生活援助（共通） | B33: ６ 心身の状況等の把握 | C33: 指定共同生活援助事業者は、指定共同生活援助の提供に当たっては、利用者の心身の状況、その置かれている環境、他の保健医療サービス又は福祉サービスの利用状況等の把握に | D33: ='指定共同生活援助（共通）'!G42
A34: 指定共同生活援助（共通） | B34: ７ 指定障害福祉サービス事業者等との連携等 | C34: （１）指定共同生活援助事業者は、指定共同生活援助を提供するに当たっては、地域及び家庭との結び付きを重視した運営を行い、市町村、他の指定障害福祉サービス事業者等そ | D34: ='指定共同生活援助（共通）'!G43
A35: 指定共同生活援助（共通） | C35: （２）指定共同生活援助事業者は、指定共同生活援助の提供の終了に際しては、利用者又はその家族に対して適切な援助を行うとともに、保健医療サービス又は福祉サービスを提 | D35: ='指定共同生活援助（共通）'!G44
A36: 指定共同生活援助（共通） | B36: ８ サービスの提供の記録 | C36: （１）指定共同生活援助事業者は、指定共同生活援助を提供した際は、当該指定共同生活援助の提供日、内容その他必要な事項を記録しているか。 | D36: ='指定共同生活援助（共通）'!G45
A37: 指定共同生活援助（共通） | C37: （２）指定共同生活援助事業者は、(1)の規定による記録に際しては、支給決定障害者等から指定共同生活援助を提供したことについて確認を受けているか。 | D37: ='指定共同生活援助（共通）'!G46
A38: 指定共同生活援助（共通） | B38: ９ 入退居 | C38: （１）指定共同生活援助は、共同生活住居への入居を必要とする利用者(入院治療を要する者を除く。)に提供されているか。 | D38: ='指定共同生活援助（共通）'!G47
A39: 指定共同生活援助（共通） | C39: （２）指定共同生活援助事業者は、利用申込者の入居に際しては、その者の心身の状況、生活歴、病歴等の把握に努めているか。 | D39: ='指定共同生活援助（共通）'!G48
A40: 指定共同生活援助（共通） | C40: （３）指定共同生活援助事業者は、利用者の退居の際は、利用者の希望を踏まえた上で、退居後の生活環境や援助の継続性に配慮し、退居に必要な援助を行い、又はこれに併せて | D40: ='指定共同生活援助（共通）'!G49
A41: 指定共同生活援助（共通） | C41: （４）指定共同生活援助事業者は、利用者の退居に際しては、利用者に対し、適切な援助を行うとともに、保健医療サービス又は福祉サービスを提供する者との密接な連携に努め | D41: ='指定共同生活援助（共通）'!G50
A42: 指定共同生活援助（共通） | B42: 10 入退居の記録の記載等 | C42: （１）指定共同生活援助事業者は、入居者の入居又は退居に際しては、当該指定共同生活援助事業者の名称、入居又は退居の年月日その他の必要な事項(受給者証記載事項）を利 | D42: ='指定共同生活援助（共通）'!G51
A43: 指定共同生活援助（共通） | C43: （２）指定共同生活援助事業者は、受給者証記載事項その他必要な事項を遅滞なく市町村に対し報告しているか。 | D43: ='指定共同生活援助（共通）'!G52
A44: 指定共同生活援助（共通） | B44: 11 指定共同生活援助事業者が支給決定障害者等に求めることのできる金銭の支払の範囲等 | C44: （１）指定共同生活援助事業者が、指定共同生活援助を提供する支給決定障害者等に対して金銭の支払を求めることができるのは、当該金銭の使途が直接利用者の便益を向上させ | D44: ='指定共同生活援助（共通）'!G53
A45: 指定共同生活援助（共通） | C45: （２）(1)の規定により金銭の支払を求める際は、当該金銭の使途及び額並びに支給決定障害者等に金銭の支払を求める理由について書面によって明らかにするとともに、支給 | D45: ='指定共同生活援助（共通）'!G54
A46: 指定共同生活援助（共通） | C46: （ただし、12の(1)から(3)までに掲げる支払については、この限りでない。） | D46: ='指定共同生活援助（共通）'!G55
A47: 指定共同生活援助（共通） | B47: 12 利用者負担額等の受領 | C47: （１）指定共同生活援助事業者は、指定共同生活援助を提供した際は、支給決定障害者から当該指定共同生活援助に係る利用者負担額の支払を受けているか。 | D47: ='指定共同生活援助（共通）'!G56
A48: 指定共同生活援助（共通） | C48: （２）指定共同生活援助事業者は、法定代理受領を行わない指定共同生活援助を提供した際は、支給決定障害者から当該指定共同生活援助に係る指定障害福祉サービス等費用基準 | D48: ='指定共同生活援助（共通）'!G57
A49: 指定共同生活援助（共通） | C49: （３）指定共同生活援助事業者は、(1)及び(2)の支払を受ける額のほか、指定共同生活援助において提供される便宜に要する費用のうち、支給決定障害者から受けることの | D49: ='指定共同生活援助（共通）'!G58
A50: 指定共同生活援助（共通） | C50: ① 食材料費 | D50: ='指定共同生活援助（共通）'!G59
A51: 指定共同生活援助（共通） | C51: ② 家賃(障害者総合支援法第34条第1項の規定により特定障害者特別給付費が利用者に支給された場合(同条第2項において準用する同法第29条第4項の規定により特定障 | D51: ='指定共同生活援助（共通）'!G60
A52: 指定共同生活援助（共通） | C52: ③ 光熱水費 | D52: ='指定共同生活援助（共通）'!G61
A53: 指定共同生活援助（共通） | C53: ④ 日用品費 | D53: ='指定共同生活援助（共通）'!G62
A54: 指定共同生活援助（共通） | C54: ⑤ ①から④のほか、指定共同生活援助において提供される便宜に要する費用のうち、日常生活においても通常必要となるものに係る費用であって、支給決定障害者に負担させる | D54: ='指定共同生活援助（共通）'!G63
A55: 指定共同生活援助（共通） | C55: （４）指定共同生活援助事業者は、(1)から(3)までに掲げる費用の額の支払を受けた場合は、当該費用に係る領収証を当該費用の額を支払った支給決定障害者に対し交付し | D55: ='指定共同生活援助（共通）'!G64
A56: 指定共同生活援助（共通） | C56: （５）指定共同生活援助事業者は、(3)の費用に係るサービスの提供に当たっては、あらかじめ、支給決定障害者に対し、当該サービスの内容及び費用について説明を行い、支 | D56: ='指定共同生活援助（共通）'!G65
A57: 指定共同生活援助（共通） | B57: 13 地域との連携 | C57: （１）指定共同生活援助事業者は、指定共同生活援助の提供に当たっては、地域住民又はその自発的な活動等との連携及び協力を行う等の地域との交流を図っているか。 | D57: ='指定共同生活援助（共通）'!G66
A58: 指定共同生活援助（共通） | C58: （２）指定共同生活援助事業者は、指定共同生活援助の提供に当たっては、利用者及びその家族、地域住民の代表者、共同生活援助について知見を有する者並びに市町村の担当者 | D58: ='指定共同生活援助（共通）'!G67
A59: 指定共同生活援助（共通） | C59: （３）指定共同生活援助事業者は、地域連携推進会議の開催のほか、おおむね一年に一回以上、当該地域連携推進会議の構成員が指定共同生活援助事業所を見学する機会を設けて | D59: ='指定共同生活援助（共通）'!G68
A60: 指定共同生活援助（共通） | C60: （４）指定共同生活援助事業者は、第二項の報告、要望、助言等についての記録を作成するとともに、当該記録を公表しているか。 | D60: ='指定共同生活援助（共通）'!G69
A61: 指定共同生活援助（共通） | C61: （５）（2）から（4）までに掲げる規定において、指定共同生活援助事業者がその提供する指定共同生活援助の質に係る外部の者による評価及び当該評価の実施状況の公表又は | D61: ='指定共同生活援助（共通）'!G70
A62: 指定共同生活援助（共通） | B62: 14 利用者負担額に係る管理 | C62: （１）指定共同生活援助事業者は、支給決定障害者（入居前の体験的な指定共同生活援助を受けている者を除く。）が同一の月に当該指定共同生活援助事業者が提供する指定共同 | D62: ='指定共同生活援助（共通）'!G71
A63: 指定共同生活援助（共通） | C63: この場合において、当該指定共同生活援助事業者は、利用者負担額合計額を市町村に報告するとともに、当該支給決定障害者及び当該他の指定障害福祉サービス等を提供した指定 | D63: ='指定共同生活援助（共通）'!G72
A64: 指定共同生活援助（共通） | C64: （２）指定共同生活援助事業者は、支給決定障害者（入居前の体験的な指定共同生活援助を受けている者に限る。）の依頼を受けて、当該支給決定障害者が同一の月に当該指定共 | D64: ='指定共同生活援助（共通）'!G73
A65: 指定共同生活援助（共通） | C65: この場合において、当該指定共同生活援助事業者は、利用者負担額合計額を市町村に報告するとともに、当該支給決定障害者及び当該他の指定障害福祉サービス等を提供した指定 | D65: ='指定共同生活援助（共通）'!G74
A66: 指定共同生活援助（共通） | B66: 15 訓練等給付費の額に係る通知等 | C66: （１）指定共同生活援助事業者は、法定代理受領により市町村から指定共同生活援助に係る訓練等給付費の支給を受けた場合は、支給決定障害者等に対し、当該支給決定障害者等 | D66: ='指定共同生活援助（共通）'!G75
A67: 指定共同生活援助（共通） | C67: （２）指定共同生活援助事業者は、法定代理受領を行わない指定共同生活援助に係る費用の支払を受けた場合は、その提供した指定共同生活援助の内容、費用の額その他必要と認 | D67: ='指定共同生活援助（共通）'!G76
A68: 指定共同生活援助（共通） | B68: 16 共同生活援助の取扱方針 | C68: （１）指定共同生活援助事業者は、指定共同生活援助に係る個別支援計画（共同生活援助計画）に基づき、利用者が地域において日常生活を営むことができるよう、当該利用者の | D68: ='指定共同生活援助（共通）'!G77
A69: 指定共同生活援助（共通） | C69: （２）指定共同生活援助事業者は、利用者が自立した日常生活または社会生活を営むことができるよう、利用者の意思決定の支援に配慮しているか。 | D69: ='指定共同生活援助（共通）'!G78
A70: 指定共同生活援助（共通） | C70: （３）指定共同生活援助事業者は、入居前の体験的な利用を希望する者に対して指定共同生活援助の提供を行う場合には、共同生活援助計画に基づき、当該利用者が、継続した指 | D70: ='指定共同生活援助（共通）'!G79
A71: 指定共同生活援助（共通） | C71: （４）指定共同生活援助事業所の従業者は、指定共同生活援助の提供に当たっては、懇切丁寧を旨とし、利用者又はその家族に対し、支援上必要な事項について、理解しやすいよ | D71: ='指定共同生活援助（共通）'!G80
A72: 指定共同生活援助（共通） | C72: （５）指定共同生活援助事業者は、その提供する指定共同生活援助の質の評価を行い、常にその改善を図っているか。 | D72: ='指定共同生活援助（共通）'!G81
A73: 指定共同生活援助（共通） | B73: 17 共同生活援助計画の作成等 | C73: （１）指定共同生活援助事業所の管理者は、サービス管理責任者に共同生活援助計画の作成に関する業務を担当させているか。 | D73: ='指定共同生活援助（共通）'!G82
A74: 指定共同生活援助（共通） | C74: （２）サービス管理責任者は、共同生活援助計画の作成に当たっては、適切な方法により、利用者について、その有する能力、その置かれている環境及び日常生活全般の状況等の | D74: ='指定共同生活援助（共通）'!G83
A75: 指定共同生活援助（共通） | C75: （３）アセスメントに当たっては、利用者が自ら意思を決定ことに困難を抱える場合には、適切に意思決定の支援を行うため、当該利用者の意思及び選好並びに判断能力等につい | D75: ='指定共同生活援助（共通）'!G84
A76: 指定共同生活援助（共通） | C76: （４）アセスメントに当たっては、利用者に面接して行っているか。この場合において、サービス管理責任者は、面接の趣旨を利用者に対して十分に説明し、理解を得ているか。 | D76: ='指定共同生活援助（共通）'!G85
A77: 指定共同生活援助（共通） | C77: （５）サービス管理責任者は、アセスメント及び支援内容の検討結果に基づき、利用者及びその家族の生活に対する意向、総合的な支援の方針、生活全般の質を向上させるための | D77: ='指定共同生活援助（共通）'!G86
A78: 指定共同生活援助（共通） | C78: （６）サービス管理責任者は、共同生活援助計画の作成に係る会議（利用者及び当該利用者に対する共同生活援助の提供に当たる担当者等を招集して行う会議をいい、テレビ電話 | D78: ='指定共同生活援助（共通）'!G87
A79: 指定共同生活援助（共通） | C79: （７）サービス管理責任者は、共同生活援助計画の原案の内容について利用者又はその家族に対して説明し、文書により利用者の同意を得ているか。 | D79: ='指定共同生活援助（共通）'!G88
A80: 指定共同生活援助（共通） | C80: （８）サービス管理責任者は、共同生活援助計画を作成した際には、当該共同生活援助計画を利用者及び指定特定相談支援事業者等に交付しているか。 | D80: ='指定共同生活援助（共通）'!G89
A81: 指定共同生活援助（共通） | C81: （９）サービス管理責任者は、共同生活援助計画の作成後、共同生活援助計画の実施状況の把握（モニタリング（利用者についての継続的なアセスメントを含む。））を行うとと | D81: ='指定共同生活援助（共通）'!G90
A82: 指定共同生活援助（共通） | C82: （10）サービス管理責任者は、モニタリングに当たっては、利用者及びその家族等との連絡を継続的に行うこととし、特段の事情のない限り、次に定めるところにより行ってい | D82: ='指定共同生活援助（共通）'!G91
A83: 指定共同生活援助（共通） | C83: （11）共同生活援助計画に変更のあった場合、(2)から(8)に準じて取り扱っているか。 | D83: ='指定共同生活援助（共通）'!G92
A84: 指定共同生活援助（共通） | B84: 18 サービス管理責任者の責務 | C84: （１）サービス管理責任者は、共同生活援助計画の作成等のほか、次に掲げる業務を行っているか。 | D84: ='指定共同生活援助（共通）'!G93
A85: 指定共同生活援助（共通） | C85: ① 利用申込者の利用に際し、その者に係る指定障害福祉サービス事業者等に対する照会等により、その者の身体及び精神の状況、当該指定共同生活援助事業所以外における指定 | D85: ='指定共同生活援助（共通）'!G94
A86: 指定共同生活援助（共通） | C86: ② 利用者の身体及び精神の状況、その置かれている環境等に照らし、利用者が自立した日常生活を営むことができるよう定期的に検討するとともに、自立した日常生活を営むこ | D86: ='指定共同生活援助（共通）'!G95
A87: 指定共同生活援助（共通） | C87: ③ 利用者が自立した社会生活を営むことができるよう指定生活介護事業所等との連絡調整を行うこと。 | D87: ='指定共同生活援助（共通）'!G96
A88: 指定共同生活援助（共通） | C88: ④ 他の従事者に対する技術的指導及び助言を行うこと。 | D88: ='指定共同生活援助（共通）'!G97
A89: 指定共同生活援助（共通） | C89: （２）サービス管理者は、業務を行うに当たっては、利用者の自己決定の尊重を原則とした上で、利用者が自ら意思を決定することに困難を抱える場合には、適切に利用者への意 | D89: ='指定共同生活援助（共通）'!G98
A90: 指定共同生活援助（共通） | B90: 19 相談及び援助 | C90: 指定共同生活援助事業者は、常に利用者の心身の状況、その置かれている環境等の的確な把握に努め、利用者又はその家族に対し、その相談に適切に応じるとともに、必要な助言 | D90: ='指定共同生活援助（共通）'!G99
A91: 指定共同生活援助（共通） | B91: 20 介護及び家事等 | C91: （１）介護は、利用者の身体及び精神の状況に応じ、利用者の自立の支援と日常生活の充実に資するよう、適切な技術をもって行っているか。 | D91: ='指定共同生活援助（共通）'!G100
A92: 指定共同生活援助（共通） | C92: （２）調理、洗濯その他の家事等は、原則として利用者と従業者が共同で行うよう努めているか。 | D92: ='指定共同生活援助（共通）'!G101
A93: 指定共同生活援助（共通） | C93: （３）指定共同生活援助事業者は、その利用者に対して、利用者の負担により、当該指定共同生活援助事業所の従業者以外の者による家事等を受けさせていないか。 | D93: ='指定共同生活援助（共通）'!G102
A94: 指定共同生活援助（共通） | B94: 21 社会生活上の便宜の供与等 | C94: （１）指定共同生活援助事業者は、利用者について、指定生活介護事業所等との連絡調整、余暇活動の支援等に努めているか。 | D94: ='指定共同生活援助（共通）'!G103
A95: 指定共同生活援助（共通） | C95: （２）指定共同生活援助事業者は、利用者が日常生活を営む上で必要な行政機関に対する手続等について、その者又はその家族が行うことが困難である場合は、その者の同意を得 | D95: ='指定共同生活援助（共通）'!G104
A96: 指定共同生活援助（共通） | C96: （３）指定共同生活援助事業者は、常に利用者の家族との連携を図るとともに、利用者とその家族との交流等の機会を確保するよう努めているか。 | D96: ='指定共同生活援助（共通）'!G105
A97: 指定共同生活援助（共通） | B97: 22 緊急時等の対応 | C97: 従業者は、現に指定共同生活援助の提供を行っているときに利用者に病状の急変が生じた場合その他必要な場合は、速やかに医療機関への連絡を行う等の必要な措置を講じている | D97: ='指定共同生活援助（共通）'!G106
A98: 指定共同生活援助（共通） | B98: 23 支給決定障害者に関する市町村への通知 | C98: 指定共同生活援助事業者は、指定共同生活援助を受けている支給決定障害者が次のいずれかに該当する場合は、遅滞なく、意見を付してその旨を市町村に通知しているか。 | D98: ='指定共同生活援助（共通）'!G107
A99: 指定共同生活援助（共通） | C99: ① 正当な理由なしに指定共同生活援助の利用に関する指示に従わないことにより、障害の状態等を悪化させたと認められるとき。 | D99: ='指定共同生活援助（共通）'!G108
A100: 指定共同生活援助（共通） | C100: ② 偽りその他不正な行為によって訓練等給付費又は特例訓練等給付費を受け、又は受けようとしたとき。 | D100: ='指定共同生活援助（共通）'!G109
...

Sheet 指定共同生活援助（共通）
C1: ※法：障害者総合支援法（障害者の日常生活及び社会生活を総合的に支援するための法律）
A2: （注）下線を付した項目が標準確認項目 | C2: ※平18厚令171：運営基準（障害者の日常生活及び社会生活を総合的に支援するための法律に基づく指定障害福祉サービスの事業等の人員、設備及び運営に関する基準）
A3: 確認項目 | B3: 確認事項 | C3: チェックポイント | D3: 根拠法令 | E3: 関係書類 | F3: 確認書類（１つ） | G3: 判定
A4: 第１基本方針 | D4: 法第43条
A5: （指定障害福祉サービス事業者の一般原則） | B5: （１）指定共同生活援助事業者は、利用者の意向、適性、障害の特性その他の事情を踏まえた計画（個別支援計画）を作成し、これに基づき利用者に対して指定共同生活援助を提供するとともに、その効果について継続的な評価を実施することその他の措置を講ずることにより利用者に対して適切かつ効果的に指定共同生活援助を提供しているか。 | C5: (1) 個別支援計画の作成と効果の評価 【現場でのチェックポイント】計画通りの支援と、定期的な振り返りができていますか？ ・適切な計画づくり： ご利用者の希望、得意なこと、障害の特性などをしっかり反映した「個別支援計画」を作成しているか。 ・計画に沿ったサポート： 作成した計画に基づき、日々の支援をブレずに提供できているか。 ・効果の確認と見直し： 支援の効果が本当に出ているかを定期的に振り返り（モニタリング）、必要に応じて計画や関わり方をアップデートしているか。 | D5: 平18厚令171 第3条第1項 | E5: 運営規程 個別支援計画 ケース記録
B6: （２）指定共同生活援助事業者は、利用者の意思及び人格を尊重して、常に当該利用者の立場に立った指定共同生活援助の提供に努めているか。 | C6: (2) ご利用者の意思・人格の尊重 【現場でのチェックポイント】常にご利用者ファーストの視点で、尊厳を大切にできていますか？ ・意思の尊重： ご利用者自身の「こうしたい」「こう生きたい」という思いや選択を尊重しているか。 ・ご利用者視点の徹底： スタッフの都合や施設のルールを押し付けるのではなく、常にご利用者の立場に立った丁寧な関わりを心がけているか。 | D6: 平18厚令171 第3条第2項 | E6: 運営規程 個別支援計画 ケース記録
B7: （３）指定共同生活援助事業者は、利用者の人権の擁護、虐待の防止等のため、必要な体制の整備を行うとともに、その従業者に対し、研修を実施する等の措置を講じているか。 | C7: (3) 人権の擁護・虐待の防止 【現場でのチェックポイント】虐待を防ぎ、人権を守るための体制づくりと研修ができていますか？ ・組織としての仕組み： 虐待防止責任者の配置や、マニュアル・通報窓口の整備など、不適切な関わりを絶対に生まないための体制を整えているか。 ・スタッフ教育の実施： 全スタッフを対象に、定期的な虐待防止研修や人権擁護に関する研修をしっかりと実施しているか。 | D7: 平18厚令171 第3条第3項 | E7: 運営規程 研修計画、研修実施記録 虐待防止関係書類 体制の整備をしていることが分かる書類
B8: （４）指定共同生活援助の事業は、利用者が地域において共同して自立した日常生活又は社会生活を営むことができるよう、当該利用者の身体及び精神の状況並びにその置かれている環境に応じて共同生活住居において相談、入浴、排せつ若しくは食事の介護その他の日常生活上の援助を適切かつ効果的に行い、又はこれに併せて、居宅における自立した日常生活への移行を希望する入居者につき当該日常生活への移行及び移行後の定着に関する相談、住居の確保に係る援助その他居宅における自立した日常生活への移行及び移行後の定着に必要な援助を適切かつ効果的に行っているか。 | C8: (4) 日常生活の援助と一人暮らし（居宅移行）への支援 【現場でのチェックポイント】ホームでの自立を支え、一人暮らしへのステップアップも応援できていますか？ ・日々の自立支援： ご利用者の心身の状況に合わせて、相談対応、入浴、排せつ、食事といった生活全般のサポートを適切に行い、地域での自立した暮らしを支えているか。 ・一人暮らしへの移行サポート： 将来的にアパートなどでの一人暮らし（居宅への移行）を希望するご利用者に対し、住まい探しの手伝いや、引っ越し後も地域生活に馴染めるような相談・見守り支援を適切に行っているか。 | D8: 平18厚令171 第207条 | E8: 運営規程 個別支援計画 ケース記録
A9: 確認項目 | B9: 確認事項 | C9: チェックポイント | D9: 根拠法令 | E9: 関係書類
A10: 第２ 人員に関す る基準 | D10: 法第43条第1項
A11: １ 指定共同生活援助事業所の従業者の員数 | B11: 指定共同生活援助事業所に置くべき従業者及びその員数は、次のとおりになっているか。 | C11: 1. スタッフ（世話人・生活支援員など）の配置人数 【現場でのチェック】ご利用者の人数や状況に対して、スタッフの「常勤換算（労働時間）」は足りていますか？ | D11: 平18厚令171 第208条第1項
A12: （１）世話人 | B12: 指定共同生活援助事業所ごとに、常勤換算方法で、利用者の数を6で除した数以上となっているか。 | C12: （1）基本の配置（世話人など）： ・全体のご利用者数を「6」で割った数以上のスタッフが配置されているか。 | D12: 平18厚令171 第208条第1項第1号 | E12: 勤務実績表 出勤簿（タイムカード） 従業員の資格証 勤務体制一覧表 利用者数（平均利用人数）が分かる書類（実績表等）
A13: （２）生活支援員 | B13: 指定共同生活援助事業所ごとに、常勤換算方法で、次の①から④までに掲げる数の合計数以上となっているか。 ① 障害支援区分に係る市町村審査会による審査及び判定の基準等に関する省令（平成26年厚生労働省令第5号）（区分省令）第1条第4号に規定する区分3に該当する利用者の数を9で除した数 ② 区分省令第1条第5号に規定する区分4に該当する利用者の数を6で除した数 ③ 区分省令第1条第6号に規定する区分5に該当する利用者の数を4で除した数 ④ 区分省令第1条第7号に規定する区分6に該当する利用者の数を2．5で除した数 | C13: （2）手厚いサポートが必要な方の配置（生活支援員など）： 以下の「区分ごとの計算」をすべて足した合計人数以上になっているか。 ・区分3のご利用者数 ÷ 9 ・区分4のご利用者数 ÷ 6 ・区分5のご利用者数 ÷ 4 ・区分6のご利用者数（※それぞれの基準に応じた数） | D13: 平18厚令171 第208条第1項 第2号 平26厚令5 第1条 | E13: 勤務実績表 出勤簿（タイムカード） 従業員の資格証 勤務体制一覧表 利用者数（平均利用人数）が分かる書類（実績表等）
A14: （３）サービス管理責任者 | B14: 指定共同生活援助事業所ごとに、①又は②に掲げる利用者の数の区分に応じ、それぞれ①又は②に掲げる数となっているか。 ① 利用者の数が30以下 1以上 ② 利用者の数が31以上 1に、利用者の数が30を超えて30又はその端数を増すごとに1を加えて得た数以上 | C14: （3） サービス管理責任者（サビ管）の配置 【現場でのチェック】ご利用者数に応じた人数のサビ管を配置できていますか？ ・ご利用者が30人以下： 1人以上の配置が必要です。 ・ご利用者が31人以上： 30人（またはその端数）が増えるごとに「+1人」を追加しているか。 【早見表】 ・1人〜30人：1人以上 ・31人〜60人：2人以上 ・61人〜90人：3人以上 | D14: 平18厚令171 第208条第1項第3号 | E14: 勤務実績表 出勤簿（タイムカード） 従業員の資格証 勤務体制一覧表 利用者数（平均利用人数）が分かる書類（実績表等）
A15: （４）利用者数の算定 | B15: (1)から(3)の利用者の数は、前年度の平均値となっているか。ただし、新規に指定を受ける場合は、適切な推定数により算定されているか。 | C15: （4）計算のベースにする「ご利用者数」のルール 【現場でのチェック】人数を計算するときの「ご利用者数」は正しい数字を使っていますか？ ・すでに対象の事業を行っている場合： 「前年度の平均ご利用者数」をベースに計算します。 ・新しくオープン（新規指定）する場合： 適切に見込んだ「推定のご利用者数」で計算して構いません。 | D15: 平18厚令171 第208条第2項 | E15: 利用者数（平均利用人数）が分かる書類（実績表等）
A16: （５）職務の専従 | B16: (1)から(3)に規定する指定共同生活援助の従業者は､専ら当該指定共同生活援助事業所の職務に従事する者となっているか。 （ただし、利用者の支援に支障がない場合はこの限りでない。） | C16: （5）管理者・スタッフの働き方（専従・兼務） 【現場でのチェック】管理者やスタッフの「兼務」のルールは守られていますか？ ・スタッフの原則： 基本的には、そのグループホームの仕事に専念しているか（ただし、ご利用者への支援に支障が出ない範囲であれば、例外も認められます）。 | D16: 平18厚令171 第208条第3項 | E16: 従業者の勤務実態の分かる書類 （出勤簿等）
A17: （６）管理者 | B17: ① 指定共同生活援助事業所ごとに専らその職務に従事する常勤の管理者を置いているか。 （ただし、指定共同生活援助事業所の管理上支障がない場合は、当該指定共同生活援助事業所の他の職務に従事させ、又は他の事業所、施設等の職務に従事させることができる。） | C17: ・管理者の配置： 常勤の管理者を1人、専従で置いているか。 ・管理者の兼務ルール： 管理業務に支障がない範囲であれば、同じホームの他の仕事（サビ管など）や、他の事業所の仕事を兼務しても問題ありません。 | D17: 平18厚令171 第209条第1項 | E17: 管理者の雇用形態が分かる書類 勤務実績表 出勤簿（タイムカード） 従業員の資格証 勤務体制一覧表
B18: ② 指定共同生活援助事業所の管理者は、適切な指定共同生活援助を提供するために必要な知識及び経験を有する者となっているか。 | C18: ・管理者の資質： グループホームを適切に運営するための「必要な知識や経験」を持っている人が管理者に就いているか。 | D18: 平18厚令171 第209条第2項 | E18: 管理者に必要な知識や経験があることが分かる書類（資格証、研修修了証
A19: 確認項目 | B19: 確認事項 | C19: チェックポイント | D19: 根拠法令 | E19: 関係書類
A20: 第３ 設備に関する基準 | D20: 法第43条第2項
A21: 設備 | B21: ① 指定共同生活援助に係る共同生活住居は、住宅地又は住宅地と同程度に利用者の家族や地域住民との交流の機会が確保される地域にあり、かつ、入所により日中及び夜間を通してサービスを提供する施設（入所施設）又は病院の敷地外にあるようになっているか。 | C21: ①ホームがある場所（立地）のルール 【現場でのチェック】地域から孤立せず、交流できる場所にありますか？・地域との交流ができる場所： ご利用者のご家族や地域住民の方々と、普段から自然に交流できるような住宅地（またはそれと同等の環境）に建っているか。 ・施設や病院の敷地外であること： 原則として、入所施設や病院の敷地内ではなく、一般的な地域の中に位置しているか。 | D21: 平18厚令171 第210条第1項 | E21: 平面図 【目視】
B22: ② 指定共同生活援助事業所は、1以上の共同生活住居（サテライト型住居を除く。以下この②、④から⑥までにおいて同じ。）を有するものとし、当該共同生活住居及びサテライト型住居の入居定員の合計は4人以上となっているか。 | C22: ②定員（人数）のルール 【現場でのチェック】事業所全体や、それぞれの住居の人数は適正ですか？ ・事業所全体の合計人数： 運営しているすべての住居（サテライト型を含む）の定員を足して、合計4人以上になっているか。 | D22: 平18厚令171 第210条第2項 | E22: 平面図 【目視】
B23: ③ 共同生活住居の配置、構造及び設備は、利用者の特性に応じて工夫したものとなっているか。 | C23: ③ご利用者に合わせた工夫： 建物の配置や設備が、ご利用者の障害の特性や状況に合わせて工夫されているか。 | D23: 平18厚令171 第210条第3項 | E23: 平面図 設備・備品等一覧表 【目視】
B24: ④ 共同生活住居は、その入居定員は2人以上10人以下となっているか。 ただし、既存の建物を共同生活住居とする場合にあっては、当該共同生活住居の入居定員は2人以上20人（都道府県知事（指定都市及び中核市にあっては、指定都市又は中核市の市長）が特に必要があると認めるときは30人）以下となっているか。 | C24: ④1つの住居の定員（原則）： 基本は2人以上 10人以下になっているか。 | D24: 平18厚令171 第210条第4項 | E24: 平面図 【目視】
B25: ⑤ 既存の建物を共同生活住居とした共同生活住居を改築する場合であって、都道府県知事が特に必要があると認めるときは、④の規定にかかわらず、当該共同生活住居の入居定員は2人以上30人以下（ただし、当該共同生活住居を改築する時点の入居定員と同数を上限とする。）となっているか。 | C25: ⑤既存の建物を活用・改築する場合： 自治体が特に認めれば、20人以下（特別な場合は30人以下）まで定員を広げることが可能です。 | D25: 平18厚令171 第210条第5項 | E25: 平面図 【目視】
B26: ⑥ 共同生活住居は、１以上のユニットを有するほか、日常生活を営む上で必要な設備を設けているか。 | C26: ⑥住居の中（ユニット）の設備とルール 【現場でのチェック】ご利用者が過ごしやすく、交流できる環境になっていますか？ | D26: 平18厚令171 第210条第6項 | E26: 平面図 設備・備品等一覧表 【目視】
B27: ⑦ ユニットの入居定員は、2人以上10人以下となっているか。 | C27: ⑦ユニットの定員： 1つの生活単位（ユニット）の定員は2人以上 10人以下に収まっているか。 | D27: 平18厚令171 第210条第7項 | E27: 平面図 【目視】
B28: ⑧ ユニットには、居室及び居室に近接して設けられる相互に交流を図ることができる設備を設けているか。その基準は次のとおりとなっているか。 ア １の居室の定員は、１人とすること。 （ただし、利用者のサービス提供上必要と認められる場合は、２人とすることができる。） イ １の居室の面積は、収納設備等を除き、7．43平方メートル以上とすること。 | C28: ⑧交流スペースの設置： ご利用者の居室の近くに、みんなで集まって交流できるリビングや食堂などのスペースがあるか。 お部屋（居室）のルール： ・原則1人部屋： ご利用者へのサービス提供上で特に必要な場合を除き、1人1部屋（個室）になっているか。 ・広さの確保： お部屋の広さは、備え付けの収納（クローゼットなど）を除いたスペースで7.43平方メートル（約4.5畳）以上あるか。 | D28: 平18厚令171 第210条第8項 | E28: 平面図 設備・備品等一覧表 【目視】
B29: ⑨ サテライト型住居の基準は、次のとおりとなっているか。 ア 入居定員を１人とすること。 イ 日常生活を営む上で必要な設備を設けること。 ウ 居室の面積は、収納設備等を除き、7．43平方メートル以上とすること。 | C29: ⑨サテライト型住居のルール 【現場でのチェック】一人暮らしに近い「サテライト型」の基準を満たしていますか？ ・定員は1人： サテライト型住居の定員は必ず1人であること。 ・必要な設備の設置： 独立して日常生活を送るために必要な設備（キッチン、お風呂、トイレなど）がきちんと備わっているか。 ・広さの確保： 一般の居室と同じく、収納スペースを除いて7.43平方メートル以上の広さがあるか。 | D29: 平18厚令171 第210条第9項 | E29: 平面図 設備・備品等一覧表 【目視】
B30: （経過措置） （１）平成18年厚生労働省令第171号（指定障害福祉サービス基準）の施行日（施行日）において現に入所施設又は病院の敷地内に存する建物を共同生活住居として指定共同生活援助の事業を行う指定共同生活援助事業者は、第3の①の規定にかかわらず、当該建物を共同生活住居とする指定共同生活援助の事業を行うことができる。 | C30: ※（経過措置）：平成18年（2006年）の制度スタート時からすでに入所施設や病院の敷地内にあった建物については、特例としてそのまま認められます。 | D30: 平18厚令171 附則第12条 | E30: 適宜必要と認める資料 | F30: 指定通知書、開設時の指定申請書控え、建物登記事項証明書、建築確認済証、賃貸借契約書、当時の平面図、敷地配置図、写真、行政との協議記録
B31: （２）指定共同生活援助事業者は、施行日において現に存する指定共同生活援助事業所において、指定共同生活援助の事業を行う場合には、当該事業所の共同生活住居（基本的な設備が完成しているものを含み、指定障害福祉サービス基準の施行の後に増築され、又は改築される等建物の構造を変更したものを除く。）が満たすべき設備に関する基準については、第3の⑦及び⑧の規定にかかわらず、平成18年厚生労働省令第58号（旧指定基準）第109条第2項及び第3項に定める基準によることができる。 | D31: 平18厚令171 附則第18条 | E31: 適宜必要と認める資料 | F31: 指定申請書控え、検査済証、増改築履歴、修繕履歴、建物登記事項証明書、賃貸借契約書、設備状況が分かる写真、行政確認記録
B32: （３）施行日において現に存する身体障害者福祉ホーム、精神障害者生活訓練施設、指定知的障害者通勤寮若しくは知的障害者福祉ホーム又は旧精神障害者福祉ホ－ム（基本的な設備が完成しているものを含み、指定障害福祉サービス基準の施行の後に増築され、又は改築される等建物の構造を変更したものを除く。）において行われる指定共同生活援助の事業について、第3の規定を適用する場合においては、当分の間、第3の⑦中「2人以上10人以下」とあるのは「2人以上30人以下」とし、第3の⑧のイの規定は、旧精神障害者福祉ホーム(障害者総合支援法施行令附則第8条の2に規定する厚生労働大臣が定めるものを除く。)を除き、当分の間、適用しない。 | D32: 平18厚令171 附則第19条 | E32: 適宜必要と認める資料 | F32: 旧施設時代の指定通知書・認可書、移行時の指定申請書、定員変更届、平面図、建物登記事項証明書、建築確認済証、増改築履歴、行政協議記録
A33: 確認項目 | B33: 確認事項 | C33: チェックポイント | D33: 根拠法令 | E33: 関係書類
A34: 第４ 運営に関する基準 | D34: 法第43条第2項
A35: １ 内容及び手続の説明及び同意 | B35: （１）指定共同生活援助事業者は、支給決定障害者等が指定共同生活援助の利用の申込みを行ったときは、当該利用申込者に係る障害の特性に応じた適切な配慮をしつつ、当該利用申込者に対し、運営規程の概要、従業者の勤務体制、その他の利用申込者のサービスの選択に資すると認められる重要事項を記した文書を交付して説明を行い、当該指定共同生活援助の提供の開始について当該利用申込者の同意を得ているか。 | C35: ・契約前に、ご利用者やご家族に重要事項説明書などを使い、サービス内容や料金を分かりやすく説明して、文書で同意（サイン）をもらっていますか？ | D35: 平18厚令171 第213条 準用（第9条第1項） | E35: 重要事項説明書 利用契約書
B36: （２）指定共同生活援助事業者は、社会福祉法第77条の規定に基づき書面の交付を行う場合は、利用者の障害の特性に応じた適切な配慮をしているか。 | D36: 平18厚令171 第213条 準用（第9条 第2項） | E36: 重要事項説明書 利用契約書 その他利用者に交付した書面
A37: ２ 提供拒否の禁止 | B37: 指定共同生活援助事業者は、正当な理由がなく、指定共同生活援助の提供を拒んでいないか。 | C37: ・「相性が悪そう」「対応が大変そう」といった事業所側の理由で、ご利用者の受け入れを断っていませんか？（拒否するには正当な理由が必要です） | D37: 平18厚令171 第213条 準用（第11条） | E37: 適宜必要と認める資料 | F37: 問い合わせ/見学記録(受入困難と判断した理由が書かれているか)
A38: ３ 連絡調整に対する協力 | B38: 指定共同生活援助事業者は、指定共同生活援助の利用について市町村又は一般相談支援事業若しくは特定相談支援事業を行う者が行う連絡調整に、できる限り協力しているか。 | C38: ・他の施設や相談支援専門員から、ご利用者の退去や転居に伴う調整、状況確認の連絡が来たとき、スムーズに協力していますか？ | D38: 平18厚令171 第213条 準用（第12条） | E38: 適宜必要と認める資料 | F38: 相談支援専門員、市町村との連絡記録(または日誌)
A39: ４ 受給資格の確認 | B39: 指定共同生活援助事業者は、指定共同生活援助の提供を求められた場合は、その者の提示する受給者証によって、支給決定の有無、支給決定の有効期間、支給量等を確かめているか。 | C39: ・ご利用者の受給者証をしっかり確認し、サービスの支給決定期間が切れていないか、負担上限月額がいくらになっているかを正確に把握していますか？ | D39: 平18厚令171 第213条 準用（第14条） | E39: 受給者証の写し
A40: ５ 訓練等給付費の支給の申請に係る援助 | B40: （１）指定共同生活援助事業者は、共同生活援助に係る支給決定を受けていない者から利用の申込みがあった場合は、その者の意向を踏まえて速やかに訓練等給付費の支給の申請が行われるよう必要な援助を行っているか。 | C40: ・ご利用者が受給者証の更新や申請手続きをするとき、本人が困らないよう必要に応じて手続きのお手伝いをしていますか？ | D40: 平18厚令171 第213条 準用（第15条 第1項） | E40: 適宜必要と認める資料 | F40: 仮申込書（相談対応・サポートした記録が残っているか）
B41: （２）指定共同生活援助事業者は、共同生活援助に係る支給決定に通常要すべき標準的な期間を考慮し、支給決定の有効期間の終了に伴う訓練等給付費の支給申請について、必要な援助を行っているか。 | D41: 平18厚令171 第213条 準用（第15条 第2項） | E41: 適宜必要と認める資料 | F41: 受給者証期限管理表
A42: ６ 心身の状況等の把握 | B42: 指定共同生活援助事業者は、指定共同生活援助の提供に当たっては、利用者の心身の状況、その置かれている環境、他の保健医療サービス又は福祉サービスの利用状況等の把握に努めているか。 | C42: ・入居前に、ご利用者の病気、障害の特性、これまでの生活歴、他にどんな福祉サービスを使っているかなどをしっかりヒアリングして把握していますか？ | D42: 平18厚令171 第213条 準用（第16条） | E42: アセスメント記録 ケース記録
A43: ７ 指定障害福祉サービス事業者等との連携等 | B43: （１）指定共同生活援助事業者は、指定共同生活援助を提供するに当たっては、地域及び家庭との結び付きを重視した運営を行い、市町村、他の指定障害福祉サービス事業者等その他の保健医療サービス又は福祉サービスを提供する者との密接な連携に努めているか。 | C43: ・ご利用者が通っている日中活動先（就労継続支援や生活介護など）の事業所や医療機関と、日頃から連絡を取り合い、情報を共有していますか？ | D43: 平18厚令171 第213条 準用（第17条第1項） | E43: 個別支援計画 ケース記録
B44: （２）指定共同生活援助事業者は、指定共同生活援助の提供の終了に際しては、利用者又はその家族に対して適切な援助を行うとともに、保健医療サービス又は福祉サービスを提供する者との密接な連携に努めているか。 | D44: 平18厚令171 第213条 準用（第17条第2項） | E44: 個別支援計画 ケース記録
A45: ８ サービスの提供の記録 | B45: （１）指定共同生活援助事業者は、指定共同生活援助を提供した際は、当該指定共同生活援助の提供日、内容その他必要な事項を記録しているか。 | C45: ・日々のサポートが終わったあと、「どんな支援をしたか」「ご利用者の様子はどうだったか」を毎回漏れなく実績記録や日誌に残していますか？ | D45: 平18厚令171 第213条準用（第53条の2第1項） | E45: サービス提供の記録
B46: （２）指定共同生活援助事業者は、(1)の規定による記録に際しては、支給決定障害者等から指定共同生活援助を提供したことについて確認を受けているか。 | C46: ・実績記録や日誌をご利用者やご家族から確認（サイン等）を受けていますか？ | D46: 平18厚令171 第213条 準用（第53条の2第2項） | E46: サービス提供の記録
A47: ９ 入退居 | B47: （１）指定共同生活援助は、共同生活住居への入居を必要とする利用者(入院治療を要する者を除く。)に提供されているか。 | C47: ・本当にグループホームでの生活を必要としているご利用者を受け入れていますか？ ※現在、病院での入院治療が絶対に必要であるような状態の方は、原則として対象外となります。 | D47: 平18厚令171 第210条の2 第1項 | E47: 個別支援計画 サービス提供の記録 アセスメント記録
B48: （２）指定共同生活援助事業者は、利用申込者の入居に際しては、その者の心身の状況、生活歴、病歴等の把握に努めているか。 | C48: ・新しく入居される方の、心身の状態、これまでの生活歴、病歴（持病やアレルギーなど）を、事前の面談や書類できちんと聞き取って把握していますか？ | D48: 平18厚令171 第210条の2 第2項 | E48: 個別支援計画 アセスメント記録 サービス担当者会議の記録
B49: （３）指定共同生活援助事業者は、利用者の退居の際は、利用者の希望を踏まえた上で、退居後の生活環境や援助の継続性に配慮し、退居に必要な援助を行い、又はこれに併せて居宅における自立した日常生活への移行後の定着に必要な援助を行っているか。 | C49: ・ご利用者が退居されるとき、本人の「次の場所でどう生きたいか」という希望をしっかり聞いていますか？また、次の引越し先でも困らずに生活を続けられるよう、必要な荷造りや手続きの手伝いをし、一人暮らし（居宅移行）を始めた後も地域生活になじめるよう見守りや相談に乗っていますか？ | D49: 平18厚令171 第210条の2 第3項 | E49: ケース記録 サービス提供の記録
B50: （４）指定共同生活援助事業者は、利用者の退居に際しては、利用者に対し、適切な援助を行うとともに、保健医療サービス又は福祉サービスを提供する者との密接な連携に努めているか。 | C50: ・退居される際、ご利用者が次の生活の場で困らないよう、新しく利用する福祉サービス事業所、相談支援専門員、病院などの関係機関と、事前の情報共有や引き継ぎの連携を密に行っていますか？ | D50: 平18厚令171 第210条の2 第4項 | E50: 他サービスとの連携状況が分かる書類（ケース記録、サービス提供の記録等）
A51: 10 入退居の記録の記載等 | B51: （１）指定共同生活援助事業者は、入居者の入居又は退居に際しては、当該指定共同生活援助事業者の名称、入居又は退居の年月日その他の必要な事項(受給者証記載事項）を利用者の受給者証に記載しているか。 | C51: ・ご利用者が入居、または退居された際、本人の「受給者証」の事業者記入欄に、私たちのホームの名称や入退居の年月日をその場で漏れなく記入していますか？ | D51: 平18厚令171 第210条の3 第1項 | E51: 適宜必要と認める資料 | F51: 受給者証写し、入居・退去に関する行政提出書類
B52: （２）指定共同生活援助事業者は、受給者証記載事項その他必要な事項を遅滞なく市町村に対し報告しているか。 | C52: ・入退居の手続きがあった場合、受給者証に書いた内容や必要な情報を、後回しにせず速やかに（遅れずに）お住まいの市町村の窓口へ報告していますか？ | D52: 平18厚令171 第210条の3 第2項 | E52: 適宜必要と認める資料 契約内容報告書 | F52: 受給者証写し、入居・退去に関する行政提出書類
A53: 11 指定共同生活援助事業者が支給決定障害者等に求めることのできる金銭の支払の範囲等 | B53: （１）指定共同生活援助事業者が、指定共同生活援助を提供する支給決定障害者等に対して金銭の支払を求めることができるのは、当該金銭の使途が直接利用者の便益を向上させるものであって、当該支給決定障害者等に支払を求めることが適当であるものに限られているか。 | C53: ・ご利用者にお金を請求する際、その使い道が「直接そのご利用者のためになるもの（生活の質や便利さが向上するもの）」だけに絞られていますか？ | D53: 平18厚令171 第213条 準用（第20条 第1項) | E53: 適宜必要と認める資料 | F53: 重要事項説明書、請求書
B54: （２）(1)の規定により金銭の支払を求める際は、当該金銭の使途及び額並びに支給決定障害者等に金銭の支払を求める理由について書面によって明らかにするとともに、支給決定障害者等に対し説明を行い、その同意を得ているか。 | C54: ・お金を請求する前に、「何に」「いくらかかるのか」、そして「なぜそれが必要なのか（理由）」を書面できちんと明記し、ご利用者やご家族に分かりやすく説明して、必ず同意（サイン）をもらっていますか？ | D54: 平18厚令171 第213条 準用（第20条 第2項） | E54: 適宜必要と認める資料 | F54: 重要事項説明書
B55: （ただし、12の(1)から(3)までに掲げる支払については、この限りでない。）
A56: 12 利用者負担額等の受領 | B56: （１）指定共同生活援助事業者は、指定共同生活援助を提供した際は、支給決定障害者から当該指定共同生活援助に係る利用者負担額の支払を受けているか。 | C56: ・ご利用者にホームのサービスを提供した際、国や役所から決められた自己負担額（1割負担などがある方）を、対象のご利用者から正しく受け取っていますか？ | D56: 平18厚令171 第210条の4 第1項 | E56: 請求書 領収書
B57: （２）指定共同生活援助事業者は、法定代理受領を行わない指定共同生活援助を提供した際は、支給決定障害者から当該指定共同生活援助に係る指定障害福祉サービス等費用基準額の支払を受けているか。 | C57: ・万が一、役所が代わりに給付費を事業所へ直接支払ってくれないケース（法定代理受領にならない特別な場合）があったとき、一旦ご利用者からサービス費用の全額（国が定める基準額）を正しく受け取っていますか？ | D57: 平18厚令171 第210条の4 第2項 | E57: 請求書 領収書
B58: （３）指定共同生活援助事業者は、(1)及び(2)の支払を受ける額のほか、指定共同生活援助において提供される便宜に要する費用のうち、支給決定障害者から受けることのできる次に掲げる費用の支払を受けているか。 | C58: ・サービス利用料とは別に、グループホームでの生活にかかる以下の費用をご利用者から適切に受け取っていますか？ | D58: 平18厚令171 第210条の4 第3項 | E58: 請求書 領収書
B59: ① 食材料費
B60: ② 家賃(障害者総合支援法第34条第1項の規定により特定障害者特別給付費が利用者に支給された場合(同条第2項において準用する同法第29条第4項の規定により特定障害者特別給付費が利用者に代わり当該指定共同生活介護事業者に支払われた場合に限る。)は、当該利用者に係る家賃の月額から同法第34条第2項において準用する同法第29条第5項の規定により当該利用者に支給があったものとみなされた特定障害者特別給付費の額を控除した額を限度とする。) | C60: 【補足】 国や自治体から「特定障害者特別給付費（家賃補助の1万円など）」が、ご利用者の代わりに事業所に直接振り込まれている（代理受領している）場合は、元の家賃月額からその補助額を差し引いた、残りの金額だけをご利用者に請求してください。
B61: ③ 光熱水費
B62: ④ 日用品費
B63: ⑤ ①から④のほか、指定共同生活援助において提供される便宜に要する費用のうち、日常生活においても通常必要となるものに係る費用であって、支給決定障害者に負担させることが適当と認められるもの | C63: ・①〜④のほかに、ホームで生活する上で通常必要となり、ご利用者に負担してもらうのが妥当と認められる費用
B64: （４）指定共同生活援助事業者は、(1)から(3)までに掲げる費用の額の支払を受けた場合は、当該費用に係る領収証を当該費用の額を支払った支給決定障害者に対し交付しているか。 | C64: ・上記の(1)から(3)までのお金（利用料や家賃・食費などの実費）を受け取ったら、支払ってくれたご利用者に対して、必ずその費用の領収証を発行して渡していますか？ | D64: 平18厚令171 第210条の4 第4項 | E64: 領収書
B65: （５）指定共同生活援助事業者は、(3)の費用に係るサービスの提供に当たっては、あらかじめ、支給決定障害者に対し、当該サービスの内容及び費用について説明を行い、支給決定障害者の同意を得ているか。 | C65: ・(3)の生活費（食費・家賃・光熱費など）をいただくにあたっては、サービスを提供する前にあらかじめ、ご利用者（またはご家族）に対して「どんな内容で、いくらかかるのか」をしっかりと説明し、必ず同意をもらっていますか？ | D65: 平18厚令171 第210条の4 第5項 | E65: 重要事項説明書
A66: 13 地域との連携 | B66: （１）指定共同生活援助事業者は、指定共同生活援助の提供に当たっては、地域住民又はその自発的な活動等との連携及び協力を行う等の地域との交流を図っているか。 | C66: ・グループホームを運営するにあたり、近隣住民の方々や地域のボランティア活動などと普段から協力・連携し、地域社会との交流を大切にしていますか？ | D66: 平18厚令171 第210条の7 第1項 | E66: 適宜必要と認める書類 | F66: 地域交流記録
B67: （２）指定共同生活援助事業者は、指定共同生活援助の提供に当たっては、利用者及びその家族、地域住民の代表者、共同生活援助について知見を有する者並びに市町村の担当者等により構成される協議会（テレビ電話装置等を活用して行うことができるものとする。以下この項、第８の22及び第12の21において、「地域連携推進会議」という。）を開催し、おおむね一年に一回以上、地域連携推進会議において、事業の運営に係る状況を報告するとともに、必要な要望、助言等を聴く機会を設けているか。 | C67: ・ご利用者、ご家族、地域住民の代表（町内会長など）、グループホームに詳しい専門家、役所（市町村）の担当者などが集まる「地域連携推進会議」を、おおむね1年に1回以上開催していますか？ ・会議の場でホームの運営状況をきちんと報告し、参加者から意見や要望、アドバイスをもらう機会を作っているかどうかが問われます。 ※この会議は、テレビ電話やオンライン会議システム（Zoomなど）を使って開催することも認められています。 | D67: 平18厚令171 第210条の7 第2項 | E67: 適宜必要と認める書類 | F67: 地域連携推進会議議事録、出席者名簿
B68: （３）指定共同生活援助事業者は、地域連携推進会議の開催のほか、おおむね一年に一回以上、当該地域連携推進会議の構成員が指定共同生活援助事業所を見学する機会を設けているか。 | C68: ・会議を開くだけでなく、おおむね1年に1回以上、その会議のメンバー（近隣住民の代表や役所の担当者など）に、実際のグループホームの様子を見学してもらう機会を作っていますか？ | D68: 平18厚令171 第210条の7 第3項 | E68: 適宜必要と認める書類 | F68: 地域連携推進会議議事録
B69: （４）指定共同生活援助事業者は、第二項の報告、要望、助言等についての記録を作成するとともに、当該記録を公表しているか。 | C69: ・会議で報告した内容や、参加者からもらった要望・アドバイスなどをしっかりと「記録（議事録）」に残していますか？また、その記録を外部に向けて公表（ホームページへの掲載やホーム内への掲示など）していますか？ | D69: 平18厚令171 第210条の7 第4項 | E69: 適宜必要と認める書類 | F69: ホームページ掲載画面
B70: （５）（2）から（4）までに掲げる規定において、指定共同生活援助事業者がその提供する指定共同生活援助の質に係る外部の者による評価及び当該評価の実施状況の公表又はこれに準ずる措置として都道府県知事が定めるものを講じている場合には適用しない。 | C70: ・もし事業所として、都道府県が定める「外部の専門業者によるサービス品質の評価（外部評価）」を定期的に受けており、その結果を公表している場合は、上記の(2)〜(4)（地域連携推進会議の開催や見学、公表など）のルールは免除されます。 | D70: 平18厚令171 第210条の7 第5項 | E70: 適宜必要と認める書類 | F70: 自立支援協議会などの外部評価結果報告書
A71: 14 利用者負担額に係る管理 | B71: （１）指定共同生活援助事業者は、支給決定障害者（入居前の体験的な指定共同生活援助を受けている者を除く。）が同一の月に当該指定共同生活援助事業者が提供する指定共同生活援助及び他の指定障害福祉サービス等を受けたときは、当該指定共同生活援助及び他の指定障害福祉サービス等に係る利用者負担額合計額を算定しているか。 | C71: 【対象】本入居しているご利用者（体験利用中の方は除く） ・同じ月に、私たちのグループホームと「他の障害福祉サービス（就労継続支援や生活介護、ヘルパーなど）」を組み合わせて使っているご利用者がいる場合、事業所として「1ヶ月の利用者負担額の合計（上限管理）」を正しく計算していますか？ | D71: 平18厚令171 第213条 準用（第170条の2第1項） | E71: 適宜必要と認める書類 | F71: 利用者負担上限額管理票
B72: この場合において、当該指定共同生活援助事業者は、利用者負担額合計額を市町村に報告するとともに、当該支給決定障害者及び当該他の指定障害福祉サービス等を提供した指定障害福祉サービス事業者等に通知しているか。 | C72: ・計算した合計額を市町村へ漏れなく報告するとともに、ご利用者本人、および他のサービスを提供した事業所にも、計算結果を正しく通知していますか？
B73: （２）指定共同生活援助事業者は、支給決定障害者（入居前の体験的な指定共同生活援助を受けている者に限る。）の依頼を受けて、当該支給決定障害者が同一の月に当該指定共同生活援助事業者が提供する指定共同生活援助及び他の指定障害福祉サービス等を受けたときは、当該指定共同生活援助及び他の指定障害福祉サービス等に係る利用者負担額合計額を算定しているか。 | C73: 【対象】体験入居（体験利用）をしているご利用者 ・体験利用中のご利用者から依頼を受けて、同じ月に私たちの体験利用と「他の障害福祉サービス」を併用した場合、本入居の方と同じように「利用者負担額の合計（上限管理）」を正しく計算していますか？ | D73: 平18厚令171 第213条 準用（第170条の2第2項) | E73: 適宜必要と認める資料 | F73: 利用者負担上限額管理票
B74: この場合において、当該指定共同生活援助事業者は、利用者負担額合計額を市町村に報告するとともに、当該支給決定障害者及び当該他の指定障害福祉サービス等を提供した指定障害福祉サービス事業者等に通知しているか。 | C74: ・本入居の場合と同様に、計算した合計額を市町村へ報告し、ご利用者本人および他のサービス事業所へ速やかに通知していますか？
A75: 15 訓練等給付費の額に係る通知等 | B75: （１）指定共同生活援助事業者は、法定代理受領により市町村から指定共同生活援助に係る訓練等給付費の支給を受けた場合は、支給決定障害者等に対し、当該支給決定障害者等に係る訓練等給付費の額を通知しているか。 | C75: ・国保連などを通じて、市町村からグループホームの運営費（訓練等給付費）が事業所に直接振り込まれた際（法定代理受領）、ご利用者に対して「あなたの代わりに市町村からこれだけのお金が支給されました」という金額の通知（代理受領通知書など）を毎月定期的にお渡ししていますか？ | D75: 平18厚令171 第213条準用（第23条第1項） | E75: 通知の写し
B76: （２）指定共同生活援助事業者は、法定代理受領を行わない指定共同生活援助に係る費用の支払を受けた場合は、その提供した指定共同生活援助の内容、費用の額その他必要と認められる事項を記載したサービス提供証明書を支給決定障害者等に対して交付しているか。 | C76: ・万が一、役所から事業所へ直接お金が振り込まれない特別なケースで、ご利用者からサービス費用の全額を一旦受け取った際、「どんなサポートを何回行い、いくら費用がかかったか」を正しく記載した「サービス提供証明書」を作成し、ご利用者に対して必ず発行して渡していますか？ | D76: 平18厚令171 第213条 準用（第23条第2項） | E76: サービス提供証明書の写し
A77: 16 共同生活援助の取扱方針 | B77: （１）指定共同生活援助事業者は、指定共同生活援助に係る個別支援計画（共同生活援助計画）に基づき、利用者が地域において日常生活を営むことができるよう、当該利用者の身体及び精神の状況並びにその置かれている環境に応じて、その者の支援を適切に行うとともに、指定共同生活援助の提供が漫然かつ画一的なものとならないように配慮しているか。 | C77: ・作成した「個別支援計画」に沿って、ご利用者の心身の状態や置かれている環境に合わせたオーダーメイドのサポートを正しく行っていますか？また、日々の支援が「いつも通りだから」とマンネリ化したり、全員に全く同じ対応をするような、おざなりなものになっていませんか？ | D77: 平18厚令171 第210条の5 第1項 | E77: 適宜必要と認める資料 | F77: 個別支援計画書一式
B78: （２）指定共同生活援助事業者は、利用者が自立した日常生活または社会生活を営むことができるよう、利用者の意思決定の支援に配慮しているか。 | C78: ・ご利用者が自分で考えて選び、自立した生活を送れるよう、本人の「こうしたい」という思いを尊重し、選択をサポートする関わり（意思決定支援）を心がけていますか？ | D78: 平18厚令171 第210条の5 第2項 | E78: 適宜必要と認める資料 | F78: 個別支援計画書一式
B79: （３）指定共同生活援助事業者は、入居前の体験的な利用を希望する者に対して指定共同生活援助の提供を行う場合には、共同生活援助計画に基づき、当該利用者が、継続した指定共同生活援助の利用に円滑に移行できるよう配慮するとともに、継続して入居している他の利用者の処遇に支障がないようにしているか。 | C79: ・入居前の体験利用を受け入れる際、計画に基づいて、将来の本入居へスムーズに進めるよう工夫していますか？同時に、すでにホームで暮らしている他のご利用者の生活ペースが乱れたり、支援に支障が出たりしていないか目を行き届かせていますか？ | D79: 平18厚令171 第210条の5 第3項 | E79: 適宜必要と認める資料 | F79: 体験利用中の支援記録
B80: （４）指定共同生活援助事業所の従業者は、指定共同生活援助の提供に当たっては、懇切丁寧を旨とし、利用者又はその家族に対し、支援上必要な事項について、理解しやすいように説明を行っているか。 | C80: ・スタッフ全員が、ご利用者やご家族に対して常に親身で丁寧な態度で接していますか？また、これからの支援や必要な事項について、専門用語を使わず、相手が一番理解しやすい言葉や方法で説明できていますか？ | D80: 平18厚令171 第210条の5 第4項 | E80: 適宜必要と認める資料 | F80: サービス担当者会議議事録
B81: （５）指定共同生活援助事業者は、その提供する指定共同生活援助の質の評価を行い、常にその改善を図っているか。 | C81: ・自分たちが提供している支援の質について、定期的に振り返り（自己評価やスタッフ間での検証など）を行っていますか？現状に満足せず、見つかった課題を日々のサービス改善につなげていますか？ | D81: 平18厚令171 第210条の5 第5項 | E81: 適宜必要と認める資料 | F81: 利用者満足度アンケート結果(アンケート結果後の行動記録も）
A82: 17 共同生活援助計画の作成等 | B82: （１）指定共同生活援助事業所の管理者は、サービス管理責任者に共同生活援助計画の作成に関する業務を担当させているか。 | C82: ・管理者として、個別支援計画の作成や管理に関する一連の業務を、サービス管理責任者（サビ管）にしっかりと担当させていますか？ | D82: 平18厚令171 第213条 準用（第58条 第1項) | E82: 個別支援計画 サービス管理責任者が個別支援計画を作成していることが分かる書類
B83: （２）サービス管理責任者は、共同生活援助計画の作成に当たっては、適切な方法により、利用者について、その有する能力、その置かれている環境及び日常生活全般の状況等の評価を通じて利用者の希望する生活や課題等の把握（アセスメント）を行うとともに、利用者の自己決定の尊重及び意思決定の支援に配慮しつつ、利用者が自立した日常生活を営むことができるように支援する上での適切な支援内容の検討をしているか。 | C83: ・サビ管は、計画を作る前にご利用者の得意なこと、生活環境、普段の様子などを正しく把握（アセスメント）していますか？また、本人の「自分で決めたい」という思いや意思決定をサポートし、自立した暮らしができるような支援内容を考えていますか？ | D83: 平18厚令171 第213条 準用（第58条 第2項) | E83: 個別支援計画 アセスメント及びモニタリングを実施したことが分かる記録
B84: （３）アセスメントに当たっては、利用者が自ら意思を決定ことに困難を抱える場合には、適切に意思決定の支援を行うため、当該利用者の意思及び選好並びに判断能力等について丁寧に把握しているか。 | C84: ・自分の気持ちを伝えるのが難しいご利用者の場合、サビ管は本人の好みやこだわり、判断の状況などを丁寧に聞き取り、適切な「意思決定支援」を行えるよう準備していますか？ | D84: 平18厚令171 第213条 準用（第58条 第3項) | E84: 個別支援計画 アセスメントを実施したことが分かる記録
B85: （４）アセスメントに当たっては、利用者に面接して行っているか。この場合において、サービス管理責任者は、面接の趣旨を利用者に対して十分に説明し、理解を得ているか。 | C85: ・アセスメントの際、サビ管は必ずご利用者本人と直接面接していますか？その際、「なぜ面接をするのか」の目的を本人に分かりやすく説明し、納得してもらった上で話を進めていますか？ | D85: 平18厚令171 第213条 準用（第58条 第4項) | E85: アセスメントを実施したことが分かる記録 面接記録
B86: （５）サービス管理責任者は、アセスメント及び支援内容の検討結果に基づき、利用者及びその家族の生活に対する意向、総合的な支援の方針、生活全般の質を向上させるための課題、指定共同生活援助の目標及びその達成時期、指定共同生活援助を提供する上での留意事項等を記載した共同生活援助計画の原案を作成しているか。 この場合において、当該指定共同生活援助事業所が提供する指定共同生活援助以外の保健医療サービス又はその他の福祉サービス等との連携も含めて共同生活援助計画の原案に位置付けるよう努めているか。 | C86: ・アセスメント結果を元に、ご利用者やご家族の希望、全体の支援方針、目標と達成時期、注意点などを盛り込んだ計画書の「原案」を作っていますか？また、ホームの支援だけでなく、通っている生活介護や就労継続支援、病院など、他のサービスとの連携も計画に組み込むよう工夫していますか？ | D86: 平18厚令171 第213条 準用（第58条 第5項) | E86: 個別支援計画の原案 他サービスとの連携状況が分かる書類
B87: （６）サービス管理責任者は、共同生活援助計画の作成に係る会議（利用者及び当該利用者に対する共同生活援助の提供に当たる担当者等を招集して行う会議をいい、テレビ電話装置等の活用可能。）を開催し、当該利用者の生活に対する意向等を改めて確認するとともに、共同生活援助計画の原案の内容について意見を求めているか。 | C87: ・サビ管が主催して、ご利用者本人や現場の担当スタッフを集めた「計画作成の会議」を開いていますか？原案を見せながら本人の意向を再確認し、みんなから意見をもらっていますか？（※テレビ電話やZoomなどのオンライン開催も可能です） | D87: 平18厚令171 第213条 準用（第58条 第6項) | E87: サービス担当者会議の記録
B88: （７）サービス管理責任者は、共同生活援助計画の原案の内容について利用者又はその家族に対して説明し、文書により利用者の同意を得ているか。 | C88: ・まとまった計画原案の内容を、ご利用者やご家族に分かりやすく説明し、納得してもらった上で「文書（サインや印鑑）」による同意をもらっていますか？ | D88: 平18厚令171 第213条 準用（第58条 第7項) | E88: 個別支援計画
B89: （８）サービス管理責任者は、共同生活援助計画を作成した際には、当該共同生活援助計画を利用者及び指定特定相談支援事業者等に交付しているか。 | C89: ・完成した個別支援計画書を、ご利用者本人（またはご家族）、および担当の相談支援専門員（指定特定相談支援事業者）に必ずコピーを渡して（交付）いますか？ | D89: 平18厚令171 第213条 準用（第58条 第8項) | E89: 利用者に交付した記録 個別支援計画
B90: （９）サービス管理責任者は、共同生活援助計画の作成後、共同生活援助計画の実施状況の把握（モニタリング（利用者についての継続的なアセスメントを含む。））を行うとともに、少なくとも6月に1回以上、共同生活援助計画の見直しを行い、必要に応じて共同生活援助計画の変更を行っているか。 | C90: ・計画通りに進んでいるかを定期的に振り返り（モニタリング）を行っていますか？また、少なくとも6ヶ月に1回以上は計画全体を見直し、状況に合わせて中身を更新していますか？ | D90: 平18厚令171 第213条 準用（第58条 第9項) | E90: 個別支援計画 アセスメント及びモニタリングに関する記録
B91: （10）サービス管理責任者は、モニタリングに当たっては、利用者及びその家族等との連絡を継続的に行うこととし、特段の事情のない限り、次に定めるところにより行っているか。 ① 定期的に利用者に面接すること。 ② 定期的にモニタリングの結果を記録すること。 | C91: ・モニタリングを行う際、ご利用者やご家族と小まめに連絡を取り、以下のルールを徹底していますか？ ① 定期的（毎月）にご利用者本人と直接面接すること ② その結果を必ず記録に残すこと | D91: 平18厚令171 第213条 準用（第58条 第10項) | E91: モニタリング記録 面接記録
B92: （11）共同生活援助計画に変更のあった場合、(2)から(8)に準じて取り扱っているか。 | C92: ・計画を変更する場合も、最初と同じように「アセスメント → 原案作成 → 会議 → 説明と同意 → 交付」の(2)〜(8)の手順を省略せずにしっかりと踏んでいますか？ | D92: 平18厚令171 第213条 準用（第58条 第11項) | E92: (2)から(8)に掲げる確認資料
A93: 18 サービス管理責任者の責務 | B93: （１）サービス管理責任者は、共同生活援助計画の作成等のほか、次に掲げる業務を行っているか。 | C93: サビ管の仕事は、個別支援計画を作るだけではありません。以下の4つの業務が日頃からキチンと行われているか確認してください。 | D93: 平18厚令171 第210条の6 第１項
B94: ① 利用申込者の利用に際し、その者に係る指定障害福祉サービス事業者等に対する照会等により、その者の身体及び精神の状況、当該指定共同生活援助事業所以外における指定障害福祉サービス等の利用状況等を把握すること。 | C94: ・新しいご利用者が入居される際、それまで使っていた障害福祉サービスの事業所などに問い合わせ（照会）をしていますか？本人の心身の状態や、私たちのホーム以外でどんなサービスをどれくらい使っているか（利用状況）を正確に把握できているかがポイントです。 | E94: 個別支援計画 アセスメント及びモニタリングに関する記録
B95: ② 利用者の身体及び精神の状況、その置かれている環境等に照らし、利用者が自立した日常生活を営むことができるよう定期的に検討するとともに、自立した日常生活を営むことができると認められる利用者に対し、必要な支援を行うこと。 | C95: ・ご利用者の心身の状態や生活環境を見ながら、「グループホームを出て一人暮らしをするなど、自立した生活を営むことができそうか」を定期的に検討していますか？そして「自立できそうだ」と認められるご利用者に対して、ステップアップに必要な支援を適切に行っていますか。 | E95: 個別支援計画 アセスメント及びモニタリングに関する記録 サービス提供の記録
B96: ③ 利用者が自立した社会生活を営むことができるよう指定生活介護事業所等との連絡調整を行うこと。 | C96: ・ご利用者が昼間に通っている「生活介護事業所」や「就労支援事業所」などと、普段から密に連絡を取り合っていますか？ご利用者がスムーズに社会生活を送れるよう、日中の関係機関とのパイプ役をしっかり果たせているかを確認してください。 | E96: 指定生活介護事業所等との連絡調整した記録
B97: ④ 他の従事者に対する技術的指導及び助言を行うこと。 | C97: ・現場で日々ご利用者と接するスタッフたちに対して、具体的な関わり方や支援の技術について、指導や助言（アドバイス）を行っていますか？サビ管として、ホーム全体の支援の質を高めるための教育ができているかが問われます。 | E97: 他の従業者に指導及び助言した記録
B98: （２）サービス管理者は、業務を行うに当たっては、利用者の自己決定の尊重を原則とした上で、利用者が自ら意思を決定することに困難を抱える場合には、適切に利用者への意思決定の支援が行われるように努めているか。 | C98: ・サビ管が日々の業務を行うにあたっては、何よりも「ご利用者自身がどうしたいかを選び、決めること（自己決定）」を一番に尊重することを大原則にしていますか？また、自分の希望をうまく言葉にできないなど、自分で決めることが難しいご利用者に対しては、周りのスタッフとも協力して、本人の本当の思いをくみ取るための丁寧なサポート（意思決定支援）に努めていますか。 | D98: 平18厚令171 第210条の6 第2項 | E98: 適宜必要と認める資料 | F98: 個別支援計画書一式
A99: 19 相談及び援助 | B99: 指定共同生活援助事業者は、常に利用者の心身の状況、その置かれている環境等の的確な把握に努め、利用者又はその家族に対し、その相談に適切に応じるとともに、必要な助言その他の援助を行っているか。 | C99: ・常にご利用者の心身の状態や、置かれている環境（日中活動先での様子や健康状態など）の変化をスタッフ間でしっかりと把握できていますか？また、ご利用者やご家族から生活上の悩みや困り事の相談があった際、親身になって適切に対応し、必要なアドバイスやサポートを行っていますか？ | D99: 平18厚令171 第213条 準用（第60条) | E99: 適宜必要と認める資料 | F99: 個別記録、日誌
A100: 20 介護及び家事等 | B100: （１）介護は、利用者の身体及び精神の状況に応じ、利用者の自立の支援と日常生活の充実に資するよう、適切な技術をもって行っているか。 | C100: ・ご利用者の体や心の状態に合わせて、本人の自立を支え、毎日の生活がより充実したものになるよう、適切な技術をもって介護を提供していますか？ | D100: 平18厚令171 第211条第1項 | E100: 個別支援計画 サービス提供の記録 業務日誌等
...

Sheet 指定共同生活援助（日中サービス支援型）
A1: （注）下線を付した項目が標準確認項目
A2: 確認項目 | B2: 確認事項 | C2: 根拠法令 | D2: 関係書類 | E2: 確認書類（１つ） | F2: 判定
A3: 第７ 日中サービス支援型指定共同生活援助の事業の設備に関する基準 | C3: 法第43条第2項
B4: ① 日中サービス支援型指定共同生活援助に係る共同生活住居は、住宅地又は住宅地と同程度に利用者の家族や地域住民との交流の機会が確保される地域にあり、かつ、入所施設又は病院の敷地外にあるようになっているか。 | C4: 平18厚令171 第213条の6 第1項 | D4: 建物の周辺図 平面図 【目視】
B5: ② 日中サービス支援型指定共同生活援助事業所は、1以上の共同生活住居を有するものとし、当該共同生活住居の入居定員の合計は4人以上となっているか。 | C5: 平18厚令171 第213条の6 第2項 | D5: 平面図 【目視】
B6: ③ 共同生活住居の配置、構造及び設備は、利用者の特性に応じて工夫したものとなっているか。 | C6: 平18厚令171 第213条の6 第3項 | D6: 平面図 設備・備品等一覧表 【目視】
B7: ④ 共同生活住居は、その入居定員は2人以上10人以下となっているか。 ただし、構造上、共同生活住居ごとの独立性が確保されており、利用者の支援に支障がない場合で、1つの建物に複数の共同生活住居を設けた場合において、1つの建物の入居定員の合計は20人以下となっているか。 | C7: 平18厚令171 第213条の6 第4項 | D7: 平面図 【目視】
B8: ⑤ 既存の建物を共同生活住居とする場合にあっては、当該共同生活住居の入居定員を2人以上20人(都道府県知事（指定都市及び中核市にあっては、指定都市又は中核市の市長。）が特に必要があると認めるときは30人)以下となっているか。 | C8: 平18厚令171 第213条の6 第5項 | D8: 平面図 【目視】
B9: ⑥ 既存の建物を共同生活住居とした共同生活住居を改築する場合であって、都道府県知事が特に必要があると認めるときは、④及び⑤の規定にかかわらず、当該共同生活住居の入居定員は2人以上30人以下（ただし、当該共同生活住居を改築する時点の入居定員と同数を上限とする。）となっているか。 | C9: 平18厚令171 第213条の6 第6項 | D9: 平面図 【目視】
B10: ⑦ 共同生活住居は、１以上のユニットを有するほか、日常生活を営む上で必要な設備を設けているか。 | C10: 平18厚令171 第213条の6 第7項 | D10: 平面図 設備・備品等一覧表 【目視】
B11: ⑧ ユニットの入居定員は、2人以上10人以下となっているか。 | C11: 平18厚令171 第213条の6 第8項 | D11: 平面図 【目視】
B12: ⑨ ユニットには、居室及び居室に近接して設けられる相互に交流を図ることができる設備を設けているか。その基準は次のとおりとなっているか。 ア 1の居室の定員は、1人とすること。 （ただし、利用者のサービス提供上必要と認められる場合は、2人とすることができる。） イ 1の居室の面積は、収納設備等を除き、7．43平方メートル以上とすること。 | C12: 平18厚令171 第213条の6 第9項 | D12: 平面図 設備・備品等一覧表 【目視】
A13: 第８ 日中サービス支援型指定共同生活援助の事業の運営に関する基準 | C13: 法第43条第2項
A14: １ 内容及び手続の説明及び同意 | B14: （１）日中サービス支援型指定共同生活援助事業者は、支給決定障害者等が日中サービス支援型指定共同生活援助の利用の申込みを行ったときは、当該利用申込者に係る障害の特性に応じた適切な配慮をしつつ、当該利用申込者に対し、運営規程の概要、従業者の勤務体制、その他の利用申込者のサービスの選択に資すると認められる重要事項を記した文書を交付して説明を行い、当該日中サービス支援型指定共同生活援助の提供の開始について当該利用申込者の同意を得ているか。 | C14: 平18厚令171 第213条の11 準用（第9条第1項） | D14: 重要事項説明書 利用契約書
B15: （２）日中サービス支援型指定共同生活援助事業者は、社会福祉法第77条の規定に基づき書面の交付を行う場合は、利用者の障害の特性に応じた適切な配慮をしているか。 | C15: 平18厚令171 第213条の11 準用（第9条 第2項） | D15: 重要事項説明書 利用契約書 その他利用者に交付した書面
A16: ２ 提供拒否の禁止 | B16: 日中サービス支援型指定共同生活援助事業者は、正当な理由がなく、日中サービス支援型指定共同生活援助の提供を拒んでいないか。 | C16: 平18厚令171 第213条の11 準用（第11条） | D16: 適宜必要と認める資料 | E16: 利用申込受付簿
A17: ３ 連絡調整に対する協力 | B17: 日中サービス支援型指定共同生活援助事業者は、日中サービス支援型指定共同生活援助の利用について市町村又は一般相談支援事業若しくは特定相談支援事業を行う者が行う連絡調整に、できる限り協力しているか。 | C17: 平18厚令171 第213条の11 準用（第12条） | D17: 適宜必要と認める資料 | E17: 相談支援専門員との連絡記録
A18: ４ 受給資格の確認 | B18: 日中サービス支援型指定共同生活援助事業者は、日中サービス支援型指定共同生活援助の提供を求められた場合は、その者の提示する受給者証によって、支給決定の有無、支給決定の有効期間、支給量等を確かめているか。 | C18: 平18厚令171 第213条の11 準用（第14条） | D18: 受給者証の写し
A19: ５ 訓練等給付費の支給の申請に係る援助 | B19: （１）日中サービス支援型指定共同生活援助事業者は、日中サービス支援型共同生活援助に係る支給決定を受けていない者から利用の申込みがあった場合は、その者の意向を踏まえて速やかに訓練等給付費の支給の申請が行われるよう必要な援助を行っているか。 | C19: 平18厚令171 第213条の11 準用（第15条 第1項） | D19: 適宜必要と認める資料 | E19: 利用申込記録
B20: （２）日中サービス支援型指定共同生活援助事業者は、日中サービス支援型共同生活援助に係る支給決定に通常要すべき標準的な期間を考慮し、支給決定の有効期間の終了に伴う訓練等給付費の支給申請について、必要な援助を行っているか。 | C20: 平18厚令171 第213条の11 準用（第15条 第2項） | D20: 適宜必要と認める資料 | E20: 受給者証期限管理表
A21: ６ 心身の状況等の把握 | B21: 日中サービス支援型指定共同生活援助事業者は、日中サービス支援型指定共同生活援助の提供に当たっては、利用者の心身の状況、その置かれている環境、他の保健医療サービス又は福祉サービスの利用状況等の把握に努めているか。 | C21: 平18厚令171 第213条の11 準用（第16条） | D21: アセスメント記録 ケース記録
A22: ７ 指定障害福祉サービス事業者等との連携等 | B22: （１）日中サービス支援型指定共同生活援助事業者は、日中サービス支援型指定共同生活援助を提供するに当たっては、地域及び家庭との結び付きを重視した運営を行い、市町村、他の指定障害福祉サービス事業者等その他の保健医療サービス又は福祉サービスを提供する者との密接な連携に努めているか。 | C22: 平18厚令171 第213条の11 準用（第17条第1項） | D22: 個別支援計画 ケース記録
B23: （２）日中サービス支援型指定共同生活援助事業者は、日中サービス支援型指定共同生活援助の提供の終了に際しては、利用者又はその家族に対して適切な援助を行うとともに、保健医療サービス又は福祉サービスを提供する者との密接な連携に努めているか。 | C23: 平18厚令171 第213条の11 準用（第17条第2項） | D23: 個別支援計画 ケース記録
A24: ８ サービスの提供の記録 | B24: （１）日中サービス支援型指定共同生活援助事業者は、日中サービス支援型指定共同生活援助を提供した際は、当該日中サービス支援型指定共同生活援助の提供日、内容その他必要な事項を記録しているか。 | C24: 平18厚令171 第213条の11 準用（第53条の2第1項） | D24: サービス提供の記録
B25: （２）日中サービス支援型指定共同生活援助事業者は、(1)の規定による記録に際しては、支給決定障害者等から日中サービス支援型指定共同生活援助を提供したことについて確認を受けているか。 | C25: 平18厚令171 第213条の11 準用（第53条の2第2項） | D25: サービス提供の記録
A26: ９ 入退居 | B26: （１）日中サービス支援型指定共同生活援助は、共同生活住居への入居を必要とする利用者(入院治療を要する者を除く。)に提供されているか。 | C26: 平18厚令171 第213条の11 準用（第210条の2第1項） | D26: 個別支援計画 サービス提供の記録 アセスメント記録
B27: （２）日中サービス支援型指定共同生活援助事業者は、利用申込者の入居に際しては、その者の心身の状況、生活歴、病歴等の把握に努めているか。 | C27: 平18厚令171 第213条の11 準用（第210条の2第2項） | D27: 個別支援計画 アセスメント記録 サービス担当者会議の記録
B28: （３）日中サービス支援型指定共同生活援助事業者は、利用者の退居の際は、利用者の希望を踏まえた上で、退居後の生活環境や援助の継続性に配慮し、退居に必要な援助を行い、又はこれに併せて居宅における自立した日常生活への移行後の定着に必要な援助を行っているか。 | C28: 平18厚令171 第213条の11 準用（第210条の2第3項） | D28: ケース記録 サービス提供の記録
B29: （４）日中サービス支援型指定共同生活援助事業者は、利用者の退居に際しては、利用者に対し、適切な援助を行うとともに、保健医療サービス又は福祉サービスを提供する者との密接な連携に努めているか。 | C29: 平18厚令171 第213条の11 準用（第210条の2第4項） | D29: 他サービスとの連携状況が分かる書類（ケース記録、サービス提供の記録等）
A30: 10 入退居の記録の記載等 | B30: （１）日中サービス支援型指定共同生活援助事業者は、入居者の入居又は退居に際しては、当該日中サービス支援型指定共同生活援助事業者の名称、入居又は退居の年月日その他の必要な事項(受給者証記載事項）を利用者の受給者証に記載しているか。 | C30: 平18厚令171 第213条の11 準用（第210条の3第1項） | D30: 適宜必要と認める資料 | E30: 受給者証写し
B31: （２）日中サービス支援型指定共同生活援助事業者は、受給者証記載事項その他必要な事項を遅滞なく市町村に対し報告しているか。 | C31: 平18厚令171 第213条の11 準用（第210条の3第2項） | D31: 適宜必要と認める資料 | E31: 契約内容報告書の提出控え
A32: 11 日中サービス支援型指定共同生活援助事業者が支給決定障害者等に求めることのできる金銭の支払の範囲等 | B32: （１）日中サービス支援型指定共同生活援助事業者が、日中サービス支援型指定共同生活援助を提供する支給決定障害者等に対して金銭の支払を求めることができるのは、当該金銭の使途が直接利用者の便益を向上させるものであって、当該支給決定障害者等に支払を求めることが適当であるものに限られているか。 | C32: 平18厚令171 第213条の11 準用（第20条 第1項) | D32: 適宜必要と認める資料 | E32: 重要事項説明書
B33: （２）(1)の規定により金銭の支払を求める際は、当該金銭の使途及び額並びに支給決定障害者等に金銭の支払を求める理由について書面によって明らかにするとともに、支給決定障害者等に対し説明を行い、その同意を得ているか。 | C33: 平18厚令171 第213条の11 準用（第20条 第2項） | D33: 適宜必要と認める資料 | E33: 重要事項説明書
B34: （ただし、12の(1)から(3)までに掲げる支払については、この限りでない。）
A35: 12 利用者負担額等の受領 | B35: （１）日中サービス支援型指定共同生活援助事業者は、日中サービス支援型指定共同生活援助を提供した際は、支給決定障害者から当該日中サービス支援型指定共同生活援助に係る利用者負担額の支払を受けているか。 | C35: 平18厚令171 第213条の11 準用（第210条の4第1項） | D35: 請求書 領収書
B36: （２）日中サービス支援型指定共同生活援助事業者は、法定代理受領を行わない日中サービス支援型指定共同生活援助を提供した際は、支給決定障害者から当該日中サービス支援型指定共同生活援助に係る指定障害福祉サービス等費用基準額の支払を受けているか。 | C36: 平18厚令171 第213条の11 準用（第210条の4第2項） | D36: 請求書 領収書
B37: （３）日中サービス支援型指定共同生活援助事業者は、(1)及び(2)の支払を受ける額のほか、日中サービス支援型指定共同生活援助において提供される便宜に要する費用のうち、支給決定障害者から受けることのできる次に掲げる費用の支払を受けているか。 | C37: 平18厚令171 第213条の11 準用（第210条の4第3項） | D37: 請求書 領収書
B38: ① 食材料費
B39: ② 家賃(障害者総合支援法第34条第1項の規定により特定障害者特別給付費が利用者に支給された場合(同条第2項において準用する同法第29条第4項の規定により特定障害者特別給付費が利用者に代わり当該日中サービス支援型指定共同生活援助事業者に支払われた場合に限る。)は、当該利用者に係る家賃の月額から同法第34条第2項において準用する同法第29条第5項の規定により当該利用者に支給があったものとみなされた特定障害者特別給付費の額を控除した額を限度とする。)
B40: ③ 光熱水費
B41: ④ 日用品費
B42: ⑤ ①から④のほか、日中サービス支援型指定共同生活援助において提供される便宜に要する費用のうち、日常生活においても通常必要となるものに係る費用であって、支給決定障害者に負担させることが適当と認められるもの
B43: （４）日中サービス支援型指定共同生活援助事業者は、(1)から(3)までに掲げる費用の額の支払を受けた場合は、当該費用に係る領収証を当該費用の額を支払った支給決定障害者に対し交付しているか。 | C43: 平18厚令171 第213条の11 準用（第210条の4第4項） | D43: 領収書
B44: （５）日中サービス支援型指定共同生活援助事業者は、(3)の費用に係るサービスの提供に当たっては、あらかじめ、支給決定障害者に対し、当該サービスの内容及び費用について説明を行い、支給決定障害者の同意を得ているか。 | C44: 平18厚令171 第213条の11 準用（第210条の4第5項） | D44: 重要事項説明書
A45: 13 利用者負担額に係る管理 | B45: （１）日中サービス支援型指定共同生活援助事業者は、支給決定障害者（入居前の体験的な日中サービス支援型指定共同生活援助を受けている者を除く。）が同一の月に当該日中サービス支援型指定共同生活援助事業者が提供する日中サービス支援型指定共同生活援助及び他の指定障害福祉サービス等を受けたときは、当該日中サービス支援型指定共同生活援助及び他の指定障害福祉サービス等に係る利用者負担額合計額を算定しているか。 この場合において、当該日中サービス支援型指定共同生活援助事業者は、利用者負担額合計額を市町村に報告するとともに、当該支給決定障害者及び当該他の指定障害福祉サービス等を提供した指定障害福祉サービス事業者等に通知しているか。 | C45: 平18厚令171 第213条の11 準用（第170条の2第1項） | D45: 適宜必要と認める資料 | E45: 利用者負担上限額管理結果票
B46: （２）日中サービス支援型指定共同生活援助事業者は、支給決定障害者（入居前の体験的な日中サービス支援型指定共同生活援助を受けている者に限る。）の依頼を受けて、当該支給決定障害者が同一の月に当該日中サービス支援型指定共同生活援助事業者が提供する日中サービス支援型指定共同生活援助及び他の指定障害福祉サービス等を受けたときは、当該日中サービス支援型指定共同生活援助及び他の指定障害福祉サービス等に係る利用者負担額合計額を算定しているか。 | C46: 平18厚令171 第213条の11 準用（第170条の2第2項） | D46: 適宜必要と認める資料 | E46: 利用者負担上限額管理結果票
B47: この場合において、当該日中サービス支援型指定共同生活援助事業者は、利用者負担額合計額を市町村に報告するとともに、当該支給決定障害者及び当該他の指定障害福祉サービス等を提供した指定障害福祉サービス事業者等に通知しているか。
A48: 14 訓練等給付費の額に係る通知等 | B48: （１）日中サービス支援型指定共同生活援助事業者は、法定代理受領により市町村から日中サービス支援型指定共同生活援助に係る訓練等給付費の支給を受けた場合は、支給決定障害者等に対し、当該支給決定障害者等に係る訓練等給付費の額を通知しているか。 | C48: 平18厚令171 第213条の11 準用（第23条第1項） | D48: 通知の写し
B49: （２）日中サービス支援型指定共同生活援助事業者は、法定代理受領を行わない日中サービス支援型指定共同生活援助に係る費用の支払を受けた場合は、その提供した日中サービス支援型指定共同生活援助の内容、費用の額その他必要と認められる事項を記載したサービス提供証明書を支給決定障害者等に対して交付しているか。 | C49: 平18厚令171 第213条の11 準用（第23条第2項） | D49: サービス提供証明書の写し
A50: 15 日中サービス支援型指定共同生活援助の取扱方針 | B50: （１）日中サービス支援型指定共同生活援助事業者は、日中サービス支援型指定共同生活援助に係る個別支援計画（日中サービス支援型共同生活援助計画）に基づき、利用者が地域において日常生活を営むことができるよう、当該利用者の身体及び精神の状況並びにその置かれている環境に応じて、その者の支援を適切に行うとともに、日中サービス支援型指定共同生活援助の提供が漫然かつ画一的なものとならないように配慮しているか。 | C50: 平18厚令171 第213条の11 準用（第210条の5第1項） | D50: 適宜必要と認める資料 | E50: 個別支援計画
B51: （２）日中サービス支援型指定共同生活援助事業者は、利用者が自立した日常生活又は社会生活を営むことができるよう、利用者の意思決定の支援に配慮しているか。 | C51: 平18厚令171 第213条の11 準用（第210条の5第2項） | D51: 適宜必要と認める資料 | E51: 意思決定支援記録
B52: （３）日中サービス支援型指定共同生活援助事業者は、入居前の体験的な利用を希望する者に対して日中サービス支援型指定共同生活援助の提供を行う場合には、日中サービス支援型共同生活援助計画に基づき、当該利用者が、継続した日中サービス支援型指定共同生活援助の利用に円滑に移行できるよう配慮するとともに、継続して入居している他の利用者の処遇に支障がないようにしているか。 | C52: 平18厚令171 第213条の11 準用（第210条の5第3項） | D52: 適宜必要と認める資料 | E52: 体験利用契約書
B53: （４）日中サービス支援型指定共同生活援助事業所の従業者は、日中サービス支援型指定共同生活援助の提供に当たっては、懇切丁寧を旨とし、利用者又はその家族に対し、支援上必要な事項について、理解しやすいように説明を行っているか。 | C53: 平18厚令171 第213条の11 準用（第210条の5第4項） | D53: 適宜必要と認める資料 | E53: 重要事項説明書
B54: （５）日中サービス支援型指定共同生活援助事業者は、その提供する日中サービス支援型指定共同生活援助の質の評価を行い、常にその改善を図っているか。 | C54: 平18厚令171 第213条の11 準用（第210条の5第5項） | D54: 適宜必要と認める資料 | E54: 自立支援協議会の評価記録
A55: 16 日中サービス支援型共同生活援助計画の作成等 | B55: （１）日中サービス支援型指定共同生活援助事業所の管理者は、サービス管理責任者に日中サービス支援型共同生活援助計画の作成に関する業務を担当させているか。 | C55: 平18厚令171 第213条の11 準用（第58条 第1項) | D55: 個別支援計画 サービス管理責任者が個別支援計画を作成していることが分かる書類
B56: （２）サービス管理責任者は、日中サービス支援型共同生活援助計画の作成に当たっては、適切な方法により、利用者について、その有する能力、その置かれている環境及び日常生活全般の状況等の評価を通じて利用者の希望する生活や課題等の把握（アセスメント）を行うとともに、利用者の自己決定の尊重及び意思決定の支援に配慮しつつ、利用者が自立した日常生活を営むことができるように支援する上での適切な支援内容の検討をしているか。 | C56: 平18厚令171 第213条の11 準用（第58条 第2項) | D56: 個別支援計画 アセスメントを実施したことが分かる記録
B57: （３）アセスメントに当たっては、利用者が自ら意思を決定することに困難を抱える場合には、適切に意思決定の支援を行うため、当該利用者の意思及び選好並びに判断能力等について丁寧に把握しているか。 | C57: 平18厚令171 第213条の11 準用（第58条 第3項) | D57: 個別支援計画 アセスメント及びモニタリングを実施したことが分かる記録
B58: （４）アセスメントに当たっては、利用者に面接して行っているか。 この場合において、サービス管理責任者は、面接の趣旨を利用者に対して十分に説明し、理解を得ているか。 | C58: 平18厚令171 第213条の11 準用（第58条 第4項) | D58: アセスメントを実施したことが分かる記録 面接記録
B59: （５）サービス管理責任者は、アセスメント及び支援内容の検討結果に基づき、利用者及びその家族の生活に対する意向、総合的な支援の方針、生活全般の質を向上させるための課題、日中サービス支援型指定共同生活援助の目標及びその達成時期、日中サービス支援型指定共同生活援助を提供する上での留意事項等を記載した日中サービス支援型共同生活援助計画の原案を作成しているか。 この場合において、当該日中サービス支援型指定共同生活援助事業所が提供する日中サービス支援型指定共同生活援助以外の保健医療サービス又はその他の福祉サービス等との連携も含めて日中サービス支援型共同生活援助計画の原案に位置付けるよう努めているか。 | C59: 平18厚令171 第213条の11 準用（第58条 第5項) | D59: 個別支援計画の原案 他サービスとの連携状況が分かる書類
B60: （６）サービス管理責任者は、日中サービス支援型共同生活援助計画の作成に係る会議（利用者及び当該利用者に対する日中サービス支援型指定共同生活援助事業所の提供に当たる担当者等を招集して行う会議をいい、テレビ電話装置等の活用可能。）を開催し、当該利用者の生活に対する移行等を改めて確認するとともに、日中サービス支援型共同生活援助計画の原案の内容について意見を求めているか。 | C60: 平18厚令171 第213条の11 準用（第58条 第6項) | D60: サービス担当者会議の記録
B61: （７）サービス管理責任者は、(5)に規定する日中サービス支援型共同生活援助計画の原案の内容について利用者又はその家族に対して説明し、文書により利用者の同意を得ているか。 | C61: 平18厚令171 第213条の11 準用（第58条 第7項) | D61: 個別支援計画
B62: （８）サービス管理責任者は、日中サービス支援型共同生活援助計画を作成した際には、当該日中サービス支援型共同生活援助計画を利用者及び指定特定相談支援事業者に交付しているか。 | C62: 平18厚令171 第213条の11 準用（第58条 第8項) | D62: 利用者及び指定特定相談支援事業者に交付した記録 個別支援計画
B63: （９）サービス管理責任者は、日中サービス支援型共同生活援助計画の作成後、日中サービス支援型共同生活援助計画の実施状況の把握（モニタリング（利用者についての継続的なアセスメントを含む。）)を行うとともに、少なくとも6月に1回以上、日中サービス支援型共同生活援助計画の見直しを行い、必要に応じて日中サービス支援型共同生活援助計画の変更を行っているか。 | C63: 平18厚令171 第213条の11 準用（第58条 第9項) | D63: 個別支援計画 アセスメント及びモニタリングに関する記録
B64: （10）サービス管理責任者は、モニタリングに当たっては、利用者及びその家族等との連絡を継続的に行うこととし、特段の事情のない限り、次に定めるところにより行っているか。 ①定期的に利用者に面接すること。 ②定期的にモニタリングの結果を記録すること。 | C64: 平18厚令171 第213条の11 準用（第58条 第10項) | D64: モニタリング記録 面接記録
B65: （11）日中サービス支援型共同生活援助計画に変更のあった場合、(2)から(8)に準じて取り扱っているか。 | C65: 平18厚令171 第213条の11 準用（第58条 第11項 | D65: (2)から(8)に掲げる確認資料
A66: 17 サービス管理 責任者の責務 | B66: （１）サービス管理責任者は、日中サービス支援型共同生活援助計画の作成等のほか、次に掲げる業務を行っているか。 | C66: 平18厚令171 第213条の11 準用（第210条の6第１項）
B67: ① 利用申込者の利用に際し、その者に係る指定障害福祉サービス事業者等に対する照会等により、その者の身体及び精神の状況、当該日中サービス支援型指定共同生活援助事業所以外における指定障害福祉サービス等の利用状況等を把握すること。 | D67: 個別支援計画 アセスメント及びモニタリングに関する記録
B68: ② 利用者の身体及び精神の状況、その置かれている環境等に照らし、利用者が自立した日常生活を営むことができるよう定期的に検討するとともに、自立した日常生活を営むことができると認められる利用者に対し、必要な支援を行うこと。 | D68: 個別支援計画 アセスメント及びモニタリングに関する記録 サービス提供の記録
B69: ③ 利用者が自立した社会生活を営むことができるよう指定生活介護事業所等との連絡調整を行うこと。 | D69: 指定生活介護事業所等との連絡調整した記録
B70: ④ 他の従事者に対する技術的指導及び助言を行うこと。 | D70: 他の従業者に指導及び助言した記録
B71: （２）サービス管理者は、業務を行うに当たっては、利用者の自己決定の尊重を原則とした上で、利用者が自ら意思を決定することに困難を抱える場合には、適切に利用者への意思決定の支援が行われるように努めているか。 | C71: 平18厚令171 第213条の11 準用（第210条の6第2項） | D71: 適宜必要と認める資料 | E71: 個別支援計画
A72: 18 実施主体 | B72: 日中サービス支援型指定共同生活援助事業者は、当該日中サービス支援型指定共同生活援助と同時に指定障害福祉サービス基準第114条に規定する指定短期入所（同基準第115条第1項に規定する併設事業所又は同基準同条第3項に規定する単独型事業所に係るものに限る。）を行うものとなっているか。 | C72: 平18厚令171 第213条の7 平18厚令171 第115条第1項、第3項 | D72: 適宜必要と認める資料 | E72: 短期入所の指定通知書
A73: 19 相談及び援助 | B73: 日中サービス支援型指定共同生活援助事業者は、常に利用者の心身の状況、その置かれている環境等の的確な把握に努め、利用者又はその家族に対し、その相談に適切に応じるとともに、必要な助言その他の援助を行っているか。 | C73: 平18厚令171 第213条の11 準用（第60条） | D73: 適宜必要と認める資料 | E73: 相談受付記録
A74: 20 介護及び家事等 | B74: （１）介護は、利用者の身体及び精神の状況に応じ、当該利用者の自立の支援及び日常生活の充実に資するよう、適切な技術をもって行っているか。 | C74: 平18厚令171 第213条の8 第1項 | D74: 個別支援計画 サービス提供の記録 業務日誌等
B75: （２）調理、洗濯その他の家事等は、原則として利用者と従業者が共同で行うよう努めているか。 | C75: 平18厚令171 第213条の8 第2項 | D75: 個別支援計画 サービス提供の記録 業務日誌等
B76: （３）日中サービス支援型指定共同生活援助事業者は、常時1人以上の従業者を介護又は家事等に従事させているか。 | C76: 平18厚令171 第213条の8 第3項 | D76: 勤務実績表 出勤簿（タイムカード） 従業員の資格証 勤務体制一覧表
B77: （４）日中サービス支援型指定共同生活援助事業者は、その利用者に対して、当該利用者の負担により、当該日中サービス支援型指定共同生活援助事業所の従業者以外の者による介護又は家事等を受けさせていないか。 | C77: 平18厚令171 第213条の8 第4項 | D77: 従業者名簿 雇用契約書 個別支援計画 サービス提供の記録 業務日誌等
A78: 21 社会生活上の便宜の供与等 | B78: （１）日中サービス支援型指定共同生活援助事業者は、利用者の身体及び精神の状況又はその置かれている環境等に応じて、利用者の意向に基づき、社会生活上必要な支援を適切に行っているか。 | C78: 平18厚令171 第213条の9 第1項 | D78: 適宜必要と認める資料 | E78: 個別支援計画
B79: （２）日中サービス支援型指定共同生活援助事業者は、利用者について、特定相談支援事業を行う者又は他の障害福祉サービスの事業を行う者等との連絡調整に努めているか。 | C79: 平18厚令171 第213条の9 第2項 | D79: 適宜必要と認める資料 | E79: 相談支援専門員との連絡記録
B80: （３）日中サービス支援型指定共同生活援助事業者は、利用者が日常生活を営む上で必要な行政機関に対する手続等について、その者又はその家族が行うことが困難である場合は、その者の同意を得て代わって行っているか。 | C80: 平18厚令171 第213条の9 第3項 | D80: 適宜必要と認める資料 | E80: 行政手続き代行同意書
B81: （４）日中サービス支援型指定共同生活援助事業者は、常に利用者の家族との連携を図るとともに、利用者とその家族との交流等の機会を確保するよう努めているか。 | C81: 平18厚令171 第213条の9 第4項 | D81: 適宜必要と認める資料 | E81: 家族連絡記録
A82: 22 地域との連携 | B82: （１）日中サービス支援型指定共同生活援助事業者は、日中サービス支援型指定共同生活援助の提供に当たっては、地域住民又はその自発的な活動等との連携及び協力を行う等の地域との交流を図っているか。 | C82: 平18厚令171 第213条の10 第1項 | D82: 適宜必要と認める資料 | E82: 地域交流記録
B83: （２）日中サービス支援型指定共同生活援助事業者は、日中サービス支援型指定共同生活援助の提供に当たっては、地域連携推進会議を開催し、おおむね一年に一回以上、地域連携推進会議において、事業の運営に係る状況を報告するとともに、必要な要望、助言等を聴く機会を設けているか。 | C83: 平18厚令171 第213条の10 第2項 | D83: 適宜必要と認める資料 | E83: 地域連携推進会議議事録
B84: （３）日中サービス支援型指定共同生活援助事業者は、地域連携推進会議の開催のほか、おおむね一年に一回以上、当該地域連携推進会議の構成員が日中サービス支援型指定共同生活援助事業所を見学する機会を設けているか。 | C84: 平18厚令171 第213条の10 第3項 | D84: 適宜必要と認める資料 | E84: 見学実施記録
B85: （４）日中サービス支援型指定共同生活援助事業者は、(2)の報告、要望、助言等についての記録を作成するとともに、当該記録を公表しているか。 | C85: 平18厚令171 第213条の10 第4項 | D85: 適宜必要と認める資料 | E85: 地域連携推進会議議事録
B86: （５）(2)から(4)までに掲げる規定において、日中サービス支援型指定共同生活援助事業者がその提供する日中サービス支援型指定共同生活援助の質に係る外部の者による評価及び当該評価の実施状況の公表又はこれに準ずる措置として都道府県知事（指定都市及び中核市にあっては指定都市及び中核市の市長）が定めるもの（次項に規定するものを除く。）を講じている場合には、適用しない。 | C86: 平18厚令171 第213条の10 第5項 | D86: 適宜必要と認める資料 | E86: 外部評価結果報告書
B87: （６）日中サービス支援型指定共同生活援助事業者は、日中サービス支援型指定共同生活援助の提供に当たっては、法第89条の3第1項に規定する協議会その他都道府県知事がこれに準ずるものとして特に認めるもの（協議会等）に対して定期的に日中サービス支援型指定共同生活援助の事業の実施状況及び⑵に掲げる報告、要望、助言等の内容又は⑸に掲げる評価の結果等を報告し、協議会等による評価を受けるとともに、協議会等から必要な要望、助言等を聴く機会を設けているか。 | C87: 平18厚令171 第213条の10 第6項 | D87: 適宜必要と認める資料 | E87: 協議会等への報告書
B88: （７）日中サービス支援型指定共同生活援助事業者は、⑹に掲げる協議会等における報告、評価、要望、助言等についての記録を整備しているか。 | C88: 平18厚令171 第213条の10 第7項 | D88: 適宜必要と認める資料 | E88: 協議会議事録
A89: 23 緊急時等の対応 | B89: 従業者は、現に日中サービス支援型指定共同生活援助の提供を行っているときに利用者に病状の急変が生じた場合その他必要な場合は、速やかに医療機関への連絡を行う等の必要な措置を講じているか。 | C89: 平18厚令171 第213条の11 準用（第28条） | D89: 緊急時対応マニュアル ケース記録 事故等の対応記録
A90: 24 支給決定障害者に関する市町村への通知 | B90: 日中サービス支援型指定共同生活援助事業者は、日中サービス支援型指定共同生活援助を受けている支給決定障害者が次のいずれかに該当する場合は、遅滞なく、意見を付してその旨を市町村に通知しているか。 | C90: 平18厚令171 第213条の11 準用（第88条） | D90: 適宜必要と認める資料 | E90: 市町村通知書
B91: ① 正当な理由なしに日中サービス支援型指定共同生活援助の利用に関する指示に従わないことにより、障害の状態等を悪化させたと認められるとき。
B92: ② 偽りその他不正な行為によって訓練等給付費又は特例訓練等給付費を受け、又は受けようとしたとき。
A93: 25 管理者の責務 | B93: （１）日中サービス支援型指定共同生活援助事業所の管理者は、当該日中サービス支援型指定共同生活援助事業所の従業者及び業務の管理その他の管理を一元的に行っているか。 | C93: 平18厚令171 第213条の11 準用（第66条 第1項) | D93: 適宜必要と認める資料 | E93: 勤務表
B94: （２）日中サービス支援型指定共同生活援助事業所の管理者は、当該日中サービス支援型指定共同生活援助事業所の従業者に指定障害福祉サービス基準第16章第5節の規定を遵守させるため必要な指揮命令を行っているか。 | C94: 平18厚令171 第213条の11 準用（第66条 第2項) | D94: 適宜必要と認める資料 | E94: 職員会議録
A95: 26 運営規程 | B95: 日中サービス支援型指定共同生活援助事業者は、指定共同生活援助事業所ごとに、次に掲げる事業の運営についての重要事項に関する運営規程を定めているか。 ① 事業の目的及び運営の方針 ② 従業者の職種、員数及び職務の内容 ③ 入居定員 ④ 指定共同生活援助の内容並びに支給決定障害者から受領する費用の種類及びその額 ⑤ 入居に当たっての留意事項 ⑥ 緊急時等における対応方法 ⑦ 非常災害対策 ⑧ 事業の主たる対象とする障害の種類を定めた場合には当該障害の種類 ⑨ 虐待の防止のための措置に関する事項 ⑩ その他運営に関する重要事項 | C95: 平18厚令171 第213条の11 準用（第211条の3） | D95: 運営規程
A96: 27 勤務体制の確保等 | B96: （１）日中サービス支援型指定共同生活援助事業者は、利用者に対し、適切な日中サービス支援型指定共同生活援助を提供できるよう、指定共同生活援助事業所ごとに、従業者の勤務の体制を定めているか。 | C96: 平18厚令171 第213条の11 準用（第212条第1項） | D96: 従業者の勤務表
B97: （２）(1)の従業者の勤務の体制を定めるに当たっては、利用者が安心して日常生活を送ることができるよう、継続性を重視した日中サービス支援型指定共同生活援助の提供に配慮しているか。 | C97: 平18厚令171 第213条の11 準用（第212条第2項） | D97: 個別支援計画 ケース記録
B98: （３）日中サービス支援型指定共同生活援助事業者は、日中サービス支援型指定共同生活援助事業所ごとに、当該日中サービス支援型指定共同生活援助事業所の従業者によって指定共同生活援助を提供しているか。（ただし、当該日中サービス支援型指定共同生活援助事業者が業務の管理及び指揮命令を確実に行うことができる場合はこの限りではない。） | C98: 平18厚令171 第213条の11 準用（第212条第3項） | D98: 勤務形態一覧表または雇用形態が分かる書類
B99: （４）日中サービス支援型指定共同生活援助事業者は、(3)ただし書により日中サービス支援型指定共同生活援助に係る生活支援員の業務の全部又は一部を委託により他の事業者に行わせる場合にあっては、当該事業者の業務の実施状況について定期的に確認し、その結果等を記録しているか。 | C99: 平18厚令171 第213条の11 準用（第212条第4項） | D99: 委託契約書 業務報告書
B100: （５）日中サービス支援型指定共同生活援助事業者は、従業者の資質の向上のために、その研修の機会を確保しているか。 | C100: 平18厚令171 第213条の11 準用（第212条第5項） | D100: 研修計画、研修実施記録
...

Sheet 指定共同生活援助（外部サービス利用型）
A2: （注）下線を付した項目が標準確認項目
A3: 確認項目 | B3: 確認事項 | C3: 根拠法令 | D3: 関係書類 | E3: 確認書類（１つ） | F3: 判定
A4: 第９ 外部サービス利用型指定共同生活援助の事業の基本方針 | C4: 法第43条
B5: （１）外部サービス利用型指定共同生活援助事業者は、利用者の意向、適性、障害の特性その他の事情を踏まえた計画（個別支援計画）を作成し、これに基づき利用者に対して外部サービス利用型指定共同生活援助を提供するとともに、その効果について継続的な評価を実施することその他の措置を講ずることにより利用者に対して適切かつ効果的に外部サービス利用型指定共同生活援助を提供しているか。 | C5: 平18厚令171 第3条第1項 | D5: 運営規程 個別支援計画 ケース記録
B6: （２）外部サービス利用型指定共同生活援助事業者は、利用者の意思及び人格を尊重して、常に当該利用者の立場に立った外部サービス利用型指定共同生活援助の提供に努めているか。 | C6: 平18厚令171 第3条第2項 | D6: 運営規程 個別支援計画 ケース記録
B7: （３）外部サービス利用型指定共同生活援助事業者は、利用者の人権の擁護、虐待の防止等のため、必要な体制の整備を行うとともに、その従業者に対し、研修を実施する等の措置を講じているか。 | C7: 平18厚令171 第3条第3項 | D7: 運営規程 研修計画、研修実施記録 虐待防止関係書類 体制の整備をしていることが分かる書類
B8: （４）外部サービス利用型指定共同生活援助の事業は、外部サービス利用型共同生活援助計画に基づき、受託居宅介護サービス事業者による受託居宅介護サービスを適切かつ円滑に提供することにより、利用者が地域において共同して自立した日常生活又は社会生活を営むことができるよう、当該利用者の身体及び精神の状況並びにその置かれている環境に応じて共同生活住居において、相談、入浴、排泄若しくは食事の介護その他の日常生活上の援助又はこれに併せて行われる居宅における自立した日常生活への移行及び移行後の定着に必要な援助を適切かつ効果的に行っているか。 | C8: 平18厚令171 第213条の13 | D8: 運営規程 個別支援計画 ケース記録
A9: 第10 外部サービス利用型指定共同生活援助の事業の人員に関する基準 | C9: 法第43条第1項
A10: １ 外部サービス利用型指定共同生活援助事業所の従業者の員数 | B10: 外部サービス利用型指定共同生活援助事業所に置くべき基本サービスを提供する従業者及びその員数は、次のとおりになっているか。 | C10: 平18厚令171 第213条の14 第1項
A11: （１）世話人 | B11: 外部サービス利用型指定共同生活援助事業所ごとに、常勤換算方法で、利用者の数を6で除した数以上となっているか。（ただし、平成26年4月1日に現に存する指定共同生活援助事業所における世話人の員数については、当分の間、常勤換算方法で、当該外部サービス利用型指定共同生活援助事業所の利用者の数を10で除した数以上となっているか。） | C11: 平18厚令171 第213条の14 第1項第1号 | D11: 勤務実績表 出勤簿（タイムカード） 従業員の資格証 勤務体制一覧表 利用者数（平均利用人数）が分かる書類（実績表等）
A12: （２）サービス管理責任者 | B12: 外部サービス利用型指定共同生活援助事業所ごとに、①又は②に掲げる利用者の数の区分に応じ、それぞれ①又は②に掲げる数となっているか。 ① 利用者の数が30以下 1以上 ② 利用者の数が31以上 1に利用者の数が30を超えて30又はその端数を増すごとに1を加えて得た数以上 | C12: 平18厚令171 第213条の14 第1項第2号 | D12: 勤務実績表 出勤簿（タイムカード） 従業員の資格証 勤務体制一覧表 利用者数（平均利用人数）が分かる書類（実績表等）
A13: （３）利用者数の 算定 | B13: (1)及び(2)の利用者の数は、前年度の平均値となっているか。ただし、新規に指定を受ける場合は、適切な推定数により算定されているか。 | C13: 平18厚令171 第213条の14 第2項 | D13: 利用者数（平均利用人数）が分かる書類（利用者名簿等）
A14: （４）職務の専従 | B14: (1)及び(2)に規定する外部サービス利用型指定共同生活援助事業者の従業者は､専ら外部サービス利用型指定共同生活援助事業所の職務に従事する者となっているか。 （ただし、利用者の支援に支障がない場合はこの限りでない。） | C14: 平18厚令171 第213条の14 第3項 | D14: 従業者の勤務実態の分かる書類 （出勤簿等）
A15: （５）管理者 | B15: ① 外部サービス利用型指定共同生活援助事業所ごとに専らその職務に従事する常勤の管理者を置いているか。 （ただし、外部サービス利用型指定共同生活援助事業所の管理上支障がない場合は、当該外部サービス利用型指定共同生活援助事業所の他の職務に従事させ、又は他の事業所、施設等の職務に従事させることができる。） | C15: 平18厚令171 第213条の14 第3項 | D15: 管理者の雇用形態が分かる書類 管理者の勤務実績表（タイムカード）
B16: ② 外部サービス利用型指定共同生活援助事業所の管理者は、適切な外部サービス利用型指定共同生活援助を提供するために必要な知識及び経験を有する者となっているか。 | C16: 平18厚令171 第213条の15 準用（第209条第2項） | D16: 管理者に必要な知識や経験があることが分かる書類（資格証、研修修了証等）
A17: 第11 外部サービス利用型指定共同生活援助の事業の設備に関する基準 | C17: 法第43条第2項
B18: ① 外部サービス利用型指定共同生活援助に係る共同生活住居は、住宅地又は住宅地と同程度に利用者の家族や地域住民との交流の機会が確保される地域にあり、かつ、入所により日中及び夜間を通してサービスを提供する施設（入所施設）又は病院の敷地外にあるようになっているか。 | C18: 平18厚令171 第213条の16 準用（第210条第1項） | D18: 建物の周辺図 平面図 【目視】
B19: ② 外部サービス利用型指定共同生活援助事業所は、１以上の共同生活住居（サテライト型住居を除く。以下この②、④から⑥までにおいて同じ。）を有するものとし、当該共同生活住居及びサテライト型住居の入居定員の合計は4人以上となっているか。 | C19: 平18厚令171 第213条の16 準用（第210条第2項） | D19: 平面図 【目視】
B20: ③ 共同生活住居の配置、構造及び設備は、利用者の特性に応じて工夫したものとなっているか。 | C20: 平18厚令171 第213条の16 準用（第210条第3項） | D20: 平面図 設備・備品等一覧表 【目視】
B21: ④ 共同生活住居は、その入居定員は2人以上10人以下となっているか。 ただし、既存の建物を共同生活住居とする場合にあっては、当該共同生活住居の入居定員は2人以上20人（都道府県知事（指定都市及び中核市にあっては、指定都市又は中核市の市長。）が特に必要があると認めるときは30人）以下となっているか。 | C21: 平18厚令171 第213条の16 準用（第210条第4項） | D21: 平面図 【目視】
B22: ⑤ 既存の建物を共同生活住居とした共同生活住居を改築する場合であって、都道府県知事が特に必要があると認めるときは、④の規定にかかわらず、当該共同生活住居の入居定員は2人以上30人以下（ただし、当該共同生活住居を改築する時点の入居定員と同数を上限とする。）となっているか。 | C22: 平18厚令171 第213条の16 準用（第210条第5項） | D22: 平面図 【目視】
B23: ⑥ 共同生活住居は、１以上のユニットを有するほか、日常生活を営む上で必要な設備を設けているか。 | C23: 平18厚令171 第213条の16 準用（第210条第6項） | D23: 平面図 設備・備品等一覧表 【目視】
B24: ⑦ ユニットの入居定員は、2人以上10人以下となっているか。 | C24: 平18厚令171 第213条の16 準用（第210条第7項） | D24: 平面図 【目視】
B25: ⑧ ユニットには、居室及び居室に近接して設けられる相互に交流を図ることができる設備を設けているか。その基準は次のとおりとなっているか。 ア １の居室の定員は、１人とすること。 （ただし、利用者のサービス提供上必要と認められる場合は、２人とすることができる。） イ １の居室の面積は、収納設備等を除き、7．43平方メートル以上とすること。 | C25: 平18厚令171 第213条の16 準用（第210条第8項） | D25: 平面図 設備・備品等一覧表 【目視】
B26: ⑨ サテライト型住居の基準は、次のとおりとなっているか。 ア 入居定員を１人とすること。 イ 日常生活を営む上で必要な設備を設けること。 ウ 居室の面積は、収納設備等を除き、7．43平方メートル以上とすること。 | C26: 平18厚令171 第213条の16 準用（第210条第9項） | D26: 平面図 設備・備品等一覧表 【目視】
B27: （経過措置）
B28: （１）平成18年厚生労働省令第171号（指定障害福祉サービス基準）の施行日（施行日）において現に入所施設又は病院の敷地内に存する建物を共同生活住居として指定共同生活援助の事業を行う外部サービス利用型指定共同生活援助事業者は、第11の①の規定にかかわらず、当該建物を共同生活住居とする外部サービス利用型指定共同生活援助の事業を行うことができる。 | C28: 平18厚令171 附則第12条 | D28: 適宜必要と認める資料 | E28: 施行日時点の指定通知書
B29: （２）外部サービス利用型指定共同生活援助事業者は、施行日において現に存する共同生活援助事業所において、外部サービス利用型指定共同生活援助の事業を行う場合には、当該事業所の共同生活住居（基本的な設備が完成しているものを含み、指定障害福祉サービス基準の施行の後に増築され、又は改築される等建物の構造を変更したものを除く。）が満たすべき設備に関する基準については、第11の⑦及び⑧の規定にかかわらず、平成18年厚生労働省令第58号（旧指定基準）第109条第2項及び第3項に定める基準によることができる。 | C29: 平18厚令171 附則第18条 | D29: 適宜必要と認める資料 | E29: 旧指定基準時代の指定通知書
B30: （３）施行日において現に存する身体障害者福祉ホーム、精神障害者生活訓練施設、指定知的障害者通勤寮若しくは知的障害者福祉ホーム又は旧精神障害者福祉ホ－ム（基本的な設備が完成しているものを含み、指定障害福祉サービス基準の施行の後に増築され、又は改築される等建物の構造を変更したものを除く。）において行われる外部サービス利用型指定共同生活援助の事業について、第7の規定を適用する場合においては、当分の間、第11の⑦中「2人以上10人以下」とあるのは「2人以上30人以下」とし、第11の⑧のイの規定は、旧精神障害者福祉ホーム(障害者総合支援法施行令附則第8条の2に規定する厚生労働大臣が定めるものを除く。)を除き、当分の間、適用しない。 | C30: 平18厚令171 附則第19条 | D30: 適宜必要と認める資料 | E30: 旧施設種別の指定通知書
A31: 第12 外部サービス利用型指定共同生活援助の事業の運営に関する基準 | C31: 法第43条第2項
A32: １ 内容及び手続の説明及び同意 | B32: （１）外部サービス利用型指定共同生活援助事業者は、支給決定障害者等が外部サービス利用型指定共同生活援助の利用の申込みを行ったときは、当該利用申込者に係る障害の特性に応じた適切な配慮をしつつ、当該利用申込者に対し、運営規程の概要、従業者の勤務体制、外部サービス利用型指定共同生活援助事業者と受託居宅介護サービス事業者の業務の分担の内容、受託居宅介護サービス事業者及び受託居宅介護サービス事業所の名称その他の利用申込者のサービスの選択に資すると認められる重要事項を記した文書を交付して説明を行い、当該外部サービス利用型指定共同生活援助の提供の開始について当該利用申込者の同意を得ているか。 | C32: 平18厚令171 第213条の17 第1項 | D32: 重要事項説明書 利用契約書
B33: （２）外部サービス利用型指定共同生活援助事業者は、社会福祉法第77条の規定に基づき、書面の交付を行う場合は、利用者の障害の特性に応じた適切な配慮をしているか。 | C33: 平18厚令171 第213条の17 第2項 | D33: 重要事項説明書 利用契約書 その他利用者に交付した書面
A34: ２ 提供拒否の禁止 | B34: 外部サービス利用型指定共同生活援助事業者は、正当な理由がなく、外部サービス利用型指定共同生活援助の提供を拒んでいないか。 | C34: 平18厚令171 第213条の22 準用（第11条） | D34: 適宜必要と認める資料 | E34: 利用申込受付票
A35: ３ 連絡調整に対する協力 | B35: 外部サービス利用型指定共同生活援助事業者は、外部サービス利用型指定共同生活援助の利用について市町村又は一般相談支援事業若しくは特定相談支援事業を行う者が行う連絡調整に、できる限り協力しているか。 | C35: 平18厚令171 第213条の22 準用（第12条） | D35: 適宜必要と認める資料 | E35: 相談支援専門員との連絡記録
A36: ４ 受給資格の確認 | B36: 外部サービス利用型指定共同生活援助事業者は、外部サービス利用型指定共同生活援助の提供を求められた場合は、その者の提示する受給者証によって、支給決定の有無、支給決定の有効期間、支給量等を確かめているか。 | C36: 平18厚令171 第213条の22 準用（第14条） | D36: 受給者証の写し
A37: ５ 訓練等給付費の支給の申請に係る援助 | B37: （１）外部サービス利用型指定共同生活援助事業者は、外部サービス利用型共同生活援助に係る支給決定を受けていない者から利用の申込みがあった場合は、その者の意向を踏まえて速やかに訓練等給付費の支給の申請が行われるよう必要な援助を行っているか。 | C37: 平18厚令171 第213条の22 準用（第15条 第1項） | D37: 適宜必要と認める資料 | E37: 利用申込記録
B38: （２）外部サービス利用型指定共同生活援助事業者は、外部サービス利用型共同生活援助に係る支給決定に通常要すべき標準的な期間を考慮し、支給決定の有効期間の終了に伴う訓練等給付費の支給申請について、必要な援助を行っているか。 | C38: 平18厚令171 第213条の22 準用（第15条 第2項） | D38: 適宜必要と認める資料 | E38: 受給者証期限管理表
A39: ６ 心身の状況等の把握 | B39: 外部サービス利用型指定共同生活援助事業者は、外部サービス利用型指定共同生活援助の提供に当たっては、利用者の心身の状況、その置かれている環境、他の保健医療サービス又は福祉サービスの利用状況等の把握に努めているか。 | C39: 平18厚令171 第213条の22 準用（第16条） | D39: アセスメント記録 ケース記録
A40: ７ 指定障害福祉 サービス事業者等との連携等 | B40: （１）外部サービス利用型指定共同生活援助事業者は、外部サービス利用型指定共同生活援助を提供するに当たっては、地域及び家庭との結び付きを重視した運営を行い、市町村、他の指定障害福祉サービス事業者等その他の保健医療サービス又は福祉サービスを提供する者との密接な連携に努めているか。 | C40: 平18厚令171 第213条の22 準用（第17条第1項） | D40: 個別支援計画 ケース記録
B41: （２）外部サービス利用型指定共同生活援助事業者は、外部サービス利用型指定共同生活援助の提供の終了に際しては、利用者又はその家族に対して適切な援助を行うとともに、保健医療サービス又は福祉サービスを提供する者との密接な連携に努めているか。 | C41: 平18厚令171 第213条の22 準用（第17条第2項） | D41: 個別支援計画 ケース記録
A42: ８ サービスの提供の記録 | B42: （１）外部サービス利用型指定共同生活援助事業者は、外部サービス利用型指定共同生活援助を提供した際は、当該外部サービス利用型指定共同生活援助の提供日、内容その他必要な事項を記録しているか。 | C42: 平18厚令171 第213条の22 準用（第53条の2第1項） | D42: サービス提供の記録
B43: （２）外部サービス利用型指定共同生活援助事業者は、(1)の規定による記録に際しては、支給決定障害者等から外部サービス利用型指定共同生活援助を提供したことについて確認を受けているか。 | C43: 平18厚令171 第213条の22 準用（第53条の2第2項） | D43: サービス提供の記録
A44: ９ 入退居 | B44: （１）外部サービス利用型指定共同生活援助は、共同生活住居への入居を必要とする利用者(入院治療を要する者を除く。)に提供されているか。 | C44: 平18厚令171 第213条の22 準用（第210条の2第1項） | D44: 個別支援計画 サービス提供の記録 アセスメント記録
B45: （２）外部サービス利用型指定共同生活援助事業者は、利用申込者の入居に際しては、その者の心身の状況、生活歴、病歴等の把握に努めているか。 | C45: 平18厚令171 第213条の22 準用（第210条の2第2項） | D45: 個別支援計画 アセスメント記録 サービス担当者会議の記録
B46: （３）外部サービス利用型指定共同生活援助事業者は、利用者の退居の際は、利用者の希望を踏まえた上で、退居後の生活環境や援助の継続性に配慮し、退居に必要な援助を行い、又はこれに併せて居宅における自立した日常生活への移行後の定着に必要な援助を行っているか。 | C46: 平18厚令171 第213条の22 準用（第210条の2第3項） | D46: ケース記録 サービス提供の記録
B47: （４）外部サービス利用型指定共同生活援助事業者は、利用者の退居に際しては、利用者に対し、適切な援助を行うとともに、保健医療サービス又は福祉サービスを提供する者との密接な連携に努めているか。 | C47: 平18厚令171 第213条の22 準用（第210条の2第4項） | D47: 他サービスとの連携状況が分かる書類（ケース記録、サービス提供の記録等）
A48: 10 入退居の記録の記載等 | B48: （１）外部サービス利用型指定共同生活援助事業者は、入居者の入居又は退居に際しては、当該外部サービス利用型指定共同生活援助事業者の名称、入居又は退居の年月日その他の必要な事項(受給者証記載事項）を利用者の受給者証に記載しているか。 | C48: 平18厚令171 第213条の22 準用（第210条の3第1項） | D48: 適宜必要と認める資料 | E48: 受給者証写し
B49: （２）外部サービス利用型指定共同生活援助事業者は、受給者証記載事項その他必要な事項を遅滞なく市町村に対し報告しているか。 | C49: 平18厚令171 第213条の22 準用（第210条の3第2項） | D49: 適宜必要と認める資料 | E49: 契約内容報告書
A50: 11 外部サービス利用型指定共同生活援助事業者が支給決定障害者等に求めることのできる金銭の支払の範囲等 | B50: （１）外部サービス利用型指定共同生活援助事業者が、外部サービス利用型指定共同生活援助を提供する支給決定障害者等に対して金銭の支払を求めることができるのは、当該金銭の使途が直接利用者の便益を向上させるものであって、当該支給決定障害者等に支払を求めることが適当であるものに限られているか。 | C50: 平18厚令171 第213条の22 準用（第20条 第1項) | D50: 適宜必要と認める資料 | E50: 重要事項説明書
B51: （２）(1)の規定により金銭の支払を求める際は、当該金銭の使途及び額並びに支給決定障害者等に金銭の支払を求める理由について書面によって明らかにするとともに、支給決定障害者等に対し説明を行い、その同意を得ているか。 （ただし、12の(1)から(3)までに掲げる支払については、この限りでない。） | C51: 平18厚令171 第213条の22 準用（第20条 第2項） | D51: 適宜必要と認める資料 | E51: 重要事項説明書同意書
A52: 12 利用者負担額等の受領 | B52: （１）外部サービス利用型指定共同生活援助事業者は、外部サービス利用型指定共同生活援助を提供した際は、支給決定障害者から当該外部サービス利用型指定共同生活援助に係る利用者負担額の支払を受けているか。 | C52: 平18厚令171 第213条の22 準用（第210条の4第1項） | D52: 請求書 領収書
B53: （２）外部サービス利用型指定共同生活援助事業者は、法定代理受領を行わない外部サービス利用型指定共同生活援助を提供した際は、支給決定障害者から当該外部サービス利用型指定共同生活援助に係る指定障害福祉サービス等費用基準額の支払を受けているか。 | C53: 平18厚令171 第213条の22 準用（第210条の4第2項） | D53: 請求書 領収書
B54: （３）外部サービス利用型指定共同生活援助事業者は、(1)及び(2)の支払を受ける額のほか、指定共同生活援助において提供される便宜に要する費用のうち、支給決定障害者から受けることのできる次に掲げる費用の支払を受けているか。 | C54: 平18厚令171 第213条の22 準用（第210条の4第3項） | D54: 請求書 領収書
B55: ① 食材料費
B56: ② 家賃(障害者総合支援法第34条第1項の規定により特定障害者特別給付費が利用者に支給された場合(同条第2項において準用する同法第29条第4項の規定により特定障害者特別給付費が利用者に代わり当該外部サービス利用型指定共同生活援助事業者に支払われた場合に限る。)は、当該利用者に係る家賃の月額から同法第34条第2項において準用する同法第29条第5項の規定により当該利用者に支給があったものとみなされた特定障害者特別給付費の額を控除した額を限度とする。)
B57: ③ 光熱水費
B58: ④ 日用品費
B59: ⑤ ①から④のほか、外部サービス利用型指定共同生活援助において提供される便宜に要する費用のうち、日常生活においても通常必要となるものに係る費用であって、支給決定障害者に負担させることが適当と認められるもの
B60: （４）外部サービス利用型指定共同生活援助事業者は、(1)から(3)までに掲げる費用の額の支払を受けた場合は、当該費用に係る領収証を当該費用の額を支払った支給決定障害者に対し交付しているか。 | C60: 平18厚令171 第213条の22 準用（第210条の4第4項） | D60: 領収書
B61: （５）外部サービス利用型指定共同生活援助事業者は、(3)の費用に係るサービスの提供に当たっては、あらかじめ、支給決定障害者に対し、当該サービスの内容及び費用について説明を行い、支給決定障害者の同意を得ているか。 | C61: 平18厚令171 第213条の22 準用（第210条の4第5項） | D61: 重要事項説明書
A62: 13 利用者負担額に係る管理 | B62: （１）外部サービス利用型指定共同生活援助事業者は、支給決定障害者（入居前の体験的な外部サービス利用型指定共同生活援助を受けている者を除く。）が同一の月に当該外部サービス利用型指定共同生活援助事業者が提供する外部サービス利用型指定共同生活援助及び他の指定障害福祉サービス等を受けたときは、当該外部サービス利用型指定共同生活援助及び他の指定障害福祉サービス等に係る利用者負担額合計額を算定しているか。 この場合において、当該外部サービス利用型指定共同生活援助事業者は、利用者負担額合計額を市町村に報告するとともに、当該支給決定障害者及び当該他の指定障害福祉サービス等を提供した指定障害福祉サービス事業者等に通知しているか。 | C62: 平18厚令171 第213条の22 準用（第170条の2第1項） | D62: 適宜必要と認める資料 | E62: 利用者負担上限額管理票
B63: （２）外部サービス利用型指定共同生活援助事業者は、支給決定障害者（入居前の体験的な外部サービス利用型指定共同生活援助を受けている者に限る。）の依頼を受けて、当該支給決定障害者が同一の月に当該外部サービス利用型指定共同生活援助事業者が提供する外部サービス利用型指定共同生活援助及び他の指定障害福祉サービス等を受けたときは、当該外部サービス利用型指定共同生活援助及び他の指定障害福祉サービス等に係る利用者負担額合計額を算定しているか。 | C63: 平18厚令171 第213条の22 準用（第170条の2第2項） | D63: 適宜必要と認める資料 | E63: 利用者負担上限額管理票
B64: この場合において、当該外部サービス利用型指定共同生活援助事業者は、利用者負担額合計額を市町村に報告するとともに、当該支給決定障害者及び当該他の指定障害福祉サービス等を提供した指定障害福祉サービス事業者等に通知しているか。
A65: 14 訓練等給付費の額に係る通知等 | B65: （１）外部サービス利用型指定共同生活援助事業者は、法定代理受領により市町村から外部サービス利用型指定共同生活援助に係る訓練等給付費の支給を受けた場合は、支給決定障害者等に対し、当該支給決定障害者等に係る訓練等給付費の額を通知しているか。 | C65: 平18厚令171 第213条の22 準用（第23条第1項） | D65: 通知の写し
B66: （２）外部サービス利用型指定共同生活援助事業者は、法定代理受領を行わない外部サービス利用型指定共同生活援助に係る費用の支払を受けた場合は、その提供した外部サービス利用型指定共同生活援助の内容、費用の額その他必要と認められる事項を記載したサービス提供証明書を支給決定障害者等に対して交付しているか。 | C66: 平18厚令171 第213条の22 準用（第23条第2項） | D66: サービス提供証明書の写し
A67: 15 外部サービス利用型指定共同生活援助の取扱方針 | B67: （１）外部サービス利用型指定共同生活援助事業者は、外部サービス利用型指定共同生活援助に係る個別支援計画（外部サービス利用型共同生活援助計画）に基づき、利用者が地域において日常生活を営むことができるよう、当該利用者の身体及び精神の状況並びにその置かれている環境に応じて、その者の支援を適切に行うとともに、外部サービス利用型指定共同生活援助の提供が漫然かつ画一的なものとならないように配慮しているか。 | C67: 平18厚令171 第213条の22 準用（第210条の5第1項） | D67: 適宜必要と認める資料 | E67: 外部サービス利用型共同生活援助計画
B68: （２）外部サービス利用型指定共同生活援助事業者は、利用者が自立した日常生活または社会生活を営むことができるよう、利用者の意思決定の支援に配慮しているか。 | C68: 平18厚令171 第213条の22 準用（第210条の5第2項） | D68: 適宜必要と認める資料 | E68: 意思決定支援記録
B69: （３）外部サービス利用型指定共同生活援助事業者は、入居前の体験的な利用を希望する者に対して外部サービス利用型指定共同生活援助の提供を行う場合には、外部サービス利用型共同生活援助計画に基づき、当該利用者が、継続した外部サービス利用型指定共同生活援助の利用に円滑に移行できるよう配慮するとともに、継続して入居している他の利用者の処遇に支障がないようにしているか。 | C69: 平18厚令171 第213条の22 準用（第210条の5第3項） | D69: 適宜必要と認める資料 | E69: 体験利用計画
B70: （４）外部サービス利用型指定共同生活援助事業所の従業者は、外部サービス利用型指定共同生活援助の提供に当たっては、懇切丁寧を旨とし、利用者又はその家族に対し、支援上必要な事項について、理解しやすいように説明を行っているか。 | C70: 平18厚令171 第213条の22 準用（第210条の5第4項） | D70: 適宜必要と認める資料 | E70: 重要事項説明書
B71: （５）外部サービス利用型指定共同生活援助事業者は、その提供する外部サービス利用型指定共同生活援助の質の評価を行い、常にその改善を図っているか。 | C71: 平18厚令171 第213条の22 準用（第210条の5第5項） | D71: 適宜必要と認める資料 | E71: 利用者アンケート
A72: 16 外部サービス利用型共同生活援助計画の作成等 | B72: （１）外部サービス利用型指定共同生活援助事業所の管理者は、サービス管理責任者に外部サービス利用型共同生活援助計画の作成に関する業務を担当させているか。 | C72: 平18厚令171 第213条の22 準用（第58条 第1項) | D72: 個別支援計画 サービス管理責任者が個別支援計画を作成していることが分かる書類
B73: （２）サービス管理責任者は、外部サービス利用型共同生活援助計画の作成に当たっては、適切な方法により、利用者について、その有する能力、その置かれている環境及び日常生活全般の状況等の評価を通じて利用者の希望する生活や課題等の把握（アセスメント）を行うとともに、利用者の自己決定の尊重及び意思決定の支援に配慮しつつ、利用者が自立した日常生活を営むことができるように支援する上での適切な支援内容の検討をしているか。 | C73: 平18厚令171 第213条の22 準用（第58条 第2項) | D73: 個別支援計画 アセスメント及びモニタリングを実施したことが分かる記録
B74: （３）アセスメントに当たっては、利用者が自ら意思を決定することに困難を抱えている場合には、適切に意思決定の支援を行うため、当該利用者の意思及び選好並びに判断能力等について丁寧に把握しているか。 | C74: 平18厚令171 第213条の22 準用（第58条 第3項) | D74: アセスメントを実施したことが分かる記録
B75: （４）アセスメントに当たっては、利用者に面接して行っているか。 この場合において、サービス管理責任者は、面接の趣旨を利用者に対して十分に説明し、理解を得ているか。 | C75: 平18厚令171 第213条の22 準用（第58条 第4項) | D75: アセスメントを実施したことが分かる記録 面接記録
B76: （５）サービス管理責任者は、アセスメント及び支援内容の検討結果に基づき、利用者及びその家族の生活に対する意向、総合的な支援の方針、生活全般の質を向上させるための課題、外部サービス利用型指定共同生活援助の目標及びその達成時期、外部サービス利用型指定共同生活援助を提供する上での留意事項等を記載した外部サービス利用型共同生活援助計画の原案を作成しているか。 この場合において、当該外部サービス利用型指定共同生活援助事業所が提供する外部サービス利用型指定共同生活援助以外の保健医療サービス又はその他の福祉サービス等との連携も含めて外部サービス利用型共同生活援助計画の原案に位置付けるよう努めているか。 | C76: 平18厚令171 第213条の22 準用（第58条 第5項) | D76: 個別支援計画の原案 他サービスとの連携状況が分かる書類
B77: （６）サービス管理責任者は、外部サービス利用型共同生活援助計画の作成に係る会議（利用者及び当該利用者に対する共同生活援助計画担当者等を招集して行う会議をいい、テレビ電話装置等の活用可能。）を開催し、当該利用者の生活に対する意向等を改めて確認するとともに、共同生活援助計画の原案の内容について意見を求めているか。 | C77: 平18厚令171 第213条の22 準用（第58条 第6項) | D77: サービス担当者会議の記録
B78: （７）サービス管理責任者は、(5)に規定する外部サービス利用型共同生活援助計画の原案の内容について利用者又はその家族に対して説明し、文書により利用者の同意を得ているか。 | C78: 平18厚令171 第213条の22 準用（第58条 第7項) | D78: 個別支援計画
B79: （８）サービス管理責任者は、外部サービス利用型共同生活援助計画を作成した際には、当該外部サービス利用型共同生活援助計画を利用者及び指定特定相談支援事業者に交付しているか。 | C79: 平18厚令171 第213条の22 準用（第58条 第8項) | D79: 利用者及び指定特定相談支援事業者に交付した記録 個別支援計画
B80: （９）サービス管理責任者は、外部サービス利用型共同生活援助計画の作成後、外部サービス利用型共同生活援助計画の実施状況の把握（モニタリング（利用者についての継続的なアセスメントを含む。）)を行うとともに、少なくとも6月に1回以上、外部サービス利用型共同生活援助計画の見直しを行い、必要に応じて外部サービス利用型共同生活援助計画の変更を行っているか。 | C80: 平18厚令171 第213条の22 準用（第58条 第9項) | D80: 個別支援計画 アセスメント及びモニタリングに関する記録
B81: （10）サービス管理責任者は、モニタリングに当たっては、利用者及びその家族等との連絡を継続的に行うこととし、特段の事情のない限り、次に定めるところにより行っているか。 ① 定期的に利用者に面接すること。 ② 定期的にモニタリングの結果を記録すること。 | C81: 平18厚令171 第213条の22 準用（第58条 第10項) | D81: モニタリング記録 面接記録
B82: （11）外部サービス利用型共同生活援助計画に変更のあった場合、(2)から(8)に準じて取り扱っているか。 | C82: 平18厚令171 第213条の22 準用（第58条 第11項) | D82: (2)から(8)に掲げる確認資料
A83: 17 サービス管理責任者の責務 | B83: （１）サービス管理責任者は、外部サービス利用型共同生活援助計画の作成等のほか、次に掲げる業務を行っているか。 | C83: 平18厚令171 第213条の22 準用（第210条の6第1項）
B84: ① 利用申込者の利用に際し、その者に係る指定障害福祉サービス事業者等に対する照会等により、その者の身体及び精神の状況、当該外部サービス利用型指定共同生活援助事業所以外における指定障害福祉サービス等の利用状況等を把握すること。 | D84: 個別支援計画 アセスメント及びモニタリングに関する記録
B85: ② 利用者の身体及び精神の状況、その置かれている環境等に照らし、利用者が自立した日常生活を営むことができるよう定期的に検討するとともに、自立した日常生活を営むことができると認められる利用者に対し、必要な支援を行うこと。 | D85: 個別支援計画 アセスメント及びモニタリングに関する記録 サービス提供の記録
B86: ③ 利用者が自立した社会生活を営むことができるよう指定生活介護事業所等との連絡調整を行うこと。 | D86: 指定生活介護事業所等との連絡調整した記録
B87: ④ 他の従事者に対する技術的指導及び助言を行うこと。 | D87: 他の従業者に指導及び助言した記録
B88: （２）サービス管理者は、業務を行うに当たっては、利用者の自己決定の尊重を原則とした上で、利用者が自ら意思を決定することに困難を抱える場合には、適切に利用者への意思決定の支援が行われるように努めているか。 | C88: 平18厚令171 第213条の22 準用（第210条の6第2項） | D88: 適宜必要と認める資料 | E88: 個別支援計画
A89: 18 相談及び援助 | B89: 外部サービス利用型指定共同生活援助事業者は、常に利用者の心身の状況、その置かれている環境等の的確な把握に努め、利用者又はその家族に対し、その相談に適切に応じるとともに、必要な助言その他の援助を行っているか。 | C89: 平18厚令171 第213条の22 準用（第60条） | D89: 適宜必要と認める資料 | E89: 相談受付記録
A90: 19 介護及び家事等 | B90: （１）介護は、利用者の身体及び精神の状況に応じ、利用者の自立の支援と日常生活の充実に資するよう、適切な技術をもって行っているか。 | C90: 平18厚令171 第213条の22 準用（第211条第1項） | D90: 個別支援計画 サービス提供の記録 業務日誌等
B91: （２）調理、洗濯その他の家事等は、原則として利用者と従業者が共同で行うよう努めているか。 | C91: 平18厚令171 第213条の22 準用（第211条第2項） | D91: 勤務実績表 出勤簿（タイムカード） 従業員の資格証 勤務体制一覧表
B92: （３）外部サービス利用型指定共同生活援助事業者は、その利用者に対して、利用者の負担により、当該外部サービス利用型指定共同生活援助事業所の従業者以外の者による家事等を受けさせていないか。 | C92: 平18厚令171 第213条の22 準用（第211条第3項） | D92: 従業者名簿 雇用契約書 個別支援計画 サービス提供の記録 業務日誌等
A93: 20 社会生活上の便宜の供与等 | B93: （１）外部サービス利用型指定共同生活援助事業者は、利用者について、指定生活介護事業所等との連絡調整、余暇活動の支援等に努めているか。 | C93: 平18厚令171 第213条の22 準用（第211条の2第1項） | D93: 適宜必要と認める資料 | E93: 生活介護事業所等との連絡記録
B94: （２）外部サービス利用型指定共同生活援助事業者は、利用者が日常生活を営む上で必要な行政機関に対する手続等について、その者又はその家族が行うことが困難である場合は、その者の同意を得て代わって行っているか。 | C94: 平18厚令171 第213条の22 準用（第211条の2第2項） | D94: 適宜必要と認める資料 | E94: 個別支援記録
B95: （３）外部サービス利用型指定共同生活援助事業者は、常に利用者の家族との連携を図るとともに、利用者とその家族との交流等の機会を確保するよう努めているか。 | C95: 平18厚令171 第213条の22 準用（第211条の2第3項） | D95: 適宜必要と認める資料 | E95: 個別支援記録
A96: 21 地域との連携 | B96: （１）外部サービス利用型指定共同生活援助事業者は、外部サービス利用型指定共同生活援助の提供に当たっては、地域住民又はその自発的な活動等との連携及び協力を行う等の地域との交流を図っているか。 | C96: 平18厚令171 第210条の7 第1項 | D96: 適宜必要と認める資料 | E96: 地域交流記録
B97: （２）外部サービス利用型指定共同生活援助事業者は、外部サービス利用型指定共同生活援助の提供に当たっては、利用者及びその家族、地域住民の代表者、共同生活援助について知見を有する者並びに市町村の担当者等により構成される協議会（テレビ電話装置等を活用して行うことができるものとする。以下21において「地域連携推進会議」という。）を開催し、おおむね一年に一回以上、地域連携推進会議において、事業の運営に係る状況を報告するとともに、必要な要望、助言等を聴く機会を設けているか。 | C97: 平18厚令171 第210条の7 第2項 | D97: 適宜必要と認める資料 | E97: 地域連携推進会議議事録
B98: （３）外部サービス利用型指定共同生活援助事業者は、地域連携推進会議の開催のほか、おおむね一年に一回以上、当該地域連携推進会議の構成員が外部サービス利用型指定共同生活援助事業所を見学する機会を設けているか。 | C98: 平18厚令171 第210条の7 第3項 | D98: 適宜必要と認める資料 | E98: 見学記録
B99: （４）外部サービス利用型指定共同生活援助事業者は、第二項の報告、要望、助言等についての記録を作成するとともに、当該記録を公表しているか。 | C99: 平18厚令171 第210条の7 第4項 | D99: 適宜必要と認める資料 | E99: 議事録
B100: （５）⑴から⑶までに掲げる規定において、外部サービス利用型指定共同生活援助事業者がその提供する外部サービス利用型指定共同生活援助の質に係る外部の者による評価及び当該評価の実施状況の公表又はこれに準ずる措置として都道府県知事が定めるものを講じているか。 | C100: 平18厚令171 第210条の7 第5項 | D100: 適宜必要と認める資料 | E100: 第三者評価結果
A101: 22 緊急時等の対応 | B101: 従業者は、現に外部サービス利用型指定共同生活援助の提供を行っているときに利用者に病状の急変が生じた場合その他必要な場合は、速やかに医療機関への連絡を行う等の必要な措置を講じているか。 | C101: 平18厚令171 第213条の22 準用（第28条） | D101: 緊急時対応マニュアル ケース記録 事故等の対応記録
...

Sheet 指定共同生活援助（訓練等給付費の算定）
A1: （注）下線を付した項目が標準確認項目
A2: 確認項目 | B2: 確認事項 | C2: 根拠法令 | D2: 関係書類 | E2: 関係書類 | F2: 判定
A3: 第14 介護給付費又は訓練等給付費の算定及び取扱い | C3: 法第29条第3項
A4: １ 基本事項 | B4: （１）指定共同生活援助又は外部サービス利用型指定共同生活援助に要する費用の額は、平成18年厚生労働省告示第523号の別表「介護給付費等単位数表」の第15により算定する単位数に、平成18年厚生労働省告示第539号「こども家庭庁長官及び厚生労働大臣が定める一単位の単価並びに厚生労働大臣が定める一単位の単価」に定める一単位の単価を乗じて得た額を算定しているか。 | C4: 平18厚告523 の一 平18厚告539 | D4: 体制等状況一覧表、当該加算の届出書等 | E4: 介護給付費等算定に係る体制等状況一覧表
B5: （ただし、その額が現に当該指定共同生活援助又は外部サービス利用型指定共同生活援助に要した費用の額を超えるときは、当該現に指定共同生活援助又は外部サービス利用型指定共同生活援助に要した費用の額となっているか。） | C5: 法第29条 第3項
B6: （２）(1)の規定により、指定共同生活援助又は外部サービス利用型指定共同生活援助に要する費用の額を算定した場合において、その額に1円未満の端数があるときは、その端数金額は切り捨てて算定しているか。 | C6: 平18厚告523の二 | D6: 体制等状況一覧表、当該加算の届出書等
A7: ２ 共同生活援助 サービス費 | B7: （１）共同生活援助サービス費（Ⅰ）については、障害者（身体障害者にあっては、65歳未満の者又は65歳に達する日の前日までに障害福祉サービス若しくはこれに準ずるものを利用したことがある者に限り、地域移行支援型ホームにおける指定共同生活援助の利用者にあっては、当該地域移行支援型ホームにおいて指定共同生活援助の事業を行う者が当該事業を開始した日において、精神科病院に1年以上入院している精神障害者に限る。）(3)において同じ。）（(3)に規定する障害者を除く。）に対し、指定共同生活援助事業所において、指定共同生活援助を行った場合に、障害支援区分に応じ、１日につき所定単位数を算定しているか。 | C7: 平18厚告523 別表第15の1の注1 | D7: 体制等状況一覧表、当該加算の届出書等 | E7: 請求明細書
B8: （２）令和9年3月31日までの間、指定共同生活援助事業所において、個人単位で居宅介護等を利用する場合の利用者に対し、指定共同生活援助を行った場合にあっては、(1)にかかわらず、次に掲げる単位数を算定しているか。ただし、これらの規定に基づく居宅介護又は重度訪問介護の利用について、所要時間が８時間以上である場合にあっては、次に掲げる単位数の100分の95に相当する単位数を算定しているか。 ア 区分6 369単位 イ 区分5 306単位 ウ 区分4 270単位 | C8: 平18厚告523 別表第15の1の 注2 | D8: 体制等状況一覧表、当該加算の届出書等
B9: （３）共同生活援助サービス費（Ⅱ）については、一時的に体験的な指定共同生活援助の利用が必要と認められる者に対し、指定共同生活援助（1回当たり連続30日以内のものに限る。）を提供した場合に、障害支援区分に応じ、年50日以内に限り、1日につき所定単位数を算定しているか。 | C9: 平18厚告523 別表第15の1の 注3 | D9: 体制等状況一覧表、当該加算の届出書等
B10: （４）共同生活援助サービス費（(2)に規定する場合を含む。）の算定に当たって、次の①から⑤までのいずれかに該当する場合に、それぞれに掲げる割合を所定単位数に乗じて得た数を算定しているか。 （ただし、③及び⑤に該当する場合にあっては、③に掲げる割合を所定単位数に乗じて得た額を、④及び⑤に該当する場合にあっては、④に掲げる割合を所定単位数に乗じて得た額を算定しているか。） | C10: 平18厚告523 別表第15の1の注４ | D10: 体制等状況一覧表、当該加算の届出書等
B11: ① 従業者の員数が平成18年厚生労働省告示第550号「厚生労働大臣が定める利用者の数の基準、従業者の員数の基準及び営業時間の時間数並びに所定単位数に乗じる割合並びにこども家庭庁長官及び厚生労働大臣が定める利用者の数の基準及び従業員の員数の基準並びに所定単位数に乗じる割合」の十の表の上欄に掲げる員数の基準に該当する場合 同表の下欄に掲げる割合 | C11: 平18厚告523 別表第15の1の注４の(1) 平18厚告550の十 | D11: 体制等状況一覧表、当該加算の届出書等
B12: ② 指定共同生活援助の提供に当たって、共同生活援助計画が作成されていない場合 次に掲げる場合に応じ、それぞれ次に掲げる割合 ア 作成されていない期間が3月未満の場合 100分の70 イ 作成されていない期間が3月以上の場合 100分の50 | C12: 平18厚告523 別表第15の1の 注４の（2） | D12: 体制等状況一覧表、当該加算の届出書等
B13: ③ 共同生活住居の入居定員が8人以上である場合 100分の95 | C13: 平18厚告523 別表第15の1の 注４の（3） | D13: 体制等状況一覧表、当該加算の届出書等
B14: ④ 共同生活住居の入居定員が21人以上である場合 100分の93 | C14: 平18厚告523 別表第15の1の 注４の（4） | D14: 体制等状況一覧表、当該加算の届出書等
B15: ⑤ 一体的な運営が行われている共同生活住居の入居定員（サテライト型住居に係る入居定員を含む。）の合計数が21人以上である場合 100分の95 | C15: 平18厚告523 別表第15の1の 注４の（5） | D15: 体制等状況一覧表、当該加算の届出書等
B16: （５）第76の３第１項の規定に基づく情報公表対象サービス等情報に係る報告を行っていない場合は、所定単位数の100分の10に相当する単位数を所定単位数から減算しているか。 | C16: 平18厚告523 別表第15の1の 注5 | D16: 体制等状況一覧表、当該加算の届出書等
B17: （６）第４の27の⑴（指定障害福祉サービス基準第213条において準用する指定障害福祉サービス基準第33条の２第１項）に規定する基準を満たしていない場合は、所定単位数の100分の３に相当する単位数を所定単位数から減算しているか。 | C17: 平18厚告523 別表第15の1の 注6 | D17: 体制等状況一覧表、当該加算の届出書等
B18: （７）第4の33の(2)又は(3)（指定障害福祉サービス基準第213条において準用する指定障害福祉サービス基準第35条の２第２項又は第3項）に規定する基準を満たしていない場合は、所定単位数の100分の10に相当する単位数を所定単位数から減算しているか。 | C18: 平18厚告523 別表第15の1の 注7 | D18: 体制等状況一覧表、当該加算の届出書等
B19: （８）第4の39（指定障害福祉サービス基準第213条において準用する指定障害福祉サービス基準第40条の２）に規定する基準を満たしていない場合は、所定単位数の100分の１に相当する単位数を所定単位数から減算しているか。 | C19: 平18厚告523 別表第15の1の 注8 | D19: 体制等状況一覧表、当該加算の届出書等
B20: （９）利用者が共同生活援助以外の障害福祉サービスを受けている間（居宅介護を受けている間（(2)の適用を受けている間に限る。）及び重度訪問介護を受けている間（(2)の適用を受けている間に限る。）を除く。）は、共同生活援助サービス費を算定していないか。 | C20: 平18厚告523 別表第15の1の 注9 | D20: 体制等状況一覧表、当該加算の届出書等
A21: ２の２ 日中サービス支援型共同生活援助サービス費 | B21: （１）日中サービス支援型共同生活援助サービス費（Ⅰ）については、障害者（身体障害者にあっては、65歳未満の者又は65歳に達する日の前日までに障害福祉サービス若しくはこれに準ずるものを利用したことがある者に限る。（5）において同じ。）（(5)に規定する障害者を除く。）に対して、日中サービス支援型指定共同生活援助事業所において、日中サービス支援型指定共同生活援助を行った場合に、所定単位数を算定しているか。 | C21: 平18厚告523 別表第15の1の2の注1 | D21: 体制等状況一覧表、当該加算の届出書等 | E21: 請求明細書
B22: （２）日中を共同生活住居（第5の(4)に規定する共同生活住居をいう。)以外の場所で過ごす利用者に対し、日中サービス支援型指定共同生活援助を行った場合は、所定単位数に代えて、次のアからカまでの場合に応じ、それぞれ1日につき次に掲げる単位数を算定しているか。ただし、(4)に規定する単位数を算定している場合は、算定しない。 ア 区分6 765単位 イ 区分5 627単位 ウ 区分4 539単位 エ 区分3 407単位 オ 区分2 270単位 カ 区分1以下 253単位 | C22: 平18厚告523 別表第15の1の2の注2 | D22: 体制等状況一覧表、当該加算の届出書等
B23: （３）令和9年3月31日までの間、日中サービス支援型指定共同生活援助事業所において、個人単位で居宅介護等を利用する場合の利用者に対し、日中サービス支援型指定共同生活援助を行った場合は、所定単位数に代えて、次のアからウまでの場合に応じ、それぞれ1日につき次に掲げる単位数を算定しているか。また、これらの規定に基づく居宅介護又は重度訪問介護の利用について、所要時間が８時間以上である場合にあっては、次に掲げる単位数の100分の95に相当する単位数を算定しているか。 ア 区分6 565単位 イ 区分5 505単位 ウ 区分4 467単位 | C23: 平18厚告523 別表第15の1の2の注3 | D23: 体制等状況一覧表、当該加算の届出書等
B24: （４）令和9年3月31日までの間、日中サービス支援型指定共同生活援助事業所において、個人単位で居宅介護等を利用する場合の利用者であって、日中を共同生活住居以外の場所で過ごす者に対し、日中サービス支援型指定共同生活援助を行った場合は、所定単位数に代えて、次のアからウまでの場合に応じ、それぞれ1日につき、次に掲げる単位数を算定しているか。また、これらの規定に基づく居宅介護又は重度訪問介護の利用について、所要時間が８時間以上である場合にあっては、次に掲げる単位数の100分の95に相当する単位数を算定しているか。 ア 区分6 454単位 イ 区分5 394単位 ウ 区分4 356単位 | C24: 平18厚告523 別表第15の1の2の注4 | D24: 体制等状況一覧表、当該加算の届出書等
B25: （５）日中サービス支援型共同生活援助サービス費（Ⅱ）については、一時的に体験的な日中サービス支援型指定共同生活援助の利用が必要と認められる障害者に対し、日中サービス支援型指定共同生活援助（1回当たり連続30日以内のものに限る。）を提供した場合に、障害支援区分に応じ、年50日以内に限り、1日につき所定単位数を算定しているか。 | C25: 平18厚告523 別表第15の1の2の注5 | D25: 体制等状況一覧表、当該加算の届出書等
B26: （６）日中サービス支援型指定共同生活援助事業所において、一時的に体験的な日中サービス支援型指定共同生活援助の利用が必要と認められる者であって、日中を当該共同生活住居以外の場所で過ごすものに対し、日中サービス支援型指定共同生活援助（1回当たり連続30日以内のものに限る。）を提供した場合は、所定単位数に代えて、次の①から⑥までの場合に応じ、年50日以内に限り、それぞれ１日につき次に掲げる所定単位数を算定 しているか。 ① 区分6 929単位 ② 区分5 787単位 ③ 区分4 695単位 ④ 区分3 546単位 ⑤ 区分2 408単位 ⑥ 区分1以下 389単位 | C26: 平18厚告523 別表第15の1の2の注6 | D26: 体制等状況一覧表、当該加算の届出書等
B27: （７）日中サービス支援型共同生活援助サービス費（(2)から(4)まで及び(6)に規定する場合を含む。）の算定に当たって、次の①から④までのいずれかに該当する場合に、それぞれ次に掲げる割合を所定単位数に乗じて得た数を算定しているか。 | C27: 平18厚告523 別表第15の1の2の注7 | D27: 体制等状況一覧表、当該加算の届出書等
B28: ① 従業者の員数が平成18年厚生労働省告示第550号「厚生労働大臣が定める利用者の数の基準、従業者の員数の基準及び営業時間の時間数並びに所定単位数に乗じる割合並びにこども家庭庁長官及び厚生労働大臣が定める利用者の数の基準及び従業者の員数の基準並びに所定単位数に乗じる割合」の十の二の表の上欄に掲げる員数の基準に該当する場合 同表の下欄に掲げる割合 | C28: 平18厚告523 別表第15の1の2の注7の(1) 平18厚告550の十の二 | D28: 体制等状況一覧表、当該加算の届出書等
B29: ② 日中サービス支援型指定共同生活援助の提供に当たって、日中サービス支援型共同生活援助計画が作成されていない場合 次に掲げる場合に応じ、それぞれ次に掲げる割合 ア 作成されていない期間が3月未満の場合 100分の70 イ 作成されていない期間が3月以上の場合 100分の50 | C29: 平18厚告523 別表第15の1の2の注7の（2） | D29: 体制等状況一覧表、当該加算の届出書等
B30: ③ 共同生活住居の入居定員が21人以上である場合 100分の93 | C30: 平18厚告523 別表第15の1の2の注7の（3） | D30: 体制等状況一覧表、当該加算の届出書等
B31: ④ 一体的な運営が行われている共同生活住居（③に該当する共同生活住居を除く。）の入居定員の合計数が21人以上である場合 100分の95 | C31: 平18厚告523 別表第15の1の2の注7の（4） | D31: 体制等状況一覧表、当該加算の届出書等
B32: （８）法第76の３第１項の規定に基づく情報公表対象サービス等情報に係る報告を行っていない場合は、所定単位数の100分の10に相当する単位数を所定単位数から減算しているか。 | C32: 平18厚告523 別表第15の1の2の注８ | D32: 体制等状況一覧表、当該加算の届出書等
B33: （９）第８の28の⑴（指定障害福祉サービス基準第213条の11において準用する指定障害福祉サービス基準第33条の２第１項）に規定する基準を満たしていない場合は、所定単位数の100分の３に相当する単位数を所定単位数から減算しているか。 | C33: 平18厚告523 別表第15の1の2の注９ | D33: 体制等状況一覧表、当該加算の届出書等
... B36: （12）利用者が日中サービス支援型共同生活援助以外の障害福祉サービスを受けている間（居宅介護を受けている間（(3)及び(4)の適用を受けている間に限る。）及び重度訪問介護を受けている間（(3)及び(4)の適用を受けている間に限る。）を除く。）は、日中サービス支援型共同生活援助サービス費を算定していないか。 | C36: 平18厚告523 別表第15の1の2の注12 | D36: 体制等状況一覧表、当該加算の届出書等
A37: ２の２の２ 外部サービス利用型共同生活援助サービス費 | B37: （１）外部サービス利用型共同生活援助サービス費（Ⅰ）については、障害者（身体障害者にあっては、65歳未満の者又は65歳に達する日の前日までに障害福祉サービス若しくはこれに準ずるものを利用したことがある者に限り、地域移行支援型ホームにおける外部サービス利用型指定共同生活援助の利用者にあっては、当該地域移行支援型ホームにおいて外部サービス利用型指定共同生活援助の事業を行う者が外部サービス利用型指定共同生活援助の事業を開始した日において精神科病院に1年以上入院している精神障害者に限る。）(2)及び(3)において同じ。）（(3)に規定する障害者を除く。）に対し、世話人が、常勤換算方法で、利用者の数を６で除して得た数以上配置されているものとして都道府県知事に届け出た外部サービス利用型指定共同生活援助事業所において、基本サービスを行った場合に、1日につき所定単位数を算定しているか。 | C37: 平18厚告523 別表第15の1の2の2の注1 | D37: 体制等状況一覧表、当該加算の届出書等 | E37: 請求明細書
B38: （２）外部サービス利用型共同生活援助サービス費（Ⅱ）については、障害者（(3)に規定する障害者を除く。）に対し、(1)に規定するもの以外の外部サービス利用型指定共同生活援助事業所（平成25年厚生労働省令第124号「地域社会における共生の実現に向けて新たな障害保健福祉施策を講ずるための関係法律の整備に関する法律の一部の施行に伴う関係省令の整備等に関する省令」の附則第4条の規定の適用を受ける外部サービス利用型指定共同生活援助事業所に限る。）において、基本サービスを行った場合に、1日につき所定単位数を算定しているか。 | C38: 平18厚告523 別表第15の1の 2の2の注2 | D38: 体制等状況一覧表、当該加算の届出書等
B39: （３）外部サービス利用型共同生活援助サービス費（Ⅲ）については、一時的に体験的な外部サービス利用型指定共同生活援助の利用が必要と認められる障害者に対し、基本サービス（1回当たり連続30日以内のものに限る。）を提供した場合に、年50日以内に限り、1日につき所定単位数を算定しているか。 | C39: 平18厚告523 別表第15の1の 2の2の注3 | D39: 体制等状況一覧表、当該加算の届出書等
B40: （４）外部サービス利用型共同生活援助サービス費の算定に当たって、次の①から④までのいずれかに該当する場合に、それぞれに掲げる割合を所定単位数に乗じて得た数を算定しているか。 | C40: 平18厚告523 別表第15の1の 2の2の注4 | D40: 体制等状況一覧表、当該加算の届出書等
B41: ① 従業者の員数が平成18年厚生労働省告示第550号「厚生労働大臣が定める利用者の数の基準、従業者の員数の基準及び営業時間の時間数並びに所定単位数に乗じる割合並びにこども家庭庁長官及び厚生労働大臣が定める利用者の数の基準及び従業者の員数の基準並びに所定単位数に乗じる割合」の十一の表の上欄に掲げる員数の基準に該当する場合 同表の下欄に掲げる割合 | C41: 平18厚告523 別表第15の1の2の2の注4の(1) 平18厚告550の十一
B42: ② 基本サービスの提供に当たって、外部サービス利用型共同生活援助計画が作成されていない場合 次に掲げる場合に応じ、それぞれ次に掲げる割合 ア 作成されていない期間が3月未満の場合 100分の70 イ 作成されていない期間が3月以上の場合 100分の50 | C42: 平18厚告523 別表第15の1の 2の2の注4の（2）
B43: ③ 共同生活住居の入居定員が8人以上である場合 100分の90 | C43: 平18厚告523 別表第15の1の 2の2の注4の（3）
B44: ④ 共同生活住居の入居定員が21人以上である場合 100分の87 | C44: 平18厚告523 別表第15の1の 2の2の注4の（4）
B45: （５）第76の３第１項の規定に基づく情報公表対象サービス等情報に係る報告を行っていない場合は、所定単位数の100分の10に相当する単位数を所定単位数から減算しているか。 | C45: 平18厚告523 別表第15の1の 2の注5 | D45: 体制等状況一覧表、当該加算の届出書等
B46: （６）第12の28の⑴（指定障害福祉サービス基準第213条の22において準用する指定障害福祉サービス基準第33条の２第１項）に規定する基準を満たしていない場合は、所定単位数の100分の３に相当する単位数を所定単位数から減算しているか。 | C46: 平18厚告523 別表第15の1の 2の注6 | D46: 体制等状況一覧表、当該加算の届出書等
B47: （７）第12の35の(2)又は(3)（指定障害福祉サービス基準第213条の22において準用する指定障害福祉サービス基準第35条の２第２項又は第3項）に規定する基準を満たしていない場合は、所定単位数の100分の10に相当する単位数を所定単位数から減算しているか。 | C47: 平18厚告523 別表第15の1の 2の注７ | D47: 体制等状況一覧表、当該加算の届出書等
B48: （８）第12の41（指定障害福祉サービス基準第213条の22において準用する指定障害福祉サービス基準第40条の２）に規定する基準を満たしていない場合は、所定単位数の100分の１に相当する単位数を所定単位数から減算しているか。 | C48: 平18厚告523 別表第15の1の 2の注8 | D48: 体制等状況一覧表、当該加算の届出書等
B49: （９）利用者が外部サービス利用型共同生活援助以外の障害福祉サービスを受けている間は、外部サービス利用型共同生活援助サービス費を算定していないか。 | C49: 平18厚告523 別表第15の1の 2の注9 | D49: 体制等状況一覧表、当該加算の届出書等
A50: ２の２の３ 退居後共同生活援助サービス費 | B50: 退居後共同生活援助サービス費については、平成18年厚生労働省告示第551号「厚生労働大臣が定める施設基準並びにこども家庭庁長官及び厚生労働大臣が定める施設基準」の十六のイに定める基準に適合しているものとして都道府県知事に届け出た指定共同生活援助事業所の従業者が、当該指定共同生活援助事業所を退居した利用者（入居中に当該利用者に対する支援について２のイの自立生活支援加算(Ⅰ)又はハの自立生活支援加算(Ⅲ)を算定していた者に限る。）に対し、当該利用者の居宅を訪問して指定共同生活援助を行った場合に、当該退居の日の属する月から３月以内の期間に限り、１月につき所定単位数を算定しているか。ただし、３月を超えて引き続き支援することが必要であると市町村が認めた利用者に対しては、退居の日の属する月から６月以内の期間に限り、１月につき所定単位数を算定できるものとしているか。 | C50: 平18厚告523 別表第15の1の 2の3注1 | D50: 体制等状況一覧表、当該加算の届出書等 | E50: 退居後支援記録
A51: ２の２の４ 退居後外部サービス利用型共同生活援助サービス費 | B51: 退居後外部サービス利用型共同生活援助サービス費については、平成18年厚生労働省告示第551号「厚生労働大臣が定める施設基準並びにこども家庭庁長官及び厚生労働大臣が定める施設基準」の十八のイに定める基準に適合しているものとして都道府県知事に届け出た指定共同生活援助事業所の従業者が、当該外部サービス利用型指定共同生活援助事業所を退居した利用者（入居中に当該利用者に対する支援について２のイの自立生活支援加算(Ⅰ)又はハの自立生活支援加算(Ⅲ)が算定されていた者に限る。）に対し、当該利用者の居宅を訪問して外部サービス利用型指定共同生活援助を行った場合に、当該退居の日の属する月から３月以内の期間に限り、１月につき所定単位数を算定しているか。ただし、３月を超えて引き続き支援することが必要であると市町村が認めた利用者に対しては、退居の日の属する月から６月以内の期間に限り、１月につき所定単位数を算定できるものとしているか。 | C51: 平18厚告523 別表第15の1の 2の4注 | D51: 体制等状況一覧表、当該加算の届出書等 | E51: 退居後支援記録
A52: ２の３ 受託居宅介護サービス費 | B52: 外部サービス利用型指定共同生活援助事業所の利用者（区分2以上に該当する利用者に限る。）に対して、受託居宅介護サービス事業所の従業者が受託居宅介護サービスを行った場合に、現に要した時間ではなく、外部サービス利用型指定共同生活援助の提供時間帯において、外部サービス利用型共同生活援助計画に位置付けられた内容の受託居宅介護サービスを行うのに要する標準的な時間で所定単位数を算定しているか。 | C52: 平18厚告523 別表第15の1の 3の注 | D52: 体制等状況一覧表、当該加算の届出書等 | E52: 委託契約書、サービス提供実績記録票
A53: ２の３の２ 人員配置体制加算 | B53: （１）人員配置体制加算（Ⅰ）については、平成18年厚生労働省告示第551号「厚生労働大臣が定める施設基準並びにこども家庭庁長官及び厚生労働大臣が定める施設基準」の十五のロの(1)に定める基準に適合しているものとして都道府県知事に届け出た指定共同生活援助事業所において、利用者に対し、指定共同生活援助の提供を行った場合（一時的に体験的な利用が必要と認められる障害者に対して行う場合を除く。以下この１の３の２において同じ。）に、障害支援区分に応じ、１日につき所定単位数を加算しているか。 | C53: 平18厚告523 別表第15の1の 3の2の注1 | D53: 体制等状況一覧表、当該加算の届出書等 | E53: 勤務形態一覧表、人員配置体制加算届出書
B54: （２）人員配置体制加算（Ⅱ）については、平成18年厚生労働省告示第551号「厚生労働大臣が定める施設基準並びにこども家庭庁長官及び厚生労働大臣が定める施設基準」の十六のロの(2)に定める基準に適合しているものとして都道府県知事に届け出た指定共同生活援助事業所において、利用者に対し、指定共同生活援助の提供を行った場合に、障害支援区分に応じ、１日につき所定単位数を加算しているか。ただし、（１）を算定している場合は、算定しない。 | C54: 平18厚告523 別表第15の1の 3の2の注2 | D54: 体制等状況一覧表、当該加算の届出書等
B55: （３）人員配置体制加算（Ⅲ）については、平成18年厚生労働省告示第551号「厚生労働大臣が定める施設基準並びにこども家庭庁長官及び厚生労働大臣が定める施設基準」の十六のロの(1)に定める基準に適合しているものとして都道府県知事に届け出た指定共同生活援助事業所において、令和９年３月31日までの間、指定障害福祉サービス基準附則第18条の２第１項又は第２項の規定の適用を受ける利用者に対し、指定共同生活援助を行った場合に、１日につき所定単位数（これらの規定に基づく居宅介護又は重度訪問介護の利用について、所要時間が８時間以上である場合にあっては、所定単位数の100分の95に相当する単位数とする。）を加算しているか。ただし、（１）又は（２）を算定している場合は、算定しない。 | C55: 平18厚告523 別表第15の1の 3の2の注3 | D55: 体制等状況一覧表、当該加算の届出書等
B56: （４）人員配置体制加算（Ⅳ）については、平成18年厚生労働省告示第551号「厚生労働大臣が定める施設基準並びにこども家庭庁及び厚生労働大臣が定める施設基準」の十六のロの(2)に定める基準に適合しているものとして都道府県知事に届け出た指定共同生活援助事業所において、令和９年３月31日までの間、指定障害福祉サービス基準附則第18条の２第１項又は第２項の規定の適用を受ける利用者に対し、指定共同生活援助を行った場合に、１日につき所定単位数（これらの規定に基づく居宅介護又は重度訪問介護の利用について、所要時間が８時間以上である場合にあっては、所定単位数の100分の95に相当する単位数とする。）を加算しているか。ただし、（１）から（３）までを算定している場合は、算定しない。 | C56: 平18厚告523 別表第15の1の 3の2の注4 | D56: 体制等状況一覧表、当該加算の届出書等
B57: （５）人員配置体制加算（Ⅴ）については、平成18年厚生労働省告示第551号「厚生労働大臣が定める施設基並びにこども家庭庁長官及び厚生労働大臣が定める施設基準」の十七のイの(1)に定める基準に適合しているものとして都道府県知事に届け出た日中サービス支援型指定共同生活援助事業所において、利用者に対して、日中サービス支援型指定共同生活援助等の提供を行った場合に、障害支援区分に応じ、１日につき所定単位数を加算しているか。 | C57: 平18厚告523 別表第15の1の 3の2の注5 | D57: 体制等状況一覧表、当該加算の届出書等
B58: （６）人員配置体制加算（Ⅵ）については、平成18年厚生労働省告示第551号「厚生労働大臣が定める施設基準並びにこども家庭庁長官及び厚生労働大臣が定める施設基準」の十七のイの(2)に定める基準に適合しているものとして都道府県知事に届け出た日中サービス支援型指定共同生活援助事業所において、利用者に対して、日中サービス支援型指定共同生活援助の提供を行った場合に、障害支援区分に応じ、１日につき所定単位数を加算しているか。ただし、（５）を算定している場合は、算定しない。 | C58: 平18厚告523 別表第15の1の 3の2の注6 | D58: 体制等状況一覧表、当該加算の届出書等
B59: （７）人員配置体制加算（Ⅶ）については、平成18年厚生労働省告示第551号「厚生労働大臣が定める施設基準並びにこども家庭庁長官及び厚生労働大臣が定める施設基準」の十七のイの(1)に定める基準に適合しているものとして都道府県知事に届け出た日中サービス支援型指定共同生活援助事業所において、日中を共同生活住居以外の場所で過ごす利用者に対して、日中サービス支援型指定共同生活援助の提供を行った場合に、障害支援区分に応じ、１日につき所定単位数を加算しているか。ただし、（５）又は（６）を算定している場合は、算定しない。 | C59: 平18厚告523 別表第15の1の 3の2の注7 | D59: 体制等状況一覧表、当該加算の届出書等
B60: （８）人員配置体制加算（Ⅷ）については、平成18年厚生労働省告示第551号「厚生労働大臣が定める施設基準並びにこども家庭庁長官及び厚生労働大臣が定める施設基準」の十七のイの(2)に定める基準に適合しているものとして都道府県知事に届け出た日中サービス支援型指定共同生活援助事業所において、日中を共同生活住居以外の場所で過ごす利用者に対して、日中サービス支援型指定共同生活援助の提供を行った場合に、障害支援区分に応じ、１日につき所定単位数を加算しているか。ただし、（５）から（７）までを算定している場合は、算定しない。 | C60: 平18厚告523 別表第15の1の 3の2の注8 | D60: 体制等状況一覧表、当該加算の届出書等
B61: （９）人員配置体制加算（Ⅸ）については、平成18年厚生労働省告示第551号「厚生労働大臣が定める施設基準並びにこども家庭庁長官及び厚生労働大臣が定める施設基準」の十七のイの(1)に定める基準に適合しているものとして都道府県知事に届け出た日中サービス支援型指定共同生活援助事業所において、令和９年３月31日までの間、指定障害福祉サービス基準附則第18条の２第１項又は第２項の規定の適用を受ける利用者に対し、日中サービス支援型指定共同生活援助を行った場合に、１日につき所定単位数（これらの規定に基づく居宅介護又は重度訪問介護の利用について、所要時間が８時間以上である場合にあっては、所定単位数の100分の95に相当する単位数とする。）を加算しているか。ただし、（５）から（８）までを算定している場合は、算定しない。 | C61: 平18厚告523 別表第15の1の 3の2の注9 | D61: 体制等状況一覧表、当該加算の届出書等
B62: （10）人員配置体制加算（Ⅹ）については、平成18年厚生労働省告示第551号「厚生労働大臣が定める施設基準並びにこども家庭庁長官及び厚生労働大臣が定める施設基準」の十七のイの(2)に定める基準に適合しているものとして都道府県知事に届け出た日中サービス支援型指定共同生活援助事業所において、令和９年３月31日までの間、指定障害福祉サービス基準附則第18条の２第１項又は第２項の規定の適用を受ける利用者に対し、日中サービス支援型指定共同生活援助を行った場合に、１日につき所定単位数（これらの規定に基づく居宅介護又は重度訪問介護の利用について、所要時間が８時間以上である場合にあっては、所定単位数の100分の95に相当する単位数とする。）を加算しているか。ただし、（５）から（９）までを算定している場合は、算定しない。 | C62: 平18厚告523 別表第15の1の 3の2の注10 | D62: 体制等状況一覧表、当該加算の届出書等
B63: （11）人員配置体制加算（Ⅺ）については、平成18年厚生労働省告示第551号「厚生労働大臣が定める施設基準並びにこども家庭庁長官及び厚生労働大臣が定める施設基準」の十七のイの(1)に定める基準に適合しているものとして都道府県知事に届け出た日中サービス支援型指定共同生活援助事業所において、令和９年３月31日までの間、指定障害福祉サービス基準附則第18条の２第１項又は第２項の規定の適用を受ける利用者であって、日中を共同生活住居以外の場所で過ごすものに対し、日中サービス支援型指定共同生活援助を行った場合に、１日につき所定単位数（これらの規定に基づく居宅介護又は重度訪問介護の利用について、所要時間が８時間以上である場合にあっては、所定単位数の100分の95に相当する単位数とする。）を加算しているか。ただし、（５）から（10）までを算定している場合は、算定しない。 | C63: 平18厚告523 別表第15の1の 3の2の注11 | D63: 体制等状況一覧表、当該加算の届出書等
B64: （12）人員配置体制加算（Ⅻ）については、平成18年厚生労働省告示第551号「厚生労働大臣が定める施設基準並びにこども家庭庁長官及び厚生労働大臣が定める施設基準」の十七のイの(2)に定める基準に適合しているものとして都道府県知事に届け出た日中サービス支援型指定共同生活援助事業所において、令和９年３月31日までの間、指定障害福祉サービス基準附則第18条の２第１項又は第２項の規定の適用を受ける利用者であって、日中を共同生活住居以外の場所で過ごすものに対し、日中サービス支援型指定共同生活援助を行った場合に、１日につき所定単位数（これらの規定に基づく居宅介護又は重度訪問介護の利用について、所要時間が８時間以上である場合にあっては、所定単位数の100分の95に相当する単位数とする。）を加算しているか。ただし、（５）から（11）までを算定している場合は、算定しない。 | C64: 平18厚告523 別表第15の1の 3の2の注12 | D64: 体制等状況一覧表、当該加算の届出書等
B65: （13）人員配置体制加算（XⅢ）については、平成18年厚生労働省告示第551号「厚生労働大臣が定める施設基準並びにこども家庭庁長官及び厚生労働大臣が定める施設基準」の十八のロの(1)に定める基準に適合しているものとして都道府県知事に届け出た外部サービス利用型指定共同生活援助事業所において、利用者に対し、外部サービス利用型指定共同生活援助を行った場合に、１日につき所定単位数を加算する。 | C65: 平18厚告523 別表第15の1の 3の2の注13 | D65: 体制等状況一覧表、当該加算の届出書等
B66: （14）人員配置体制加算（XⅣ）については、平成18年厚生労働省告示第551号「厚生労働大臣が定める施設基準並びにこども家庭庁長官及び厚生労働大臣が定める施設基準」の十八のロの(2)に定める基準に適合しているものとして都道府県知事に届け出た外部サービス利用型指定共同生活援助事業所において、利用者に対し、外部サービス利用型指定共同生活援助を行った場合に、１日につき所定単位数を加算しているか。ただし、（13）を算定している場合は、算定しない。 | C66: 平18厚告523 別表第15の1の 3の2の注14 | D66: 体制等状況一覧表、当該加算の届出書等
A67: ２の４ 福祉専門職員配置等加算 | B67: （１）福祉専門職員配置等加算（Ⅰ）については、世話人又は生活支援員（世話人等）として常勤で配置されている従業者のうち、社会福祉士、介護福祉士、精神保健福祉士又は公認心理師である従業者の割合が100分の35以上であるものとして都道府県知事に届け出た指定共同生活援助事業所、日中サービス支援型指定共同生活援助事業所又は外部サービス利用型指定共同生活援助事業所（指定共同生活援助事業所等）において、指定共同生活援助、日中サービス支援型指定共同生活援助又は外部サービス利用型指定共同生活援助（指定共同生活援助等）を行った場合に、1日につき所定単位数を加算しているか。 | C67: 平18厚告523 別表第15の1の4の注1 | D67: 体制等状況一覧表、当該加算の届出書等 | E67: 福祉専門職員配置等加算届出書、勤務形態一覧表、資格証写し
B68: （２）福祉専門職員配置等加算（Ⅱ）については、世話人等として常勤で配置されている従業者のうち、社会福祉士、介護福祉士、精神保健福祉士又は公認心理師である従業者の割合が100分の25以上であるものとして都道府県知事に届け出た指定共同生活援助事業所等において、指定共同生活援助等を行った場合に、1日につき所定単位数を加算しているか。ただし、この場合において、（1）の福祉専門職員配置等加算（Ⅰ）を算定している場合は、算定しない。 | C68: 平18厚告523 別表第15の1の4の注2 | D68: 体制等状況一覧表、当該加算の届出書等
B69: （３）福祉専門職員配置等加算（Ⅲ）については、次の①又は②のいずれかに該当するものとして都道府県知事に届け出た指定共同生活援助事業所等において、指定共同生活援助等を行った場合に、1日につき所定単位数を加算しているか。ただし、この場合において、（1）の福祉専門職員配置等加算（Ⅰ）又は（2）の福祉専門職員配置等加算（Ⅱ）を算定している場合は、算定しない。 ① 世話人等とし配置されている従業者のうち、常勤で配置されている従業者の割合が100分の75以上であること。 ② 世話人等として常勤で配置されている従業者のうち、3年以上従事している従業者の割合が100分の30以上であること。 | C69: 平18厚告523 別表第15の1の 4の注3 | D69: 体制等状況一覧表、当該加算の届出書等
A70: ２の４の２ 視覚・聴覚・言語障害者支援体制加算 | B70: （１）視覚・聴覚言語障害者支援体制加算（Ⅰ）については、視覚障害者等である指定共同生活援助等の利用者の数（重度の視覚障害、聴覚障害、言語機能障害又は知的障害のうち2以上の障害を有する利用者については、当該利用者数に2を乗じて得た数とする。⑵について同じ。）が、当該指定共同生活援助等の利用者の数に100分の50を乗じて得た数以上であって、視覚障害者等との意思疎通に関し専門性を有する者として専ら視覚障害者等の生活支援に従事する従業者を、第2の1、第6の1又は第10の1に定める人員配置に加え、常勤換算方法で当該指定共同生活援助等の、利用者の数を40で除して得た数以上配置しているものとして都道府県知事に届け出た指定共同生活援助事業所等において、指定共同生活援助等を行った場合に、1日につき所定単位数を加算しているか。 | C70: 平18厚告523 別表第15の1の 4の2の注1 | D70: 体制等状況一覧表、当該加算の届出書等 | E70: 対象利用者の障害者手帳等、職員の資格・経歴資料
B71: （２）視覚・聴覚言語障害者支援体制加算（Ⅱ）については、視覚障害者等である指定共同生活援助等の利用者の数が、当該指定共同生活援助等の利用者の数に100分の30を乗じて得た数以上であって、視覚障害者等との意思疎通に関し専門性を有する者として専ら視覚障害者等の生活支援に従事する従業者を、第2の1、第6の1又は第10の1に定める人員配置に加え、常勤換算方法で当該指定共同生活援助等の、利用者の数を50で除して得た数以上配置しているものとして都道府県知事に届け出た指定共同生活援助事業所等において、指定共同生活援助等を行った場合に、1日につき所定単位数を加算しているか。 | C71: 平18厚告523 別表第15の1の 4の2の注2 | D71: 体制等状況一覧表、当該加算の届出書等
A72: ２の４の３ 看護職員配置加算 | B72: 指定障害福祉サービス基準に定める員数の従業者に加え、看護職員を常勤換算方法で1以上配置しているものとして都道府県知事に届け出た指定共同生活援助事業所等において、指定共同生活援助等を行った場合に、1日につき所定単位数を加算しているか。 | C72: 平18厚告523 別表第15の1の 4の3の注 | D72: 体制等状況一覧表、当該加算の届出書等 | E72: 看護職員の資格証、勤務形態一覧表
A73: ２の４の４ 高次脳機能障害者支援体制加算 | B73: 平成18年厚生労働省告示第543号「こども家庭庁長官及び厚生労働大臣が定める基準並びに厚生労働大臣が定める基準」の四十に定める基準に適合すると認められた利用者の数が当該指定共同生活援助等の利用者の数に100分の30を乗じて得た数以上であって、平成18年厚生労働省告示第551号「厚生労働大臣が定める施設基準並びにこども家庭庁長官及び厚生労働大臣が定める施設基準」の十六のハに定める基準に適合しているものとして都道府県知事に届け出た指定共同生活援助事業所等において、指定共同生活援助等を行った場合に、１日につき所定単位数を加算しているか。 | C73: 平18厚告523 別表第15の1の 4の4 | D73: 体制等状況一覧表、当該加算の届出書等 | E73: 診断書・意見書等、支援記録
A74: ２の４の５ ピアサポート実施加算 | B74: 次の⑴から⑶までのいずれにも該当するものとして都道府県知事に届け出た指定共同生活援助事業所又は外部サービス利用型指定共同生活援助事業所において、法第４条第１項に規定する障害者（以下この注及び２の４の６において単に「障害者」という。）又は障害者であったと都道府県知事が認める者（以下この注及び２の４の６において「障害者等」という。）である従業者であって、障害者ピアサポート研修修了者であるものが、その経験に基づき、利用者に対して相談援助を行った場合に、当該相談援助を受けた利用者の数に応じ、１月につき所定単位数を加算しているか。 | C74: 平18厚告523 別表第15の1の 4の5 | D74: 体制等状況一覧表、当該加算の届出書等 | E74: ピアサポート研修修了証、職員研修記録、支援記録
B75: ⑴ ３の（３）の自立生活支援加算(Ⅲ)を算定していること。
B76: ⑵ 障害者ピアサポート研修修了者を指定共同生活援助事業所又は外部サービス利用型指定共同生活援助事業所の従業者として２名以上（当該２名以上のうち少なくとも１名は障害者等とする。）配置していること。
B77: ⑶ ⑵に掲げるところにより配置した者のいずれかにより、当該指定共同生活援助事業所又は外部サービス利用型指定共同生活援助事業所の従業者に対し、障害者に対する配慮等に関する研修が年１回以上行われていること。
A78: ２の４の６ 退居後ピアサポート実施加算 | B78: 次の⑴から⑶までのいずれにも該当するものとして都道府県知事に届け出た指定共同生活援助事業所又は外部サービス利用型指定共同生活援助事業所において、障害者等である従業者であって、障害者ピアサポート研修修了者であるものが、その経験に基づき、利用者に対して相談援助を行った場合に、当該相談援助を受けた利用者の数に応じ、１月につき所定単位数を加算しているか。 | C78: 平18厚告523 別表第15の1の 4の6 | D78: 体制等状況一覧表、当該加算の届出書等 | E78: 退居後支援記録、研修修了証
B79: ⑴ ２の２の３の退居後共同生活援助サービス費又は２の２の４の退居後外部サービス利用型共同生活援助サービス費を算定していること。
B80: ⑵ 障害者ピアサポート研修修了者を指定共同生活援助事業所又は外部サービス利用型指定共同生活援助事業所の従業者として２名以上（当該２名以上のうち少なくとも１名は障害者等とする。）配置していること。
B81: ⑶ ⑵に掲げるところにより配置した者のいずれかにより、当該指定共同生活援助事業所又は外部サービス利用型指定共同生活援助事業所の従業者に対し、障害者に対する配慮等に関する研修が年１回以上行われていること。
A82: ２の５ 夜間支援等体制加算 | B82: （１）夜間支援等体制加算（Ⅰ）については、夜勤を行う夜間支援従事者を配置し、利用者に対して夜間及び深夜の時間帯を通じて必要な介護等の支援を提供できる体制を確保しているものとして都道府県知事が認めた指定共同生活援助事業所又は外部サービス利用型指定共同生活援助事業所において、指定共同生活援助又は外部サービス利用型指定共同生活援助を行った場合に、夜間支援対象利用者の数に応じ、1日につき所定単位数を加算しているか。 | C82: 平18厚告523 別表第15の1の 5の注1 | D82: 体制等状況一覧表、当該加算の届出書等 | E82: 夜勤シフト表、夜間支援記録
B83: （２）夜間支援等体制加算（Ⅱ）については、宿直を行う夜間支援従事者を配置し、利用者に対して夜間及び深夜の時間帯を通じて、定時的な居室の巡回や緊急時の支援等を提供できる体制を確保しているものとして都道府県知事が認めた指定共同生活援助事業所又は外部サービス利用型指定共同生活援助事業所において、指定共同生活援助又は外部サービス利用型指定共同生活援助を行った場合に、夜間支援対象利用者の数に応じ、1日につき所定単位数を加算しているか。ただし、（1）の夜間支援等体制加算（Ⅰ）の算定対象となる利用者については、算定しない。 | C83: 平18厚告523 別表第15の1の5の注2 | D83: 体制等状況一覧表、当該加算の届出書等
B84: （３）夜間支援等体制加算（Ⅲ）については、夜間及び深夜の時間帯を通じて、利用者に病状の急変その他の緊急の事態が生じた時に、利用者の呼び出し等に速やかに対応できるよう、常時の連絡体制又は防災体制を確保しているものとして都道府県知事が認めた指定共同生活援助事業所又は外部サービス利用型指定共同生活援助事業所において、指定共同生活援助又は外部サービス利用型指定共同生活援助を行った場合に、1日につき所定単位数を加算しているか。ただし、（1）の夜間支援等体制加算（Ⅰ）又は（2）の夜間支援等体制加算（Ⅱ）の算定対象となる利用者については、算定しない。 | C84: 平18厚告523 別表第15の1の5の注3 | D84: 体制等状況一覧表、当該加算の届出書等
B85: （４）夜間支援等体制加算（Ⅳ）については、夜間支援等体制加算（Ⅰ）を算定している指定共同生活援助事業所又は外部サービス利用型指定共同生活援助事業所であって、更に夜勤を行う夜間支援従業者を配置し、共同生活住居（同加算の算定対象となる夜勤を行う夜間支援従業者を1名配置しているものに限る。以下（５）及び（６）において同じ。）を巡回させることにより、利用者に対して夜間及び深夜の時間帯を通じて必要な介護等の支援を提供できる体制を確保しているものとして都道府県知事が認めた指定共同生活援助事業所又は外部サービス利用型指定共同生活援助事業所において、指定共同生活援助又は外部サービス利用型指定共同生活援助を行った場合に、1日につき所定単位数を加算しているか。 | C85: 平18厚告523 別表第15の1の5の注4 | D85: 体制等状況一覧表、当該加算の届出書等
B86: （５）夜間支援等体制加算（Ⅴ）については、夜間支援等体制加算（Ⅰ）を算定している指定共同生活援助事業所又は外部サービス利用型指定共同生活援助事業所であって、更に夜勤を行う夜間支援従業者を配置し、共同生活住居を巡回させることにより、利用者に対して夜間及び深夜の一部の時間帯を通じて必要な介護等の支援を提供できる体制を確保しているものとして都道府県知事が認めた指定共同生活援助事業所又は外部サービス利用型指定共同生活援助事業所において、指定共同生活援助又は外部サービス利用型指定共同生活援助を行った場合に、夜間支援対象利用者の数に応じ、1日につき所定単位数を加算しているか。ただし、夜間支援等体制加算（Ⅳ）の算定対象となる利用者については、加算しない。 | C86: 平18厚告523 別表第15の1の5の注5 | D86: 体制等状況一覧表、当該加算の届出書等
B87: （６）夜間支援等体制加算（Ⅵ）については、夜間支援等体制加算（Ⅰ）を算定している指定共同生活援助事業所又は外部サービス利用型指定共同生活援助事業所であって、更に夜勤を行う夜間支援従業者を配置し、共同生活住居を巡回させることにより、利用者に対して夜間及び深夜の時間帯を通じて、定期的な居室の巡回や緊急時の支援等を提供できる体制を確保しているものとして都道府県知事が認めた指定共同生活援助事業所又は外部サービス利用型指定共同生活援助事業所において、指定共同生活援助又は外部サービス利用型指定共同生活援助を行った場合に、夜間支援対象利用者の数に応じ、1日につき所定単位数を加算しているか。ただし、夜間支援等体制加算（Ⅳ）又は夜間支援等体制加算（Ⅴ）の算定対象となる利用者については、加算しない。 | C87: 平18厚告523 別表第15の1の5の注6 | D87: 体制等状況一覧表、当該加算の届出書等
A88: ２の５の２ 夜勤職員加配加算 | B88: 第6の1の(4)に定める員数の夜間支援従事者に加え、共同生活住居ごとに、夜勤を行う夜間支援従事者を1以上配置しているものとして都道府県知事に届け出た日中サービス支援型指定共同生活援助事業所において、日中サービス支援型指定共同生活援助を行った場合に、1日につき所定単位数を加算しているか。 | C88: 平18厚告523 別表第15の1の5の2の注 | D88: 体制等状況一覧表、当該加算の届出書等 | E88: 勤務形態一覧表
A89: ２の６ 重度障害者支援加算 | B89: （１）重度障害者支援加算（Ⅰ）については、平成18年厚生労働省告示第551号「厚生労働大臣が定める施設基準並びにこども家庭庁長官及び厚生労働大臣が定める施設基準」の十六のイの(1)に定める基準に適合しているものとして都道府県知事に届け出た指定共同生活援助事業所又は日中サービス支援型指定共同生活援助事業所において、平成18年厚生労働省告示第523号の別表「介護給付費等単位数表」の第8の1の注1に規定する利用者の支援の度合に相当する支援の度合にある者（指定障害福祉サービス基準附則第18条の2第1項又は第2項の規定の適用を受ける利用者を除く。）に対して指定共同生活援助又は日中サービス支援型指定共同生活援助を行った場合に、1日につき所定単位数を加算しているか。 | C89: 平18厚告523 別表第15の1の6の注 平18厚告551 の十六のイの(1) | D89: 体制等状況一覧表、当該加算の届出書等 | E89: 修了証、支援手順書・支援記録
B90: （２）⑴の重度障害者支援加算（Ⅰ）が算定されている指定共同生活援助事業所又は日中サービス支援型指定共同生活援助事業所であって、平成18年厚生労働省告示第551号「厚生労働大臣が定める施設基準並びににこども家庭庁長官及び厚生労働大臣が定める施設基準」の十六のイの(2)に定める基準に適合しているものとして都道府県知事に届け出た指定共同生活援助事業所又は日中サービス支援型指定共同生活援助事業所において、平成１８年告示第556号「厚生労働大臣が定める者並びに子ども家庭庁長官及び厚生労働大臣が定める者」五の二で定める者に対し、指定共同援助又は日中サービス支援型指定共同生活援助を行った場合に、さらに１日につき所定単位数に150単位を加算しているか。 | C90: 平18厚告523 別表第15の1の6の注2 平18厚告551 の十六のイの(2) | D90: 体制等状況一覧表、当該加算の届出書等
B91: （３）重度障害者支援加算（Ⅱ）については、平成18年厚生労働省告示第551号「厚生労働大臣が定める施設基準並びにこども家庭庁長官及び厚生労働大臣が定める施設基準」の十六のイの(2)に定める基準に適合しているものとして都道府県知事に届け出た指定共同生活援助事業所又は日中サービス支援型指定共同生活援助事業所において、平成１８年告示第556号「厚生労働大臣が定める者並びに子ども家庭庁長官及び厚生労働大臣が定める者」五の二で定める者に対して指定共同生活援助又は日中サービス支援型指定共同生活援助を行った場合に、1日につき所定単位数を加算しているか。ただし、重度障害者支援加算（Ⅰ）を算定している場合は、加算しない。 | C91: 平18厚告523 別表第15の1の6の注3 平18厚告551 の十六のイの(2) | D91: 体制等状況一覧表、当該加算の届出書等
B92: （４）重度障害者支援加算（Ⅱ）が算定されている指定共同生活援助事業所又は日中サービス支援型指定共同生活援助事業所であって、平成18年厚生労働省告示第551号「厚生労働大臣が定める施設基準並びにこども家庭庁長官及び厚生労働大臣が定める施設基準」の十六のイの(2)に定める基準に適合しているものとして都道府県知事に届け出た指定共同生活援助事業所又は日中サービス支援型指定共同生活援助事業所において、平成18年告示第556号「厚生労働大臣が定める者並びに子ども家庭庁長官及び厚生労働大臣が定める者」五の二で定める者に対して指定共同生活援助又は日中サービス支援型指定共同生活援助を行った場合に、さらに１日につき所定単位数に150単位を加算しているか。 | C92: 平18厚告523 別表第15の1の6の注4 平18厚告551 の十六のイの(2) | D92: 体制等状況一覧表、当該加算の届出書等
B93: （５） 重度障害者支援加算(Ⅰ)が算定されている指定共同生活援助事業所又は日中サービス支援型指定共同生活援助事業所については、当該加算の算定を開始した日から起算して180日以内の期間について、更に１日につき所定単位数に500単位を加算しているか。 | C93: 平18厚告523 別表第15の1の6の注5 | D93: 体制等状況一覧表、当該加算の届出書等
B94: （６）（２）の加算が算定されている指定共同生活援助事業所又は日中サービス支援型指定共同生活援助事業所については、当該加算の算定を開始した日から起算して180日以内の期間について、更に１日につき所定単位数に200単位を加算しているか。 | C94: 平18厚告523 別表第15の1の6の注6 | D94: 体制等状況一覧表、当該加算の届出書等
B95: （７）重度障害者支援加算(Ⅱ)が算定されている指定共同助事業所について生活援助事業所又は日中サービス支援型指定共同生活援は、当該加算の算定を開始した日から起算して180日以内の期間について、更に１日につき所定単位数に400単位を加算しているか。 | C95: 平18厚告523 別表第15の1の6の注7 | D95: 体制等状況一覧表、当該加算の届出書等
B96: （８）（４）の加算が算定されている指定共同生活援助事業所又は日中サービス支援型指定共同生活援助事業所についでは、当該加算の算定を開始した日から起算して180日以内の期間について、更に１日につき所定単位数に200単位を加算しているか。 | C96: 平18厚告523 別表第15の1の6の注8 | D96: 体制等状況一覧表、当該加算の届出書等
A97: ２の７ 医療的ケア対応支援加算 | B97: 指定障害福祉サービス基準に定める員数の従業者に加え、看護職員を常勤換算方法で1以上配置するものとして都道府県知事に届け出た指定共同生活援助事業所等において、平成18年厚生労働省告示第556号の五の二に規定する厚生労働大臣が定める者に対して指定共同生活援助等を行った場合に、1日につき所定単位数を加算しているか。ただし、重度障害者支援加算（Ⅰ）を算定している場合は、加算しない。 | C97: 平18厚告523 別表第15の1の 7の注 平18厚告556 の五の二 | D97: 体制等状況一覧表、当該加算の届出書等 | E97: 勤務形態一覧表、医療的ケア実施記録、
A98: ２の８ 日中支援加算 | B98: （１）日中支援加算（Ⅰ）については、指定共同生活援助事業所又は外部サービス利用型指定共同生活援助事業所が、高齢又は重度の障害者（65歳以上又は障害支援区分4以上の障害者をいう。）であって日中を共同生活住居の外で過ごすことが困難であると認められる利用者に対して、共同生活援助計画又は外部サービス利用型共同生活援助計画に基づき、日中に支援を行った場合に、日中支援対象利用者の数に応じ、1日につき所定単位数を加算しているか。ただし、指定共同生活援助事業所にあっては、日曜日、土曜日又は国民の祝日に関する法律（昭和23年法律第178号）に規定する休日に支援を行った場合については、算定しない。 | C98: 平18厚告523 別表第15の1の 8の注1 | D98: 体制等状況一覧表、当該加算の届出書等 | E98: 日中支援記録、通所・就労先の欠席記録
B99: （２）日中支援加算（Ⅱ）については、指定共同生活援助事業所、日中サービス支援型指定共同生活援助事業所（区分2以下に該当する利用者に限る。）又は外部サービス利用型指定共同生活援助事業所が、生活介護等利用者が心身の状況等によりこれらのサービスを利用することができないとき又は就労することができないときに、当該利用者に対して日中に支援を行った場合に、1日につき所定単位数を加算しているか。 | C99: 平18厚告523 別表第15の1の 8の注2 | D99: 体制等状況一覧表、当該加算の届出書等
A100: ２の９ 集中的支援加算 | B100: （１）集中的支援加算（Ⅰ）については、平成18年厚生労働省告示第556号「厚生労働大臣が定める者並びにこども家庭庁長官及び厚生労働大臣が定める者」の一の二に定める者の状態が悪化した場合において、広域的支援人材を指定共同生活援助事業所等に訪問させ、又はテレビ電話装置等を活用して、当該広域的支援人材が中心となって集中的に支援を行ったときに、当該支援を開始した日の属する月から起算して３月以内の期間に限り１月に４回を限度として所定単位数を加算しているか。 | C100: 平18厚告523 別表第15の１の９の注１ | D100: 体制等状況一覧表、当該加算の届出書等 | E100: 外部専門家等の助言記録、集中的支援記録
B101: （２）集中的支援加算（Ⅱ）については、平成18年厚生労働省告示第556号「厚生労働大臣が定める者並びにこども家庭庁長官及び厚生労働大臣が定める者」の一の二に定める者の状態が悪化した場合において、強度行動障害を有する者への集中的な支援を提供できる体制を確保しているものとして都道府県知事が認めた指定共同生活援助事業所等が、集中的な支援が必要な利用者を他の指定障害福祉サービスを行う事業所又は指定障害者支援施設等から受け入れ、当該利用者に対して集中的な支援を実施した場合に、当該支援を開始した日の属する月から起算して３月以内期間に限り１日につき所定単位数を加算しているか。 | C101: 平18厚告523 別表第15の１の９の注２ | D101: 体制等状況一覧表、当該加算の届出書等
A102: ３ 自立生活支援加算 | B102: （１）自立生活支援加算（Ⅰ）については、居宅における単身等での生活を本人が希望し、かつ、単身等での生活が可能であると見込まれる利用者（利用期間が１月を超えると見込まれる利用者に限る。注３を除き、以下この２において同じ。）の退居に向けて、指定共同生活援助事業所又は外部サービス利用型共同生活援助事業所の従業者が、共同生活援助計画又は外部サービス利用型共同生活援助計画（以下この注１において単に「計画」という。）を見直した上で、当該利用者に対して、退居後の生活について相談援助を行い、かつ当該利用者が退居後に生活する居宅を訪問し、当該利用者及びその家族等に対して退居後の障害福祉サービスその他の保健医療サービス又は福祉サービスについて相談援助及び連絡調整を行った場合に、計画の見直しを行った日の属する月から起算して６月以内の期間（当該利用者が退居した場合には、退居した日の属する月までの期間）に限り、１月に１回を限度として所定単位数を加算しているか。ただし、当該利用者が退居後に他の社会福祉施設等に入所することを希望している場合にあっては、算定していないか。 | C102: 平18厚告523 別表第15の2の 注1 | D102: 体制等状況一覧表、当該加算の届出書等 | E102: 個別支援計画、相談援助記録
...
